exp-6/fir_pl_direct.sv
module fir_direct_pipeline #(parameter TAPS = 100)(
    input  logic clk, rst,
    input  logic signed [15:0] x,
    input  logic signed [15:0] coeff [0:TAPS-1],
    output logic signed [47:0] y // 48-bit for internal precision
);
    logic signed [15:0] shift_reg [0:TAPS-1];
    logic signed [31:0] mult_reg [0:TAPS-1];
    logic signed [47:0] acc_reg;
    
    // Shifting
    always_ff @(posedge clk) begin
        if (rst) begin
            for (int i=0; i<TAPS; i++) shift_reg[i] <= 0;
        end else begin
            shift_reg[0] <= x;
            for (int i=1; i<TAPS; i++) shift_reg[i] <= shift_reg[i-1];
        end
    end

    // Multiplication
    always_ff @(posedge clk) begin
        if (rst) begin
            for (int i=0; i<TAPS; i++) mult_reg[i] <= 0;
        end else begin
            for (int i=0; i<TAPS; i++) mult_reg[i] <= shift_reg[i] * coeff[i];
        end
    end

    // Accumulation
    always_ff @(posedge clk) begin
        if (rst) begin
            acc_reg <= 0;
            y <= 0;
        end else begin
            acc_reg = 0;
            for (int i=0; i<TAPS; i++) acc_reg += mult_reg[i];
            y <= acc_reg;
        end
    end
endmodule

exp-6/tb_pip_dir.sv
module tb_direct;
    reg clk=0, rst;
    reg signed [15:0] x1, x2, x3;
    wire signed [47:0] y1, y2, y3;
    reg signed [15:0] coeff[0:99], s950[0:1052], s1100[0:909], s2000[0:499];
    integer f1, f2, f3;
    integer i;

    fir_direct_pipeline #(100) dut1(.clk(clk), .rst(rst), .x(x1), .coeff(coeff), .y(y1));
    fir_direct_pipeline #(100) dut2(.clk(clk), .rst(rst), .x(x2), .coeff(coeff), .y(y2));
    fir_direct_pipeline #(100) dut3(.clk(clk), .rst(rst), .x(x3), .coeff(coeff), .y(y3));

    always #1 clk = ~clk;
    
    initial begin
        $dumpfile("wave_direct.vcd"); 
        $dumpvars(0, tb_direct);
    end
    
    initial begin
        // Fix: Changed variable names to match declarations
        $readmemb("fc_quantized_2_14.txt", coeff);  // was 'h', now 'coeff'
        $readmemb("q_2_14_950.txt", s950);
        $readmemb("q_2_14_1100.txt", s1100);
        $readmemb("q_2_14_2000.txt", s2000);
        
        f1 = $fopen("out_direct_950.txt", "w");
        f2 = $fopen("out_direct_1100.txt", "w");
        f3 = $fopen("out_direct_2000.txt", "w");
        
        rst = 1; 
        x1 = 0; x2 = 0; x3 = 0;
        #10 rst = 0;
        
        // Add the main simulation loop
        for(i = 0; i < 500; i++) begin  // Run for 500 samples (smallest array size)
            @(posedge clk);
            
            // Apply inputs (with bounds checking)
            if(i <= 1052) x1 <= s950[i];
            if(i <= 909)  x2 <= s1100[i];
            if(i <= 499)  x3 <= s2000[i];
            
        end
        
        $fclose(f1); 
        $fclose(f2); 
        $fclose(f3);
        $finish;
    end
endmodule

exp-6/tb_pip_dir.vcd
$date
	Tue Apr 21 12:39:08 2026
$end
$version
	Icarus Verilog
$end
$timescale
	1s
$end
$scope module tb_direct $end
$var wire 48 ! y3 [47:0] $end
$var wire 48 " y2 [47:0] $end
$var wire 48 # y1 [47:0] $end
$var reg 1 $ clk $end
$var reg 1 % rst $end
$var reg 16 & x1 [15:0] $end
$var reg 16 ' x2 [15:0] $end
$var reg 16 ( x3 [15:0] $end
$var integer 32 ) f1 [31:0] $end
$var integer 32 * f2 [31:0] $end
$var integer 32 + f3 [31:0] $end
$var integer 32 , i [31:0] $end
$scope module dut1 $end
$var wire 1 $ clk $end
$var wire 1 % rst $end
$var wire 16 - x [15:0] $end
$var parameter 32 . TAPS $end
$var reg 48 / acc_reg [47:0] $end
$var reg 48 0 y [47:0] $end
$scope begin $ivl_for_loop0 $end
$var integer 32 1 i [31:0] $end
$upscope $end
$scope begin $ivl_for_loop1 $end
$var integer 32 2 i [31:0] $end
$upscope $end
$scope begin $ivl_for_loop2 $end
$var integer 32 3 i [31:0] $end
$upscope $end
$scope begin $ivl_for_loop3 $end
$var integer 32 4 i [31:0] $end
$upscope $end
$scope begin $ivl_for_loop4 $end
$var integer 32 5 i [31:0] $end
$upscope $end
$upscope $end
$scope module dut2 $end
$var wire 1 $ clk $end
$var wire 1 % rst $end
$var wire 16 6 x [15:0] $end
$var parameter 32 7 TAPS $end
$var reg 48 8 acc_reg [47:0] $end
$var reg 48 9 y [47:0] $end
$scope begin $ivl_for_loop0 $end
$var integer 32 : i [31:0] $end
$upscope $end
$scope begin $ivl_for_loop1 $end
$var integer 32 ; i [31:0] $end
$upscope $end
$scope begin $ivl_for_loop2 $end
$var integer 32 < i [31:0] $end
$upscope $end
$scope begin $ivl_for_loop3 $end
$var integer 32 = i [31:0] $end
$upscope $end
$scope begin $ivl_for_loop4 $end
$var integer 32 > i [31:0] $end
$upscope $end
$upscope $end
$scope module dut3 $end
$var wire 1 $ clk $end
$var wire 1 % rst $end
$var wire 16 ? x [15:0] $end
$var parameter 32 @ TAPS $end
$var reg 48 A acc_reg [47:0] $end
$var reg 48 B y [47:0] $end
$scope begin $ivl_for_loop0 $end
$var integer 32 C i [31:0] $end
$upscope $end
$scope begin $ivl_for_loop1 $end
$var integer 32 D i [31:0] $end
$upscope $end
$scope begin $ivl_for_loop2 $end
$var integer 32 E i [31:0] $end
$upscope $end
$scope begin $ivl_for_loop3 $end
$var integer 32 F i [31:0] $end
$upscope $end
$scope begin $ivl_for_loop4 $end
$var integer 32 G i [31:0] $end
$upscope $end
$upscope $end
$upscope $end
$enddefinitions $end
$comment Show the parameter values. $end
$dumpall
b1100100 @
b1100100 7
b1100100 .
$end
#0
$dumpvars
b0 G
b0 F
b0 E
b0 D
b0 C
bx B
bx A
b0 ?
b0 >
b0 =
b0 <
b0 ;
b0 :
bx 9
bx 8
b0 6
b0 5
b0 4
b0 3
b0 2
b0 1
bx 0
bx /
b0 -
bx ,
b10000000000000000000000000000101 +
b10000000000000000000000000000100 *
b10000000000000000000000000000011 )
b0 (
b0 '
b0 &
1%
0$
bx #
bx "
bx !
$end
#1
b0 #
b0 0
b0 /
b0 "
b0 9
b0 8
b0 !
b0 B
b0 A
b1100100 E
b1100100 C
b1100100 <
b1100100 :
b1100100 3
b1100100 1
1$
#2
0$
#3
b1100100 E
b1100100 C
b1100100 <
b1100100 :
b1100100 3
b1100100 1
1$
#4
0$
#5
b1100100 E
b1100100 C
b1100100 <
b1100100 :
b1100100 3
b1100100 1
1$
#6
0$
#7
b1100100 E
b1100100 C
b1100100 <
b1100100 :
b1100100 3
b1100100 1
1$
#8
0$
#9
b1100100 E
b1100100 C
b1100100 <
b1100100 :
b1100100 3
b1100100 1
1$
#10
0$
b0 ,
0%
#11
b1100100 F
b1100100 D
b1100100 =
b1100100 ;
b1100100 4
b1100100 2
b1100100 5
b1100100 >
b1100100 G
b1 ,
1$
#12
0$
#13
b11110011011110 (
b11110011011110 ?
b10100011001100 '
b10100011001100 6
b10001111111001 &
b10001111111001 -
b1100100 F
b1100100 D
b1100100 =
b1100100 ;
b1100100 4
b1100100 2
b1100100 5
b1100100 >
b1100100 G
b10 ,
1$
#14
0$
#15
b10010110011110 (
b10010110011110 ?
b11111011011110 '
b11111011011110 6
b11101110000001 &
b11101110000001 -
b1100100 F
b1100100 D
b1100100 =
b1100100 ;
b1100100 4
b1100100 2
b1100100 5
b1100100 >
b1100100 G
b11 ,
1$
#16
0$
#17
b1101101001100010 (
b1101101001100010 ?
b11100000010101 '
b11100000010101 6
b11111001110101 &
b11111001110101 -
b1100100 F
b1100100 D
b1100100 =
b1100100 ;
b1100100 4
b1100100 2
b1100100 5
b1100100 >
b1100100 G
b100 ,
1$
#18
0$
#19
b111111111111111111111111111111111001010000010101 #
b111111111111111111111111111111111001010000010101 0
b111111111111111111111111111111111000010110011100 "
b111111111111111111111111111111111000010110011100 9
b111111111111111111111111111111110100100101100110 !
b111111111111111111111111111111110100100101100110 B
b1100001100100010 (
b1100001100100010 ?
b1011110001111 '
b1011110001111 6
b10101111010000 &
b10101111010000 -
b1100100 F
b1100100 D
b1100100 =
b1100100 ;
b1100100 4
b1100100 2
b111111111111111111111111111111111001010000010101 /
b1100100 5
b111111111111111111111111111111111000010110011100 8
b1100100 >
b111111111111111111111111111111110100100101100110 A
b1100100 G
b101 ,
1$
#20
0$
#21
b111111111111111111111111111111100101000110101110 #
b111111111111111111111111111111100101000110101110 0
b111111111111111111111111111111100010010111010010 "
b111111111111111111111111111111100010010111010010 9
b111111111111111111111111111111011110010100010100 !
b111111111111111111111111111111011110010100010100 B
b0 (
b0 ?
b1110110000111001 '
b1110110000111001 6
b101000000011 &
b101000000011 -
b1100100 F
b1100100 D
b1100100 =
b1100100 ;
b1100100 4
b1100100 2
b1100100 5
b1100100 >
b1100100 G
b110 ,
b111111111111111111111111111111011110010100010100 A
b111111111111111111111111111111100010010111010010 8
b111111111111111111111111111111100101000110101110 /
1$
#22
0$
#23
b111111111111111111111111111111000110000001011001 #
b111111111111111111111111111111000110000001011001 0
b111111111111111111111111111111000011000010000011 "
b111111111111111111111111111111000011000010000011 9
b111111111111111111111111111111010100010110111010 !
b111111111111111111111111111111010100010110111010 B
b11110011011110 (
b11110011011110 ?
b1100100111110111 '
b1100100111110111 6
b1110010011000000 &
b1110010011000000 -
b1100100 F
b1100100 D
b1100100 =
b1100100 ;
b1100100 4
b1100100 2
b1100100 5
b1100100 >
b1100100 G
b111 ,
b111111111111111111111111111111010100010110111010 A
b111111111111111111111111111111000011000010000011 8
b111111111111111111111111111111000110000001011001 /
1$
#24
0$
#25
b111111111111111111111111111110101001000000001100 #
b111111111111111111111111111110101001000000001100 0
b111111111111111111111111111110101011010010010010 "
b111111111111111111111111111110101011010010010010 9
b111111111111111111111111111111101000010001101110 !
b111111111111111111111111111111101000010001101110 B
b10010110011110 (
b10010110011110 ?
b1100000010000001 '
b1100000010000001 6
b1100100011101010 &
b1100100011101010 -
b1100100 F
b1100100 D
b1100100 =
b1100100 ;
b1100100 4
b1100100 2
b1100100 5
b1100100 >
b1100100 G
b1000 ,
b111111111111111111111111111111101000010001101110 A
b111111111111111111111111111110101011010010010010 8
b111111111111111111111111111110101001000000001100 /
1$
#26
0$
#27
b111111111111111111111111111110100011010100110111 #
b111111111111111111111111111110100011010100110111 0
b111111111111111111111111111110110010110001011011 "
b111111111111111111111111111110110010110001011011 9
b10001100100010110 !
b10001100100010110 B
b1101101001100010 (
b1101101001100010 ?
b1101010000110000 '
b1101010000110000 6
b1100000000100000 &
b1100000000100000 -
b1100100 F
b1100100 D
b1100100 =
b1100100 ;
b1100100 4
b1100100 2
b1100100 5
b1100100 >
b1100100 G
b1001 ,
b10001100100010110 A
b111111111111111111111111111110110010110001011011 8
b111111111111111111111111111110100011010100110111 /
1$
#28
0$
#29
b111111111111111111111111111111000110101100010100 #
b111111111111111111111111111111000110101100010100 0
b111111111111111111111111111111100111111001110011 "
b111111111111111111111111111111100111111001110011 9
b110001110011000010 !
b110001110011000010 B
b1100001100100010 (
b1100001100100010 ?
b1111101111111011 '
b1111101111111011 6
b1100110101101110 &
b1100110101101110 -
b1100100 F
b1100100 D
b1100100 =
b1100100 ;
b1100100 4
b1100100 2
b1100100 5
b1100100 >
b1100100 G
b1010 ,
b110001110011000010 A
b111111111111111111111111111111100111111001110011 8
b111111111111111111111111111111000110101100010100 /
1$
#30
0$
#31
b10110100110111111 #
b10110100110111111 0
b1000100001001000000 "
b1000100001001000000 9
b110111000011100000 !
b110111000011100000 B
b0 (
b0 ?
b10010110011110 '
b10010110011110 6
b1110110000111001 &
b1110110000111001 -
b1100100 F
b1100100 D
b1100100 =
b1100100 ;
b1100100 4
b1100100 2
b1100100 5
b1100100 >
b1100100 G
b1011 ,
b110111000011100000 A
b1000100001001000000 8
b10110100110111111 /
1$
#32
0$
#33
b10000000011011101000 #
b10000000011011101000 0
b10100111010110010111 "
b10100111010110010111 9
b101001010010101000 !
b101001010010101000 B
b11110011011110 (
b11110011011110 ?
b11110111111101 '
b11110111111101 6
b1000111011011 &
b1000111011011 -
b1100100 F
b1100100 D
b1100100 =
b1100100 ;
b1100100 4
b1100100 2
b1100100 5
b1100100 >
b1100100 G
b1100 ,
b101001010010101000 A
b10100111010110010111 8
b10000000011011101000 /
1$
#34
0$
#35
b11011101010100000111 #
b11011101010100000111 0
b11100001011100100000 "
b11100001011100100000 9
b10111101110010010 !
b10111101110010010 B
b10010110011110 (
b10010110011110 ?
b11100111101001 '
b11100111101001 6
b11000101010000 &
b11000101010000 -
b1100100 F
b1100100 D
b1100100 =
b1100100 ;
b1100100 4
b1100100 2
b1100100 5
b1100100 >
b1100100 G
b1101 ,
b10111101110010010 A
b11100001011100100000 8
b11011101010100000111 /
1$
#36
0$
#37
b11111011001001011110 #
b11111011001001011110 0
b11000011010111011100 "
b11000011010111011100 9
b111111111111111111111111111111111100001100100010 !
b111111111111111111111111111111111100001100100010 B
b1101101001100010 (
b1101101001100010 ?
b1101101000000 '
b1101101000000 6
b11111110110111 &
b11111110110111 -
b1100100 F
b1100100 D
b1100100 =
b1100100 ;
b1100100 4
b1100100 2
b1100100 5
b1100100 >
b1100100 G
b1110 ,
b111111111111111111111111111111111100001100100010 A
b11000011010111011100 8
b11111011001001011110 /
1$
#38
0$
#39
b10110010011000110010 #
b10110010011000110010 0
b111001110001010111 "
b111001110001010111 9
b111111111111111111111111111111001011010010111110 !
b111111111111111111111111111111001011010010111110 B
b1100001100100010 (
b1100001100100010 ?
b1111000000010101 '
b1111000000010101 6
b11100000010101 &
b11100000010101 -
b1100100 F
b1100100 D
b1100100 =
b1100100 ;
b1100100 4
b1100100 2
b1100100 5
b1100100 >
b1100100 G
b1111 ,
b111111111111111111111111111111001011010010111110 A
b111001110001010111 8
b10110010011000110010 /
1$
#40
0$
#41
b111111111111111111111111111111111100101110000001 #
b111111111111111111111111111111111100101110000001 0
b111111111111111111111111111101100000000111011110 "
b111111111111111111111111111101100000000111011110 9
b111111111111111111111111111110010011010110000000 !
b111111111111111111111111111110010011010110000000 B
b0 (
b0 ?
b1100110000111001 '
b1100110000111001 6
b1110100001110 &
b1110100001110 -
b1100100 F
b1100100 D
b1100100 =
b1100100 ;
b1100100 4
b1100100 2
b1100100 5
b1100100 >
b1100100 G
b10000 ,
b111111111111111111111111111110010011010110000000 A
b111111111111111111111111111101100000000111011110 8
b111111111111111111111111111111111100101110000001 /
1$
#42
0$
#43
b111111111111111111111111111100000110111111000001 #
b111111111111111111111111111100000110111111000001 0
b111111111111111111111111111010000101111001110010 "
b111111111111111111111111111010000101111001110010 9
b111111111111111111111111111110000011001110101010 !
b111111111111111111111111111110000011001110101010 B
b11110011011110 (
b11110011011110 ?
b1100000000100000 '
b1100000000100000 6
b1111011111111011 &
b1111011111111011 -
b1100100 F
b1100100 D
b1100100 =
b1100100 ;
b1100100 4
b1100100 2
b1100100 5
b1100100 >
b1100100 G
b10001 ,
b111111111111111111111111111110000011001110101010 A
b111111111111111111111111111010000101111001110010 8
b111111111111111111111111111100000110111111000001 /
1$
#44
0$
#45
b111111111111111111111111111000101100111010011101 #
b111111111111111111111111111000101100111010011101 0
b111111111111111111111111111000010110111011110001 "
b111111111111111111111111111000010110111011110001 9
b111111111111111111111111111110111100101000101000 !
b111111111111111111111111111110111100101000101000 B
b10010110011110 (
b10010110011110 ?
b1101000101011001 '
b1101000101011001 6
b1101010110101101 &
b1101010110101101 -
b1100100 F
b1100100 D
b1100100 =
b1100100 ;
b1100100 4
b1100100 2
b1100100 5
b1100100 >
b1100100 G
b10010 ,
b111111111111111111111111111110111100101000101000 A
b111111111111111111111111111000010110111011110001 8
b111111111111111111111111111000101100111010011101 /
1$
#46
0$
#47
b111111111111111111111111110111011011101001011010 #
b111111111111111111111111110111011011101001011010 0
b111111111111111111111111111001101100011000110001 "
b111111111111111111111111111001101100011000110001 9
b101001010010101000 !
b101001010010101000 B
b1101101001100010 (
b1101101001100010 ?
b1111011111111011 '
b1111011111111011 6
b1100001000000011 &
b1100001000000011 -
b1100100 F
b1100100 D
b1100100 =
b1100100 ;
b1100100 4
b1100100 2
b1100100 5
b1100100 >
b1100100 G
b10011 ,
b101001010010101000 A
b111111111111111111111111111001101100011000110001 8
b111111111111111111111111110111011011101001011010 /
1$
#48
0$
#49
b111111111111111111111111111001100101001111111110 #
b111111111111111111111111111001100101001111111110 0
b111111111111111111111111111110011100001111000001 "
b111111111111111111111111111110011100001111000001 9
b10001110010101101100 !
b10001110010101101100 B
b1100001100100010 (
b1100001100100010 ?
b10001001001011 '
b10001001001011 6
b1100001111001001 &
b1100001111001001 -
b1100100 F
b1100100 D
b1100100 =
b1100100 ;
b1100100 4
b1100100 2
b1100100 5
b1100100 >
b1100100 G
b10100 ,
b10001110010101101100 A
b111111111111111111111111111110011100001111000001 8
b111111111111111111111111111001100101001111111110 /
1$
#50
0$
#51
b111111111111111111111111111111010010010101110100 #
b111111111111111111111111111111010010010101110100 0
b101011010110000101101 "
b101011010110000101101 9
b10111111001111010000 !
b10111111001111010000 B
b0 (
b0 ?
b11110011011110 '
b11110011011110 6
b1101101001100010 &
b1101101001100010 -
b1100100 F
b1100100 D
b1100100 =
b1100100 ;
b1100100 4
b1100100 2
b1100100 5
b1100100 >
b1100100 G
b10101 ,
b10111111001111010000 A
b101011010110000101101 8
b111111111111111111111111111111010010010101110100 /
1$
#52
0$
#53
b111000100001000101000 #
b111000100001000101000 0
b1011111110101101111011 "
b1011111110101101111011 9
b10101101101010111010 !
b10101101101010111010 B
b11110011011110 (
b11110011011110 ?
b11101110000001 '
b11101110000001 6
b1111110111111101 &
b1111110111111101 -
b1100100 F
b1100100 D
b1100100 =
b1100100 ;
b1100100 4
b1100100 2
b1100100 5
b1100100 >
b1100100 G
b10110 ,
b10101101101010111010 A
b1011111110101101111011 8
b111000100001000101000 /
1$
#54
0$
#55
b1110000011001110111110 #
b1110000011001110111110 0
b1110111010100110110101 "
b1110111010100110110101 9
b1011110111001001000 !
b1011110111001001000 B
b10010110011110 (
b10010110011110 ?
b1111011010101 '
b1111011010101 6
b10001001001011 &
b10001001001011 -
b1100100 F
b1100100 D
b1100100 =
b1100100 ;
b1100100 4
b1100100 2
b1100100 5
b1100100 >
b1100100 G
b10111 ,
b1011110111001001000 A
b1110111010100110110101 8
b1110000011001110111110 /
1$
#56
0$
#57
b10000111000010011110110 #
b10000111000010011110110 0
b1011110011010110011010 "
b1011110011010110011010 9
b111111111111111111111111111111011001000011110110 !
b111111111111111111111111111111011001000011110110 B
b1101101001100010 (
b1101101001100010 ?
b1111010000000010 '
b1111010000000010 6
b11101010111100 &
b11101010111100 -
b1100100 F
b1100100 D
b1100100 =
b1100100 ;
b1100100 4
b1100100 2
b1100100 5
b1100100 >
b1100100 G
b11000 ,
b111111111111111111111111111111011001000011110110 A
b1011110011010110011010 8
b10000111000010011110110 /
1$
#58
0$
#59
b1101000110010011111011 #
b1101000110010011111011 0
b10011001010100000110 "
b10011001010100000110 9
b111111111111111111111111111100110101010110010110 !
b111111111111111111111111111100110101010110010110 B
b1100001100100010 (
b1100001100100010 ?
b1100111010110000 '
b1100111010110000 6
b11111011011110 &
b11111011011110 -
b1100100 F
b1100100 D
b1100100 =
b1100100 ;
b1100100 4
b1100100 2
b1100100 5
b1100100 >
b1100100 G
b11001 ,
b111111111111111111111111111100110101010110010110 A
b10011001010100000110 8
b1101000110010011111011 /
1$
#60
0$
#61
b10100010100000000100 #
b10100010100000000100 0
b111111111111111111111111110101010101101110101100 "
b111111111111111111111111110101010101101110101100 9
b111111111111111111111111111010110110001110100010 !
b111111111111111111111111111010110110001110100010 B
b0 (
b0 ?
b1100000000000000 '
b1100000000000000 6
b10110101000001 &
b10110101000001 -
b1100100 F
b1100100 D
b1100100 =
b1100100 ;
b1100100 4
b1100100 2
b1100100 5
b1100100 >
b1100100 G
b11010 ,
b111111111111111111111111111010110110001110100010 A
b111111111111111111111111110101010101101110101100 8
b10100010100000000100 /
1$
#62
0$
#63
b111111111111111111111111110100000010111000111001 #
b111111111111111111111111110100000010111000111001 0
b111111111111111111111111101001101101011101110000 "
b111111111111111111111111101001101101011101110000 9
b111111111111111111111111111010110011111000000100 !
b111111111111111111111111111010110011111000000100 B
b11110011011110 (
b11110011011110 ?
b1100111010110000 '
b1100111010110000 6
b101111111110 &
b101111111110 -
b1100100 F
b1100100 D
b1100100 =
b1100100 ;
b1100100 4
b1100100 2
b1100100 5
b1100100 >
b1100100 G
b11011 ,
b111111111111111111111111111010110011111000000100 A
b111111111111111111111111101001101101011101110000 8
b111111111111111111111111110100000010111000111001 /
1$
#64
0$
#65
b111111111111111111111111100110111100100000110101 #
b111111111111111111111111100110111100100000110101 0
b111111111111111111111111100101001101000100001101 "
b111111111111111111111111100101001101000100001101 9
b111111111111111111111111111101010011110010000110 !
b111111111111111111111111111101010011110010000110 B
b10010110011110 (
b10010110011110 ?
b1111010000000010 '
b1111010000000010 6
b1110011010010101 &
b1110011010010101 -
b1100100 F
b1100100 D
b1100100 =
b1100100 ;
b1100100 4
b1100100 2
b1100100 5
b1100100 >
b1100100 G
b11100 ,
b111111111111111111111111111101010011110010000110 A
b111111111111111111111111100101001101000100001101 8
b111111111111111111111111100110111100100000110101 /
1$
#66
0$
#67
b111111111111111111111111100001010110011111010100 #
b111111111111111111111111100001010110011111010100 0
b111111111111111111111111101011101011101000110000 "
b111111111111111111111111101011101011101000110000 9
b1100100001001100110 !
b1100100001001100110 B
b1101101001100010 (
b1101101001100010 ?
b1111011010101 '
b1111011010101 6
b1100100111110111 &
b1100100111110111 -
b1100100 F
b1100100 D
b1100100 =
b1100100 ;
b1100100 4
b1100100 2
b1100100 5
b1100100 >
b1100100 G
b11101 ,
b1100100001001100110 A
b111111111111111111111111101011101011101000110000 8
b111111111111111111111111100001010110011111010100 /
1$
#68
0$
#69
b111111111111111111111111100111100111110001010001 #
b111111111111111111111111100111100111110001010001 0
b111111111111111111111111111100111010110101001001 "
b111111111111111111111111111100111010110101001001 9
b101110011000100000110 !
b101110011000100000110 B
b1100001100100010 (
b1100001100100010 ?
b11101110000001 '
b11101110000001 6
b1100000000001000 &
b1100000000001000 -
b1100100 F
b1100100 D
b1100100 =
b1100100 ;
b1100100 4
b1100100 2
b1100100 5
b1100100 >
b1100100 G
b11110 ,
b101110011000100000110 A
b111111111111111111111111111100111010110101001001 8
b111111111111111111111111100111100111110001010001 /
1$
#70
0$
#71
b111111111111111111111111111001111110011101100010 #
b111111111111111111111111111001111110011101100010 0
b10011101101101100000111 "
b10011101101101100000111 9
b1000001100110100001100 !
b1000001100110100001100 B
b0 (
b0 ?
b11110011011110 '
b11110011011110 6
b1100110000111001 &
b1100110000111001 -
b1100100 F
b1100100 D
b1100100 =
b1100100 ;
b1100100 4
b1100100 2
b1100100 5
b1100100 >
b1100100 G
b11111 ,
b1000001100110100001100 A
b10011101101101100000111 8
b111111111111111111111111111001111110011101100010 /
1$
#72
0$
#73
b10011010111011111111011 #
b10011010111011111111011 0
b100111000100111110010110 "
b100111000100111110010110 9
b111101001101011100000 !
b111101001101011100000 B
b11110011011110 (
b11110011011110 ?
b10001001001011 '
b10001001001011 6
b1110101001010010 &
b1110101001010010 -
b1100100 F
b1100100 D
b1100100 =
b1100100 ;
b1100100 4
b1100100 2
b1100100 5
b1100100 >
b1100100 G
b100000 ,
b111101001101011100000 A
b100111000100111110010110 8
b10011010111011111111011 /
1$
#74
0$
#75
b101010011100111010001100 #
b101010011100111010001100 0
b101101011111000101110001 "
b101101011111000101110001 9
b11111101010110001010 !
b11111101010110001010 B
b10010110011110 (
b10010110011110 ?
b1111011111111011 '
b1111011111111011 6
b111111101011 &
b111111101011 -
b1100100 F
b1100100 D
b1100100 =
b1100100 ;
b1100100 4
b1100100 2
b1100100 5
b1100100 >
b1100100 G
b100001 ,
b11111101010110001010 A
b101101011111000101110001 8
b101010011100111010001100 /
1$
#76
0$
#77
b110100101011100111110001 #
b110100101011100111110001 0
b100001000101101011010010 "
b100001000101101011010010 9
b111111111111111111111111111101111000101101101110 !
b111111111111111111111111111101111000101101101110 B
b1101101001100010 (
b1101101001100010 ?
b1101000101011001 '
b1101000101011001 6
b11000000000010 &
b11000000000010 -
b1100100 F
b1100100 D
b1100100 =
b1100100 ;
b1100100 4
b1100100 2
b1100100 5
b1100100 >
b1100100 G
b100010 ,
b111111111111111111111111111101111000101101101110 A
b100001000101101011010010 8
b110100101011100111110001 /
1$
#78
0$
#79
b101010101100001001010010 #
b101010101100001001010010 0
b11001110111110001001 "
b11001110111110001001 9
b111111111111111111111111110111010110001101000100 !
b111111111111111111111111110111010110001101000100 B
b1100001100100010 (
b1100001100100010 ?
b1100000000100000 '
b1100000000100000 6
b11111101111111 &
b11111101111111 -
b1100100 F
b1100100 D
b1100100 =
b1100100 ;
b1100100 4
b1100100 2
b1100100 5
b1100100 >
b1100100 G
b100011 ,
b111111111111111111111111110111010110001101000100 A
b11001110111110001001 8
b101010101100001001010010 /
1$
#80
0$
#81
b1100001011000100001110 #
b1100001011000100001110 0
b111111111111111111111111011101010111000111101000 "
b111111111111111111111111011101010111000111101000 9
b111111111111111111111111110011000001001000101000 !
b111111111111111111111111110011000001001000101000 B
b0 (
b0 ?
b1100110000111001 '
b1100110000111001 6
b11100100000110 &
b11100100000110 -
b1100100 F
b1100100 D
b1100100 =
b1100100 ;
b1100100 4
b1100100 2
b1100100 5
b1100100 >
b1100100 G
b100100 ,
b111111111111111111111111110011000001001000101000 A
b111111111111111111111111011101010111000111101000 8
b1100001011000100001110 /
1$
#82
0$
#83
b111111111111111111111111100001101001011011100011 #
b111111111111111111111111100001101001011011100011 0
b111111111111111111111110111110100010101110010000 "
b111111111111111111111110111110100010101110010000 9
b111111111111111111111111110011011011110000111010 !
b111111111111111111111111110011011011110000111010 B
b11110011011110 (
b11110011011110 ?
b1111000000010101 '
b1111000000010101 6
b1111011010101 &
b1111011010101 -
b1100100 F
b1100100 D
b1100100 =
b1100100 ;
b1100100 4
b1100100 2
b1100100 5
b1100100 >
b1100100 G
b100101 ,
b111111111111111111111111110011011011110000111010 A
b111111111111111111111110111110100010101110010000 8
b111111111111111111111111100001101001011011100011 /
1$
#84
0$
#85
b111111111111111111111110111010101100101100010010 #
b111111111111111111111110111010101100101100010010 0
b111111111111111111111110110101111010110011011011 "
b111111111111111111111110110101111010110011011011 9
b111111111111111111111111111001100000011001010110 !
b111111111111111111111111111001100000011001010110 B
b10010110011110 (
b10010110011110 ?
b1101101000000 '
b1101101000000 6
b1111100111111010 &
b1111100111111010 -
b1100100 F
b1100100 D
b1100100 =
b1100100 ;
b1100100 4
b1100100 2
b1100100 5
b1100100 >
b1100100 G
b100110 ,
b111111111111111111111111111001100000011001010110 A
b111111111111111111111110110101111010110011011011 8
b111111111111111111111110111010101100101100010010 /
1$
#86
0$
#87
b111111111111111111111110101000110011001111011110 #
b111111111111111111111110101000110011001111011110 0
b111111111111111111111111001011111111010110000100 "
b111111111111111111111111001011111111010110000100 9
b11100111101000011010 !
b11100111101000011010 B
b1101101001100010 (
b1101101001100010 ?
b11100111101001 '
b11100111101001 6
b1101011100110100 &
b1101011100110100 -
b1100100 F
b1100100 D
b1100100 =
b1100100 ;
b1100100 4
b1100100 2
b1100100 5
b1100100 >
b1100100 G
b100111 ,
b11100111101000011010 A
b111111111111111111111111001011111111010110000100 8
b111111111111111111111110101000110011001111011110 /
1$
#88
0$
#89
b111111111111111111111110111000010000011011010100 #
b111111111111111111111110111000010000011011010100 0
b111111111111111111111111111101100011101011010010 "
b111111111111111111111111111101100011101011010010 9
b1110001000111100001110 !
b1110001000111100001110 B
b1100001100100010 (
b1100001100100010 ?
b11110111111101 '
b11110111111101 6
b1100001010001011 &
b1100001010001011 -
b1100100 F
b1100100 D
b1100100 =
b1100100 ;
b1100100 4
b1100100 2
b1100100 5
b1100100 >
b1100100 G
b101000 ,
b1110001000111100001110 A
b111111111111111111111111111101100011101011010010 8
b111111111111111111111110111000010000011011010100 /
1$
#90
0$
#91
b111111111111111111111111101001110000110110111101 #
b111111111111111111111111101001110000110110111101 0
b111010101110010101000111 "
b111010101110010101000111 9
b10100110000001001110100 !
b10100110000001001110100 B
b0 (
b0 ?
b10010110011110 '
b10010110011110 6
b1100001100100010 &
b1100001100100010 -
b1100100 F
b1100100 D
b1100100 =
b1100100 ;
b1100100 4
b1100100 2
b1100100 5
b1100100 >
b1100100 G
b101001 ,
b10100110000001001110100 A
b111010101110010101000111 8
b111111111111111111111111101001110000110110111101 /
1$
#92
0$
#93
b101111100110110111000000 #
b101111100110110111000000 0
b1101011010001111001110000 "
b1101011010001111001110000 9
b10100000101011010001100 !
b10100000101011010001100 B
b11110011011110 (
b11110011011110 ?
b1111101111111011 '
b1111101111111011 6
b1101100011000110 &
b1101100011000110 -
b1100100 F
b1100100 D
b1100100 =
b1100100 ;
b1100100 4
b1100100 2
b1100100 5
b1100100 >
b1100100 G
b101010 ,
b10100000101011010001100 A
b1101011010001111001110000 8
b101111100110110111000000 /
1$
#94
0$
#95
b1110000010111100101111100 #
b1110000010111100101111100 0
b1110111100000010011110011 "
b1110111100000010011110011 9
b1010111010110101000010 !
b1010111010110101000010 B
b10010110011110 (
b10010110011110 ?
b1101010000110000 '
b1101010000110000 6
b1111101111111011 &
b1111101111111011 -
b1100100 F
b1100100 D
b1100100 =
b1100100 ;
b1100100 4
b1100100 2
b1100100 5
b1100100 >
b1100100 G
b101011 ,
b1010111010110101000010 A
b1110111100000010011110011 8
b1110000010111100101111100 /
1$
#96
0$
