exp-6/fir_pl_direct.sv
module fir_direct #(parameter TAPS = 100)(
    input  logic clk, rst_n,
    input  logic signed [15:0] din,
    input  logic signed [15:0] coeffs [0:TAPS-1],
    output logic signed [39:0] dout
);
    logic signed [15:0] shift_reg [0:TAPS-1];
    logic signed [31:0] mult_reg [0:TAPS-1];
    logic signed [39:0] acc_reg;
    
    // Shifting
    always_ff @(posedge clk) begin
        if (rst_n) begin
            for (int i=0; i<TAPS; i++) shift_reg[i] <= 0;
        end else begin
            shift_reg[0] <= din;
            for (int i=1; i<TAPS; i++) shift_reg[i] <= shift_reg[i-1];
        end
    end

    // Multiplication
    always_ff @(posedge clk) begin
        if (rst_n) begin
            for (int i=0; i<TAPS; i++) mult_reg[i] <= 0;
        end else begin
            for (int i=0; i<TAPS; i++) mult_reg[i] <= shift_reg[i] * coeffs[i];
        end
    end

    // Accumulation
    always_ff @(posedge clk) begin
        if (rst_n) begin
            acc_reg <= 0;
            dout <= 0;
        end else begin
            acc_reg = 0;
            for (int i=0; i<TAPS; i++) acc_reg += mult_reg[i];
            dout <= acc_reg;
        end
    end
endmodule

exp-6/tb_pip_dir.sv
`timescale 1ns/1ns
module tb_fir_direct();
    reg clk, rst_n;
    wire signed [39:0] dout_950;
    wire signed [39:0] dout_1100;
    wire signed [39:0] dout_2000;
    reg signed [15:0] din_950;
    reg signed [15:0] din_1100;
    reg signed [15:0] din_2000;
    reg signed [15:0] coeffs [0:99];
    reg signed [15:0] samples_950 [0:1052];
    reg signed [15:0] samples_1100 [0:909];
    reg signed [15:0] samples_2000 [0:499];
    reg signed [39:0] out_950 [0:1899];
    reg signed [39:0] out_1100 [0:1899];
    reg signed [39:0] out_2000 [0:1899];
    integer idx;
    
    // Three separate FIR modules
    fir_direct u_dut_950 (
        .clk(clk),
        .rst_n(rst_n),
        .din(din_950),
        .dout(dout_950),
        .coeffs(coeffs)
    );
    
    fir_direct u_dut_1100 (
        .clk(clk),
        .rst_n(rst_n),
        .din(din_1100),
        .dout(dout_1100),
        .coeffs(coeffs)
    );
    
    fir_direct u_dut_2000 (
        .clk(clk),
        .rst_n(rst_n),
        .din(din_2000),
        .dout(dout_2000),
        .coeffs(coeffs)
    );
    
    initial clk = 0;
    always #1 clk = ~clk;

    always @(posedge clk) begin
        if(rst_n) begin
            idx <= 0;
            din_950 <= 16'b0;
            din_1100 <= 16'b0;
            din_2000 <= 16'b0;
        end
        else begin
            // Apply different samples to each input
            if(idx <= 1052) din_950 <= samples_950[idx];
            else din_950 <= 16'b0;
            
            if(idx <= 909) din_1100 <= samples_1100[idx];
            else din_1100 <= 16'b0;
            
            if(idx <= 499) din_2000 <= samples_2000[idx];
            else din_2000 <= 16'b0;
            
            // Store outputs
            out_950[idx] <= dout_950;
            out_1100[idx] <= dout_1100;
            out_2000[idx] <= dout_2000;
            
            idx <= idx + 1;
        end
    end

    task read_coeffs;
        integer coeff_file;
        integer i;
        coeff_file = $fopen("fc_quantized_2_14.txt", "r");
        if (coeff_file == 0) begin
            $display("Error: Cannot open fc_quantized_2_14.txt");
            $finish;
        end
        for (i = 0; i < 100; i = i + 1)
            $fscanf(coeff_file, "%b\n", coeffs[i]);
        $fclose(coeff_file);
        $display("Read 100 coefficients");
    endtask;

    task read_q_2_14_950;
        integer in_file;
        integer idx;
        in_file = $fopen("q_2_14_950.txt", "r");
        if (in_file == 0) begin
            $display("Error: Cannot open q_2_14_950.txt");
            $finish;
        end
        for (idx = 0; idx < 1053; idx = idx + 1) begin
            $fscanf(in_file, "%b\n", samples_950[idx]);
        end
        $fclose(in_file);
        $display("Read 1053 samples for 950 Hz");
    endtask;
    
    task read_q_2_14_1100;
        integer in_file;
        integer idx;
        in_file = $fopen("q_2_14_1100.txt", "r");
        if (in_file == 0) begin
            $display("Error: Cannot open q_2_14_1100.txt");
            $finish;
        end
        for (idx = 0; idx < 910; idx = idx + 1) begin
            $fscanf(in_file, "%b\n", samples_1100[idx]);
        end
        $fclose(in_file);
        $display("Read 910 samples for 1100 Hz");
    endtask;

    task read_q_2_14_2000;
        integer in_file;
        integer idx;
        in_file = $fopen("q_2_14_2000.txt", "r");
        if (in_file == 0) begin
            $display("Error: Cannot open q_2_14_2000.txt");
            $finish;
        end
        for (idx = 0; idx < 500; idx = idx + 1) begin
            $fscanf(in_file, "%b\n", samples_2000[idx]);
        end
        $fclose(in_file);
        $display("Read 500 samples for 2000 Hz");
    endtask;
    
    task readFiles;
        read_coeffs();
        read_q_2_14_950();
        read_q_2_14_1100();
        read_q_2_14_2000();
    endtask;
    
    task writeFiles;
        integer j, out_950_file, out_1100_file, out_2000_file;
        out_950_file = $fopen("out_direct_950.txt", "w");
        out_1100_file = $fopen("out_direct_1100.txt", "w");
        out_2000_file = $fopen("out_direct_2000.txt", "w");
        
        for(j = 0; j < idx; j = j + 1) begin
            $fdisplay(out_950_file, "%b", out_950[j]);
            $fdisplay(out_1100_file, "%b", out_1100[j]);
            $fdisplay(out_2000_file, "%b", out_2000[j]);
        end
        
        $fclose(out_950_file);
        $fclose(out_1100_file);
        $fclose(out_2000_file);
        $display("Wrote %0d samples to output files", idx);
    endtask;

    initial begin
        $dumpfile("wave_direct.vcd"); 
        $dumpvars(0, tb_fir_direct);
    end
    
    initial begin
        rst_n = 1;
        idx = 0;
        
        readFiles();
        
        #2;
        rst_n = 0;
        
        // Run for enough cycles to process all samples + pipeline flush
        #( (1053 + 100) * 2 );  // 2ns per clock cycle (500MHz)
        
        writeFiles();
        $finish;
    end
endmodule

exp-6/wave_direct.vcd
$date
	Tue Apr 21 13:04:05 2026
$end
$version
	Icarus Verilog
$end
$timescale
	1ns
$end
$scope module tb_fir_direct $end
$var wire 40 ! dout_950 [39:0] $end
$var wire 40 " dout_2000 [39:0] $end
$var wire 40 # dout_1100 [39:0] $end
$var reg 1 $ clk $end
$var reg 16 % din_1100 [15:0] $end
$var reg 16 & din_2000 [15:0] $end
$var reg 16 ' din_950 [15:0] $end
$var reg 1 ( rst_n $end
$var integer 32 ) idx [31:0] $end
$scope module u_dut_1100 $end
$var wire 1 $ clk $end
$var wire 16 * din [15:0] $end
$var wire 1 ( rst_n $end
$var parameter 32 + TAPS $end
$var reg 40 , acc_reg [39:0] $end
$var reg 40 - dout [39:0] $end
$scope begin $ivl_for_loop0 $end
$var integer 32 . i [31:0] $end
$upscope $end
$scope begin $ivl_for_loop1 $end
$var integer 32 / i [31:0] $end
$upscope $end
$scope begin $ivl_for_loop2 $end
$var integer 32 0 i [31:0] $end
$upscope $end
$scope begin $ivl_for_loop3 $end
$var integer 32 1 i [31:0] $end
$upscope $end
$scope begin $ivl_for_loop4 $end
$var integer 32 2 i [31:0] $end
$upscope $end
$upscope $end
$scope module u_dut_2000 $end
$var wire 1 $ clk $end
$var wire 16 3 din [15:0] $end
$var wire 1 ( rst_n $end
$var parameter 32 4 TAPS $end
$var reg 40 5 acc_reg [39:0] $end
$var reg 40 6 dout [39:0] $end
$scope begin $ivl_for_loop0 $end
$var integer 32 7 i [31:0] $end
$upscope $end
$scope begin $ivl_for_loop1 $end
$var integer 32 8 i [31:0] $end
$upscope $end
$scope begin $ivl_for_loop2 $end
$var integer 32 9 i [31:0] $end
$upscope $end
$scope begin $ivl_for_loop3 $end
$var integer 32 : i [31:0] $end
$upscope $end
$scope begin $ivl_for_loop4 $end
$var integer 32 ; i [31:0] $end
$upscope $end
$upscope $end
$scope module u_dut_950 $end
$var wire 1 $ clk $end
$var wire 16 < din [15:0] $end
$var wire 1 ( rst_n $end
$var parameter 32 = TAPS $end
$var reg 40 > acc_reg [39:0] $end
$var reg 40 ? dout [39:0] $end
$scope begin $ivl_for_loop0 $end
$var integer 32 @ i [31:0] $end
$upscope $end
$scope begin $ivl_for_loop1 $end
$var integer 32 A i [31:0] $end
$upscope $end
$scope begin $ivl_for_loop2 $end
$var integer 32 B i [31:0] $end
$upscope $end
$scope begin $ivl_for_loop3 $end
$var integer 32 C i [31:0] $end
$upscope $end
$scope begin $ivl_for_loop4 $end
$var integer 32 D i [31:0] $end
$upscope $end
$upscope $end
$scope task readFiles $end
$upscope $end
$scope task read_coeffs $end
$var integer 32 E coeff_file [31:0] $end
$var integer 32 F i [31:0] $end
$upscope $end
$scope task read_q_2_14_1100 $end
$var integer 32 G idx [31:0] $end
$var integer 32 H in_file [31:0] $end
$upscope $end
$scope task read_q_2_14_2000 $end
$var integer 32 I idx [31:0] $end
$var integer 32 J in_file [31:0] $end
$upscope $end
$scope task read_q_2_14_950 $end
$var integer 32 K idx [31:0] $end
$var integer 32 L in_file [31:0] $end
$upscope $end
$scope task writeFiles $end
$var integer 32 M j [31:0] $end
$var integer 32 N out_1100_file [31:0] $end
$var integer 32 O out_2000_file [31:0] $end
$var integer 32 P out_950_file [31:0] $end
$upscope $end
$upscope $end
$enddefinitions $end
$comment Show the parameter values. $end
$dumpall
b1100100 =
b1100100 4
b1100100 +
$end
#0
$dumpvars
bx P
bx O
bx N
bx M
b10000000000000000000000000000011 L
b10000011101 K
b10000000000000000000000000000011 J
b111110100 I
b10000000000000000000000000000011 H
b1110001110 G
b1100100 F
b10000000000000000000000000000011 E
b0 D
b0 C
b0 B
b0 A
b0 @
bx ?
bx >
bx <
b0 ;
b0 :
b0 9
b0 8
b0 7
bx 6
bx 5
bx 3
b0 2
b0 1
b0 0
b0 /
b0 .
bx -
bx ,
bx *
b0 )
1(
bx '
bx &
bx %
0$
bx #
bx "
bx !
$end
#1
b0 !
b0 ?
b0 >
b0 #
b0 -
b0 ,
b0 "
b0 6
b0 5
b0 &
b0 3
b0 %
b0 *
b0 '
b0 <
b1100100 9
b1100100 7
b1100100 0
b1100100 .
b1100100 B
b1100100 @
1$
#2
0$
0(
#3
b1 )
b1100100 :
b1100100 8
b1100100 1
b1100100 /
b1100100 C
b1100100 A
b1100100 D
b1100100 2
b1100100 ;
1$
#4
0$
#5
b10 )
b11110011011110 &
b11110011011110 3
b10100011001100 %
b10100011001100 *
b10001111111001 '
b10001111111001 <
b1100100 :
b1100100 8
b1100100 1
b1100100 /
b1100100 C
b1100100 A
b1100100 D
b1100100 2
b1100100 ;
1$
#6
0$
#7
b11 )
b10010110011110 &
b10010110011110 3
b11111011011110 %
b11111011011110 *
b11101110000001 '
b11101110000001 <
b1100100 :
b1100100 8
b1100100 1
b1100100 /
b1100100 C
b1100100 A
b1100100 D
b1100100 2
b1100100 ;
1$
#8
0$
#9
b100 )
b1101101001100010 &
b1101101001100010 3
b11100000010101 %
b11100000010101 *
b11111001110101 '
b11111001110101 <
b1100100 :
b1100100 8
b1100100 1
b1100100 /
b1100100 C
b1100100 A
b1100100 D
b1100100 2
b1100100 ;
1$
#10
0$
#11
b1111111111111111111111111001010000010101 !
b1111111111111111111111111001010000010101 ?
b1111111111111111111111111000010110011100 #
b1111111111111111111111111000010110011100 -
b1111111111111111111111110100100101100110 "
b1111111111111111111111110100100101100110 6
b101 )
b1100001100100010 &
b1100001100100010 3
b1011110001111 %
b1011110001111 *
b10101111010000 '
b10101111010000 <
b1100100 :
b1100100 8
b1100100 1
b1100100 /
b1100100 C
b1100100 A
b1111111111111111111111111001010000010101 >
b1100100 D
b1111111111111111111111111000010110011100 ,
b1100100 2
b1111111111111111111111110100100101100110 5
b1100100 ;
1$
#12
0$
#13
b1111111111111111111111100101000110101110 !
b1111111111111111111111100101000110101110 ?
b1111111111111111111111100010010111010010 #
b1111111111111111111111100010010111010010 -
b1111111111111111111111011110010100010100 "
b1111111111111111111111011110010100010100 6
b110 )
b0 &
b0 3
b1110110000111001 %
b1110110000111001 *
b101000000011 '
b101000000011 <
b1100100 :
b1100100 8
b1100100 1
b1100100 /
b1100100 C
b1100100 A
b1100100 D
b1100100 2
b1100100 ;
b1111111111111111111111011110010100010100 5
b1111111111111111111111100010010111010010 ,
b1111111111111111111111100101000110101110 >
1$
#14
0$
#15
b1111111111111111111111000110000001011001 !
b1111111111111111111111000110000001011001 ?
b1111111111111111111111000011000010000011 #
b1111111111111111111111000011000010000011 -
b1111111111111111111111010100010110111010 "
b1111111111111111111111010100010110111010 6
b111 )
b11110011011110 &
b11110011011110 3
b1100100111110111 %
b1100100111110111 *
b1110010011000000 '
b1110010011000000 <
b1100100 :
b1100100 8
b1100100 1
b1100100 /
b1100100 C
b1100100 A
b1100100 D
b1100100 2
b1100100 ;
b1111111111111111111111010100010110111010 5
b1111111111111111111111000011000010000011 ,
b1111111111111111111111000110000001011001 >
1$
#16
0$
#17
b1111111111111111111110101001000000001100 !
b1111111111111111111110101001000000001100 ?
b1111111111111111111110101011010010010010 #
b1111111111111111111110101011010010010010 -
b1111111111111111111111101000010001101110 "
b1111111111111111111111101000010001101110 6
b1000 )
b10010110011110 &
b10010110011110 3
b1100000010000001 %
b1100000010000001 *
b1100100011101010 '
b1100100011101010 <
b1100100 :
b1100100 8
b1100100 1
b1100100 /
b1100100 C
b1100100 A
b1100100 D
b1100100 2
b1100100 ;
b1111111111111111111111101000010001101110 5
b1111111111111111111110101011010010010010 ,
b1111111111111111111110101001000000001100 >
1$
#18
0$
#19
b1111111111111111111110100011010100110111 !
b1111111111111111111110100011010100110111 ?
b1111111111111111111110110010110001011011 #
b1111111111111111111110110010110001011011 -
b10001100100010110 "
b10001100100010110 6
b1001 )
b1101101001100010 &
b1101101001100010 3
b1101010000110000 %
b1101010000110000 *
b1100000000100000 '
b1100000000100000 <
b1100100 :
b1100100 8
b1100100 1
b1100100 /
b1100100 C
b1100100 A
b1100100 D
b1100100 2
b1100100 ;
b10001100100010110 5
b1111111111111111111110110010110001011011 ,
b1111111111111111111110100011010100110111 >
1$
#20
0$
#21
b1111111111111111111111000110101100010100 !
b1111111111111111111111000110101100010100 ?
b1111111111111111111111100111111001110011 #
b1111111111111111111111100111111001110011 -
b110001110011000010 "
b110001110011000010 6
b1010 )
b1100001100100010 &
b1100001100100010 3
b1111101111111011 %
b1111101111111011 *
b1100110101101110 '
b1100110101101110 <
b1100100 :
b1100100 8
b1100100 1
b1100100 /
b1100100 C
b1100100 A
b1100100 D
b1100100 2
b1100100 ;
b110001110011000010 5
b1111111111111111111111100111111001110011 ,
b1111111111111111111111000110101100010100 >
1$
#22
0$
#23
b10110100110111111 !
b10110100110111111 ?
b1000100001001000000 #
b1000100001001000000 -
b110111000011100000 "
b110111000011100000 6
b1011 )
b0 &
b0 3
b10010110011110 %
b10010110011110 *
b1110110000111001 '
b1110110000111001 <
b1100100 :
b1100100 8
b1100100 1
b1100100 /
b1100100 C
b1100100 A
b1100100 D
b1100100 2
b1100100 ;
b110111000011100000 5
b1000100001001000000 ,
b10110100110111111 >
1$
#24
0$
#25
b10000000011011101000 !
b10000000011011101000 ?
b10100111010110010111 #
b10100111010110010111 -
b101001010010101000 "
b101001010010101000 6
b1100 )
b11110011011110 &
b11110011011110 3
b11110111111101 %
b11110111111101 *
b1000111011011 '
b1000111011011 <
b1100100 :
b1100100 8
b1100100 1
b1100100 /
b1100100 C
b1100100 A
b1100100 D
b1100100 2
b1100100 ;
b101001010010101000 5
b10100111010110010111 ,
b10000000011011101000 >
1$
#26
0$
#27
b11011101010100000111 !
b11011101010100000111 ?
b11100001011100100000 #
b11100001011100100000 -
b10111101110010010 "
b10111101110010010 6
b1101 )
b10010110011110 &
b10010110011110 3
b11100111101001 %
b11100111101001 *
b11000101010000 '
b11000101010000 <
b1100100 :
b1100100 8
b1100100 1
b1100100 /
b1100100 C
b1100100 A
b1100100 D
b1100100 2
b1100100 ;
b10111101110010010 5
b11100001011100100000 ,
b11011101010100000111 >
1$
#28
0$
#29
b11111011001001011110 !
b11111011001001011110 ?
b11000011010111011100 #
b11000011010111011100 -
b1111111111111111111111111100001100100010 "
b1111111111111111111111111100001100100010 6
b1110 )
b1101101001100010 &
b1101101001100010 3
b1101101000000 %
b1101101000000 *
b11111110110111 '
b11111110110111 <
b1100100 :
b1100100 8
b1100100 1
b1100100 /
b1100100 C
b1100100 A
b1100100 D
b1100100 2
b1100100 ;
b1111111111111111111111111100001100100010 5
b11000011010111011100 ,
b11111011001001011110 >
1$
#30
0$
#31
b10110010011000110010 !
b10110010011000110010 ?
b111001110001010111 #
b111001110001010111 -
b1111111111111111111111001011010010111110 "
b1111111111111111111111001011010010111110 6
b1111 )
b1100001100100010 &
b1100001100100010 3
b1111000000010101 %
b1111000000010101 *
b11100000010101 '
b11100000010101 <
b1100100 :
b1100100 8
b1100100 1
b1100100 /
b1100100 C
b1100100 A
b1100100 D
b1100100 2
b1100100 ;
b1111111111111111111111001011010010111110 5
b111001110001010111 ,
b10110010011000110010 >
1$
#32
0$
#33
b1111111111111111111111111100101110000001 !
b1111111111111111111111111100101110000001 ?
b1111111111111111111101100000000111011110 #
b1111111111111111111101100000000111011110 -
b1111111111111111111110010011010110000000 "
b1111111111111111111110010011010110000000 6
b10000 )
b0 &
b0 3
b1100110000111001 %
b1100110000111001 *
b1110100001110 '
b1110100001110 <
b1100100 :
b1100100 8
b1100100 1
b1100100 /
b1100100 C
b1100100 A
b1100100 D
b1100100 2
b1100100 ;
b1111111111111111111110010011010110000000 5
b1111111111111111111101100000000111011110 ,
b1111111111111111111111111100101110000001 >
1$
#34
0$
#35
b1111111111111111111100000110111111000001 !
b1111111111111111111100000110111111000001 ?
b1111111111111111111010000101111001110010 #
b1111111111111111111010000101111001110010 -
b1111111111111111111110000011001110101010 "
b1111111111111111111110000011001110101010 6
b10001 )
b11110011011110 &
b11110011011110 3
b1100000000100000 %
b1100000000100000 *
b1111011111111011 '
b1111011111111011 <
b1100100 :
b1100100 8
b1100100 1
b1100100 /
b1100100 C
b1100100 A
b1100100 D
b1100100 2
b1100100 ;
b1111111111111111111110000011001110101010 5
b1111111111111111111010000101111001110010 ,
b1111111111111111111100000110111111000001 >
1$
#36
0$
#37
b1111111111111111111000101100111010011101 !
b1111111111111111111000101100111010011101 ?
b1111111111111111111000010110111011110001 #
b1111111111111111111000010110111011110001 -
b1111111111111111111110111100101000101000 "
b1111111111111111111110111100101000101000 6
b10010 )
b10010110011110 &
b10010110011110 3
b1101000101011001 %
b1101000101011001 *
b1101010110101101 '
b1101010110101101 <
b1100100 :
b1100100 8
b1100100 1
b1100100 /
b1100100 C
b1100100 A
b1100100 D
b1100100 2
b1100100 ;
b1111111111111111111110111100101000101000 5
b1111111111111111111000010110111011110001 ,
b1111111111111111111000101100111010011101 >
1$
#38
0$
#39
b1111111111111111110111011011101001011010 !
b1111111111111111110111011011101001011010 ?
b1111111111111111111001101100011000110001 #
b1111111111111111111001101100011000110001 -
b101001010010101000 "
b101001010010101000 6
b10011 )
b1101101001100010 &
b1101101001100010 3
b1111011111111011 %
b1111011111111011 *
b1100001000000011 '
b1100001000000011 <
b1100100 :
b1100100 8
b1100100 1
b1100100 /
b1100100 C
b1100100 A
b1100100 D
b1100100 2
b1100100 ;
b101001010010101000 5
b1111111111111111111001101100011000110001 ,
b1111111111111111110111011011101001011010 >
1$
#40
0$
#41
b1111111111111111111001100101001111111110 !
b1111111111111111111001100101001111111110 ?
b1111111111111111111110011100001111000001 #
b1111111111111111111110011100001111000001 -
b10001110010101101100 "
b10001110010101101100 6
b10100 )
b1100001100100010 &
b1100001100100010 3
b10001001001011 %
b10001001001011 *
b1100001111001001 '
b1100001111001001 <
b1100100 :
b1100100 8
b1100100 1
b1100100 /
b1100100 C
b1100100 A
b1100100 D
b1100100 2
b1100100 ;
b10001110010101101100 5
b1111111111111111111110011100001111000001 ,
b1111111111111111111001100101001111111110 >
1$
#42
0$
#43
b1111111111111111111111010010010101110100 !
b1111111111111111111111010010010101110100 ?
b101011010110000101101 #
b101011010110000101101 -
b10111111001111010000 "
b10111111001111010000 6
b10101 )
b0 &
b0 3
b11110011011110 %
b11110011011110 *
b1101101001100010 '
b1101101001100010 <
b1100100 :
b1100100 8
b1100100 1
b1100100 /
b1100100 C
b1100100 A
b1100100 D
b1100100 2
b1100100 ;
b10111111001111010000 5
b101011010110000101101 ,
b1111111111111111111111010010010101110100 >
1$
#44
0$
#45
b111000100001000101000 !
b111000100001000101000 ?
b1011111110101101111011 #
b1011111110101101111011 -
b10101101101010111010 "
b10101101101010111010 6
b10110 )
b11110011011110 &
b11110011011110 3
b11101110000001 %
b11101110000001 *
b1111110111111101 '
b1111110111111101 <
b1100100 :
b1100100 8
b1100100 1
b1100100 /
b1100100 C
b1100100 A
b1100100 D
b1100100 2
b1100100 ;
b10101101101010111010 5
b1011111110101101111011 ,
b111000100001000101000 >
1$
#46
0$
#47
b1110000011001110111110 !
b1110000011001110111110 ?
b1110111010100110110101 #
b1110111010100110110101 -
b1011110111001001000 "
b1011110111001001000 6
b10111 )
b10010110011110 &
b10010110011110 3
b1111011010101 %
b1111011010101 *
b10001001001011 '
b10001001001011 <
b1100100 :
b1100100 8
b1100100 1
b1100100 /
b1100100 C
b1100100 A
b1100100 D
b1100100 2
b1100100 ;
b1011110111001001000 5
b1110111010100110110101 ,
b1110000011001110111110 >
1$
#48
0$
#49
b10000111000010011110110 !
b10000111000010011110110 ?
b1011110011010110011010 #
b1011110011010110011010 -
b1111111111111111111111011001000011110110 "
b1111111111111111111111011001000011110110 6
b11000 )
b1101101001100010 &
b1101101001100010 3
b1111010000000010 %
b1111010000000010 *
b11101010111100 '
b11101010111100 <
b1100100 :
b1100100 8
b1100100 1
b1100100 /
b1100100 C
b1100100 A
b1100100 D
b1100100 2
b1100100 ;
b1111111111111111111111011001000011110110 5
b1011110011010110011010 ,
b10000111000010011110110 >
1$
#50
0$
#51
b1101000110010011111011 !
b1101000110010011111011 ?
b10011001010100000110 #
b10011001010100000110 -
b1111111111111111111100110101010110010110 "
b1111111111111111111100110101010110010110 6
b11001 )
b1100001100100010 &
b1100001100100010 3
b1100111010110000 %
b1100111010110000 *
b11111011011110 '
b11111011011110 <
b1100100 :
b1100100 8
b1100100 1
b1100100 /
b1100100 C
b1100100 A
b1100100 D
b1100100 2
b1100100 ;
b1111111111111111111100110101010110010110 5
b10011001010100000110 ,
b1101000110010011111011 >
1$
#52
0$
#53
b10100010100000000100 !
b10100010100000000100 ?
b1111111111111111110101010101101110101100 #
b1111111111111111110101010101101110101100 -
b1111111111111111111010110110001110100010 "
b1111111111111111111010110110001110100010 6
b11010 )
b0 &
b0 3
b1100000000000000 %
b1100000000000000 *
b10110101000001 '
b10110101000001 <
b1100100 :
b1100100 8
b1100100 1
b1100100 /
b1100100 C
b1100100 A
b1100100 D
b1100100 2
b1100100 ;
b1111111111111111111010110110001110100010 5
b1111111111111111110101010101101110101100 ,
b10100010100000000100 >
1$
#54
0$
#55
b1111111111111111110100000010111000111001 !
b1111111111111111110100000010111000111001 ?
b1111111111111111101001101101011101110000 #
b1111111111111111101001101101011101110000 -
b1111111111111111111010110011111000000100 "
b1111111111111111111010110011111000000100 6
b11011 )
b11110011011110 &
b11110011011110 3
b1100111010110000 %
b1100111010110000 *
b101111111110 '
b101111111110 <
b1100100 :
b1100100 8
b1100100 1
b1100100 /
b1100100 C
b1100100 A
b1100100 D
b1100100 2
b1100100 ;
b1111111111111111111010110011111000000100 5
b1111111111111111101001101101011101110000 ,
b1111111111111111110100000010111000111001 >
1$
#56
0$
#57
b1111111111111111100110111100100000110101 !
b1111111111111111100110111100100000110101 ?
b1111111111111111100101001101000100001101 #
b1111111111111111100101001101000100001101 -
b1111111111111111111101010011110010000110 "
b1111111111111111111101010011110010000110 6
b11100 )
b10010110011110 &
b10010110011110 3
b1111010000000010 %
b1111010000000010 *
b1110011010010101 '
b1110011010010101 <
b1100100 :
b1100100 8
b1100100 1
b1100100 /
b1100100 C
b1100100 A
b1100100 D
b1100100 2
b1100100 ;
b1111111111111111111101010011110010000110 5
b1111111111111111100101001101000100001101 ,
b1111111111111111100110111100100000110101 >
1$
#58
0$
#59
b1111111111111111100001010110011111010100 !
b1111111111111111100001010110011111010100 ?
b1111111111111111101011101011101000110000 #
b1111111111111111101011101011101000110000 -
b1100100001001100110 "
b1100100001001100110 6
b11101 )
b1101101001100010 &
b1101101001100010 3
b1111011010101 %
b1111011010101 *
b1100100111110111 '
b1100100111110111 <
b1100100 :
b1100100 8
b1100100 1
b1100100 /
b1100100 C
b1100100 A
b1100100 D
b1100100 2
b1100100 ;
b1100100001001100110 5
b1111111111111111101011101011101000110000 ,
b1111111111111111100001010110011111010100 >
1$
#60
0$
#61
b1111111111111111100111100111110001010001 !
b1111111111111111100111100111110001010001 ?
b1111111111111111111100111010110101001001 #
b1111111111111111111100111010110101001001 -
b101110011000100000110 "
b101110011000100000110 6
b11110 )
b1100001100100010 &
b1100001100100010 3
b11101110000001 %
b11101110000001 *
b1100000000001000 '
b1100000000001000 <
b1100100 :
b1100100 8
b1100100 1
b1100100 /
b1100100 C
b1100100 A
b1100100 D
b1100100 2
b1100100 ;
b101110011000100000110 5
b1111111111111111111100111010110101001001 ,
b1111111111111111100111100111110001010001 >
1$
#62
0$
#63
b1111111111111111111001111110011101100010 !
b1111111111111111111001111110011101100010 ?
b10011101101101100000111 #
b10011101101101100000111 -
b1000001100110100001100 "
b1000001100110100001100 6
b11111 )
b0 &
b0 3
b11110011011110 %
b11110011011110 *
b1100110000111001 '
b1100110000111001 <
b1100100 :
b1100100 8
b1100100 1
b1100100 /
b1100100 C
b1100100 A
b1100100 D
b1100100 2
b1100100 ;
b1000001100110100001100 5
b10011101101101100000111 ,
b1111111111111111111001111110011101100010 >
1$
#64
0$
#65
b10011010111011111111011 !
b10011010111011111111011 ?
b100111000100111110010110 #
b100111000100111110010110 -
b111101001101011100000 "
b111101001101011100000 6
b100000 )
b11110011011110 &
b11110011011110 3
b10001001001011 %
b10001001001011 *
b1110101001010010 '
b1110101001010010 <
b1100100 :
b1100100 8
b1100100 1
b1100100 /
b1100100 C
b1100100 A
b1100100 D
b1100100 2
b1100100 ;
b111101001101011100000 5
b100111000100111110010110 ,
b10011010111011111111011 >
1$
#66
0$
#67
b101010011100111010001100 !
b101010011100111010001100 ?
b101101011111000101110001 #
b101101011111000101110001 -
b11111101010110001010 "
b11111101010110001010 6
b100001 )
b10010110011110 &
b10010110011110 3
b1111011111111011 %
b1111011111111011 *
b111111101011 '
b111111101011 <
b1100100 :
b1100100 8
b1100100 1
b1100100 /
b1100100 C
b1100100 A
b1100100 D
b1100100 2
b1100100 ;
b11111101010110001010 5
b101101011111000101110001 ,
b101010011100111010001100 >
1$
#68
0$
#69
b110100101011100111110001 !
b110100101011100111110001 ?
b100001000101101011010010 #
b100001000101101011010010 -
b1111111111111111111101111000101101101110 "
b1111111111111111111101111000101101101110 6
b100010 )
b1101101001100010 &
b1101101001100010 3
b1101000101011001 %
b1101000101011001 *
b11000000000010 '
b11000000000010 <
b1100100 :
b1100100 8
b1100100 1
b1100100 /
b1100100 C
b1100100 A
b1100100 D
b1100100 2
b1100100 ;
b1111111111111111111101111000101101101110 5
b100001000101101011010010 ,
b110100101011100111110001 >
1$
#70
0$
#71
b101010101100001001010010 !
b101010101100001001010010 ?
b11001110111110001001 #
b11001110111110001001 -
b1111111111111111110111010110001101000100 "
b1111111111111111110111010110001101000100 6
b100011 )
b1100001100100010 &
b1100001100100010 3
b1100000000100000 %
b1100000000100000 *
b11111101111111 '
b11111101111111 <
b1100100 :
b1100100 8
b1100100 1
b1100100 /
b1100100 C
b1100100 A
b1100100 D
b1100100 2
b1100100 ;
b1111111111111111110111010110001101000100 5
b11001110111110001001 ,
b101010101100001001010010 >
1$
#72
0$
#73
b1100001011000100001110 !
b1100001011000100001110 ?
b1111111111111111011101010111000111101000 #
b1111111111111111011101010111000111101000 -
b1111111111111111110011000001001000101000 "
b1111111111111111110011000001001000101000 6
b100100 )
b0 &
b0 3
b1100110000111001 %
b1100110000111001 *
b11100100000110 '
b11100100000110 <
b1100100 :
b1100100 8
b1100100 1
b1100100 /
b1100100 C
b1100100 A
b1100100 D
b1100100 2
b1100100 ;
b1111111111111111110011000001001000101000 5
b1111111111111111011101010111000111101000 ,
b1100001011000100001110 >
1$
#74
0$
#75
b1111111111111111100001101001011011100011 !
b1111111111111111100001101001011011100011 ?
b1111111111111110111110100010101110010000 #
b1111111111111110111110100010101110010000 -
b1111111111111111110011011011110000111010 "
b1111111111111111110011011011110000111010 6
b100101 )
b11110011011110 &
b11110011011110 3
b1111000000010101 %
b1111000000010101 *
b1111011010101 '
b1111011010101 <
b1100100 :
b1100100 8
b1100100 1
b1100100 /
b1100100 C
b1100100 A
b1100100 D
b1100100 2
b1100100 ;
b1111111111111111110011011011110000111010 5
b1111111111111110111110100010101110010000 ,
b1111111111111111100001101001011011100011 >
1$
#76
0$
#77
b1111111111111110111010101100101100010010 !
b1111111111111110111010101100101100010010 ?
b1111111111111110110101111010110011011011 #
b1111111111111110110101111010110011011011 -
b1111111111111111111001100000011001010110 "
b1111111111111111111001100000011001010110 6
b100110 )
b10010110011110 &
b10010110011110 3
b1101101000000 %
b1101101000000 *
b1111100111111010 '
b1111100111111010 <
b1100100 :
b1100100 8
b1100100 1
b1100100 /
b1100100 C
b1100100 A
b1100100 D
b1100100 2
b1100100 ;
b1111111111111111111001100000011001010110 5
b1111111111111110110101111010110011011011 ,
b1111111111111110111010101100101100010010 >
1$
#78
0$
#79
b1111111111111110101000110011001111011110 !
b1111111111111110101000110011001111011110 ?
b1111111111111111001011111111010110000100 #
b1111111111111111001011111111010110000100 -
b11100111101000011010 "
b11100111101000011010 6
b100111 )
b1101101001100010 &
b1101101001100010 3
b11100111101001 %
b11100111101001 *
b1101011100110100 '
b1101011100110100 <
b1100100 :
b1100100 8
b1100100 1
b1100100 /
b1100100 C
b1100100 A
b1100100 D
b1100100 2
b1100100 ;
b11100111101000011010 5
b1111111111111111001011111111010110000100 ,
b1111111111111110101000110011001111011110 >
1$
#80
0$
