exp-6/fir_pl_opt.sv
module fir_optimized #(
    parameter TAPS = 100
) (
    input wire clk,
    input wire rst_n,
    input wire signed [15:0] coeffs [0:TAPS-1],
    input wire signed [15:0] din,
    output reg signed [39:0] dout
);
    
    reg signed [39:0] tap_reg [0:TAPS-1];
    reg signed [39:0] product;
    integer i;
    
    always @(posedge clk or negedge rst_n) begin
        if (!rst_n) begin
            for (i = 0; i < TAPS; i = i + 1) begin
                tap_reg[i] <= 40'sb0;
            end
            dout <= 40'sb0;
        end
        else begin
            // Compute product once per cycle
            product = din * coeffs[0];
            
            // Transposed FIR: each tap adds product to previous tap
            tap_reg[0] <= product;
            for (i = 1; i < TAPS; i = i + 1) begin
                tap_reg[i] <= tap_reg[i-1] + (din * coeffs[i]);
            end
            
            // Output is the last tap
            dout <= tap_reg[TAPS-1];
        end
    end
    
endmodule

exp-6/tb_pip_opt.sv
`timescale 1ns/1ns
module tb_fir_optimized();
    reg clk, rst_n;
    wire signed [39:0] dout_950, dout_1100, dout_2000;
    reg signed [15:0] din_950, din_1100, din_2000;
    reg signed [15:0] coeffs [0:99];
    reg signed [15:0] samples_950 [0:1052];
    reg signed [15:0] samples_1100 [0:1052];
    reg signed [15:0] samples_2000 [0:1052];
    reg signed [39:0] out_950 [0:1899];
    reg signed [39:0] out_1100 [0:1899];
    reg signed [39:0] out_2000 [0:1899];
    integer idx;
    
    fir_optimized #(.TAPS(100)) u_dut_950 (
    .clk(clk),
    .rst_n(rst_n),
    .din(din_950),
    .dout(dout_950),
    .coeffs(coeffs)
);
        fir_optimized #(.TAPS(100)) u_dut2 (
            .clk(clk),
            .rst_n(rst_n),
            .din(din_1100),
            .dout(dout_1100),
            .coeffs(coeffs)
        );
    fir_optimized #(.TAPS(100)) u_dut3 (
        .clk(clk),
        .rst_n(rst_n),
        .din(din_2000),
        .dout(dout_2000),
        .coeffs(coeffs)
    );

    
    initial clk = 0;
    always #1 clk = ~clk;
    
    always @(posedge clk) begin
        if (!rst_n) begin
            idx <= 0;
            din_950 <= 16'sb0;
            din_1100 <= 16'sb0;
            din_2000 <= 16'sb0;
        end
        else begin
            if (idx < 1053) begin
                din_950 <= samples_950[idx];
                din_1100 <= samples_1100[idx];
                din_2000 <= samples_2000[idx];
                out_950[idx] <= dout_950;
                out_1100[idx] <= dout_1100;
                out_2000[idx] <= dout_2000;
                idx <= idx + 1;
            end
        end
    end
    
    task read_coeffs;
        integer coeff_file, i;
        begin
            coeff_file = $fopen("fc_quantized_2_14.txt", "r");
            for (i = 0; i < 100; i = i + 1)
                $fscanf(coeff_file, "%b\n", coeffs[i]);
            $fclose(coeff_file);
            $display("Read 100 coefficients");
        end
    endtask
    
    task read_samples;
        integer file_950, file_1100, file_2000, i;
        begin
            file_950 = $fopen("q_2_14_950.txt", "r");
            file_1100 = $fopen("q_2_14_1100.txt", "r");
            file_2000 = $fopen("q_2_14_2000.txt", "r");
            
            for (i = 0; i < 1053; i = i + 1) begin
                $fscanf(file_950, "%b\n", samples_950[i]);
                $fscanf(file_1100, "%b\n", samples_1100[i]);
                $fscanf(file_2000, "%b\n", samples_2000[i]);
            end
            
            $fclose(file_950);
            $fclose(file_1100);
            $fclose(file_2000);
            $display("Read samples for all frequencies");
        end
    endtask
    
    task write_outputs;
        integer j, f_950, f_1100, f_2000;
        begin
            f_950 = $fopen("out_950_optimized.txt", "w");
            f_1100 = $fopen("out_1100_optimized.txt", "w");
            f_2000 = $fopen("out_2000_optimized.txt", "w");
            
            for (j = 100; j < 603; j = j + 1) begin  // Skip initial transients
                $fwrite(f_950, "%b\n", out_950[j]);
                $fwrite(f_1100, "%b\n", out_1100[j]);
                $fwrite(f_2000, "%b\n", out_2000[j]);
            end
            
            $fclose(f_950);
            $fclose(f_1100);
            $fclose(f_2000);
            $display("Written optimized outputs");
        end
    endtask
    
    initial begin
        $dumpfile("wave_optimized.vcd");
        $dumpvars(0, tb_fir_optimized);
    end
    
    initial begin
        rst_n = 0;
        idx = 0;
        
        read_coeffs();
        read_samples();
        
        #2;
        rst_n = 1;
        
        #10008;
        
        write_outputs();
        $finish;
    end
    
endmodule

exp-6/wave_optimized.vcd
$date
	Tue Apr 21 12:52:25 2026
$end
$version
	Icarus Verilog
$end
$timescale
	1ns
$end
$scope module tb_fir_optimized $end
$var wire 40 ! dout_950 [39:0] $end
$var wire 40 " dout_2000 [39:0] $end
$var wire 40 # dout_1100 [39:0] $end
$var reg 1 $ clk $end
$var reg 16 % din_1100 [15:0] $end
$var reg 16 & din_2000 [15:0] $end
$var reg 16 ' din_950 [15:0] $end
$var reg 1 ( rst_n $end
$var integer 32 ) idx [31:0] $end
$scope module u_dut2 $end
$var wire 1 $ clk $end
$var wire 16 * din [15:0] $end
$var wire 1 ( rst_n $end
$var parameter 32 + TAPS $end
$var reg 40 , dout [39:0] $end
$var reg 40 - product [39:0] $end
$var integer 32 . i [31:0] $end
$upscope $end
$scope module u_dut3 $end
$var wire 1 $ clk $end
$var wire 16 / din [15:0] $end
$var wire 1 ( rst_n $end
$var parameter 32 0 TAPS $end
$var reg 40 1 dout [39:0] $end
$var reg 40 2 product [39:0] $end
$var integer 32 3 i [31:0] $end
$upscope $end
$scope module u_dut_950 $end
$var wire 1 $ clk $end
$var wire 16 4 din [15:0] $end
$var wire 1 ( rst_n $end
$var parameter 32 5 TAPS $end
$var reg 40 6 dout [39:0] $end
$var reg 40 7 product [39:0] $end
$var integer 32 8 i [31:0] $end
$upscope $end
$scope task read_coeffs $end
$var integer 32 9 coeff_file [31:0] $end
$var integer 32 : i [31:0] $end
$upscope $end
$scope task read_samples $end
$var integer 32 ; file_1100 [31:0] $end
$var integer 32 < file_2000 [31:0] $end
$var integer 32 = file_950 [31:0] $end
$var integer 32 > i [31:0] $end
$upscope $end
$scope task write_outputs $end
$var integer 32 ? f_1100 [31:0] $end
$var integer 32 @ f_2000 [31:0] $end
$var integer 32 A f_950 [31:0] $end
$var integer 32 B j [31:0] $end
$upscope $end
$upscope $end
$enddefinitions $end
$comment Show the parameter values. $end
$dumpall
b1100100 5
b1100100 0
b1100100 +
$end
#0
$dumpvars
bx B
bx A
bx @
bx ?
b10000011101 >
b10000000000000000000000000000011 =
b10000000000000000000000000000101 <
b10000000000000000000000000000100 ;
b1100100 :
b10000000000000000000000000000011 9
b1100100 8
bx 7
b0 6
bx 4
b1100100 3
bx 2
b0 1
bx /
b1100100 .
bx -
b0 ,
bx *
b0 )
0(
bx '
bx &
bx %
0$
b0 #
b0 "
b0 !
$end
#1
b0 &
b0 /
b0 %
b0 *
b0 '
b0 4
b1100100 3
b1100100 .
b1100100 8
1$
#2
0$
1(
#3
b1 )
b1100100 8
b0 7
b1100100 .
b0 -
b1100100 3
b0 2
1$
#4
0$
#5
b10 )
b11110011011110 &
b11110011011110 /
b10100011001100 %
b10100011001100 *
b10001111111001 '
b10001111111001 4
b1100100 3
b1100100 .
b1100100 8
1$
#6
0$
#7
b11 )
b10010110011110 &
b10010110011110 /
b11111011011110 %
b11111011011110 *
b11101110000001 '
b11101110000001 4
b1100100 8
b1111111111111111111111111001010000010101 7
b1100100 .
b1111111111111111111111111000010110011100 -
b1100100 3
b1111111111111111111111110100100101100110 2
1$
#8
0$
#9
b1111111111111111111111110100100101100110 "
b1111111111111111111111110100100101100110 1
b1111111111111111111111111000010110011100 #
b1111111111111111111111111000010110011100 ,
b1111111111111111111111111001010000010101 !
b1111111111111111111111111001010000010101 6
b100 )
b1101101001100010 &
b1101101001100010 /
b11100000010101 %
b11100000010101 *
b11111001110101 '
b11111001110101 4
b1100100 3
b1111111111111111111111111000111100100110 2
b1100100 .
b1111111111111111111111110100001101100110 -
b1100100 8
b1111111111111111111111110100110101111101 7
1$
#10
0$
#11
b1111111111111111111111100101000110101110 !
b1111111111111111111111100101000110101110 6
b1111111111111111111111100010010111010010 #
b1111111111111111111111100010010111010010 ,
b1111111111111111111111011110010100010100 "
b1111111111111111111111011110010100010100 1
b101 )
b1100001100100010 &
b1100001100100010 /
b1011110001111 %
b1011110001111 *
b10101111010000 '
b10101111010000 4
b1100100 8
b1111111111111111111111110100010010100001 7
b1100100 .
b1111111111111111111111110101011111000001 -
b1100100 3
b111000011011010 2
1$
#12
0$
#13
b1111111111111111111111010100010110111010 "
b1111111111111111111111010100010110111010 1
b1111111111111111111111000011000010000011 #
b1111111111111111111111000011000010000011 ,
b1111111111111111111111000110000001011001 !
b1111111111111111111111000110000001011001 6
b110 )
b0 &
b0 /
b1110110000111001 %
b1110110000111001 *
b101000000011 '
b101000000011 4
b1100100 3
b1011011010011010 2
b1100100 .
b1111111111111111111111111011100101010011 -
b1100100 8
b1111111111111111111111110111110010010000 7
1$
#14
0$
#15
b1111111111111111111110101001000000001100 !
b1111111111111111111110101001000000001100 6
b1111111111111111111110101011010010010010 #
b1111111111111111111110101011010010010010 ,
b1111111111111111111111101000010001101110 "
b1111111111111111111111101000010001101110 1
b111 )
b11110011011110 &
b11110011011110 /
b1100100111110111 %
b1100100111110111 *
b1110010011000000 '
b1110010011000000 4
b1100100 8
b1111111111111111111111111110000111110111 7
b1100100 .
b11101101010101 -
b1100100 3
b0 2
1$
#16
0$
#17
b10001100100010110 "
b10001100100010110 1
b1111111111111111111110110010110001011011 #
b1111111111111111111110110010110001011011 ,
b1111111111111111111110100011010100110111 !
b1111111111111111111110100011010100110111 6
b1000 )
b10010110011110 &
b10010110011110 /
b1100000010000001 %
b1100000010000001 *
b1100100011101010 '
b1100100011101010 4
b1100100 3
b1111111111111111111111110100100101100110 2
b1100100 .
b1010001000011011 -
b1100100 8
b101000111000000 7
1$
#18
0$
#19
b1111111111111111111111000110101100010100 !
b1111111111111111111111000110101100010100 6
b1111111111111111111111100111111001110011 #
b1111111111111111111111100111111001110011 ,
b110001110011000010 "
b110001110011000010 1
b1001 )
b1101101001100010 &
b1101101001100010 /
b1101010000110000 %
b1101010000110000 *
b1100000000100000 '
b1100000000100000 4
b1100100 8
b1010010101000010 7
b1100100 .
b1011111001111101 -
b1100100 3
b1111111111111111111111111000111100100110 2
1$
#20
0$
#21
b110111000011100000 "
b110111000011100000 1
b1000100001001000000 #
b1000100001001000000 ,
b10110100110111111 !
b10110100110111111 6
b1010 )
b1100001100100010 &
b1100001100100010 /
b1111101111111011 %
b1111101111111011 *
b1100110101101110 '
b1100110101101110 4
b1100100 3
b111000011011010 2
b1100100 .
b1000001101110000 -
b1100100 8
b1011111110100000 7
1$
#22
0$
#23
b10000000011011101000 !
b10000000011011101000 6
b10100111010110010111 #
b10100111010110010111 ,
b101001010010101000 "
b101001010010101000 1
b1011 )
b0 &
b0 /
b10010110011110 %
b10010110011110 *
b1110110000111001 '
b1110110000111001 4
b1100100 8
b1001011110110110 7
b1100100 .
b110000001111 -
b1100100 3
b1011011010011010 2
1$
#24
0$
#25
b10111101110010010 "
b10111101110010010 1
b11100001011100100000 #
b11100001011100100000 ,
b11011101010100000111 !
b11011101010100000111 6
b1100 )
b11110011011110 &
b11110011011110 /
b11110111111101 %
b11110111111101 *
b1000111011011 '
b1000111011011 4
b1100100 3
b0 2
b1100100 .
b1111111111111111111111111000111100100110 -
b1100100 8
b11101101010101 7
1$
#26
0$
#27
b11111011001001011110 !
b11111011001001011110 6
b11000011010111011100 #
b11000011010111011100 ,
b1111111111111111111111111100001100100010 "
b1111111111111111111111111100001100100010 1
b1101 )
b10010110011110 &
b10010110011110 /
b11100111101001 %
b11100111101001 *
b11000101010000 '
b11000101010000 4
b1100100 8
b1111111111111111111111111100101001101111 7
b1100100 .
b1111111111111111111111110100011000001001 -
b1100100 3
b1111111111111111111111110100100101100110 2
1$
#28
0$
#29
b1111111111111111111111001011010010111110 "
b1111111111111111111111001011010010111110 1
b111001110001010111 #
b111001110001010111 ,
b10110010011000110010 !
b10110010011000110010 6
b1110 )
b1101101001100010 &
b1101101001100010 /
b1101101000000 %
b1101101000000 *
b11111110110111 '
b11111110110111 4
b1100100 3
b1111111111111111111111111000111100100110 2
b1100100 .
b1111111111111111111111110101001001000101 -
b1100100 8
b1111111111111111111111110110110000010000 7
1$
#30
0$
#31
b1111111111111111111111111100101110000001 !
b1111111111111111111111111100101110000001 6
b1111111111111111111101100000000111011110 #
b1111111111111111111101100000000111011110 ,
b1111111111111111111110010011010110000000 "
b1111111111111111111110010011010110000000 1
b1111 )
b1100001100100010 &
b1100001100100010 /
b1111000000010101 %
b1111000000010101 *
b11100000010101 '
b11100000010101 4
b1100100 8
b1111111111111111111111110100000011011011 7
b1100100 .
b1111111111111111111111111010111001000000 -
b1100100 3
b111000011011010 2
1$
#32
0$
#33
b1111111111111111111110000011001110101010 "
b1111111111111111111110000011001110101010 1
b1111111111111111111010000101111001110010 #
b1111111111111111111010000101111001110010 ,
b1111111111111111111100000110111111000001 !
b1111111111111111111100000110111111000001 6
b10000 )
b0 &
b0 /
b1100110000111001 %
b1100110000111001 *
b1110100001110 '
b1110100001110 4
b1100100 3
b1011011010011010 2
b1100100 .
b10111111000001 -
b1100100 8
b1111111111111111111111110101011111000001 7
1$
#34
0$
#35
b1111111111111111111000101100111010011101 !
b1111111111111111111000101100111010011101 6
b1111111111111111111000010110111011110001 #
b1111111111111111111000010110111011110001 ,
b1111111111111111111110111100101000101000 "
b1111111111111111111110111100101000101000 1
b10001 )
b11110011011110 &
b11110011011110 /
b1100000000100000 %
b1100000000100000 *
b1111011111111011 '
b1111011111111011 4
b1100100 8
b1111111111111111111111111010100011010110 7
b1100100 .
b1001101101010101 -
b1100100 3
b0 2
1$
#36
0$
#37
b101001010010101000 "
b101001010010101000 1
b1111111111111111111001101100011000110001 #
b1111111111111111111001101100011000110001 ,
b1111111111111111110111011011101001011010 !
b1111111111111111110111011011101001011010 6
b10010 )
b10010110011110 &
b10010110011110 /
b1101000101011001 %
b1101000101011001 *
b1101010110101101 '
b1101010110101101 4
b1100100 3
b1111111111111111111111110100100101100110 2
b1100100 .
b1011111110100000 -
b1100100 8
b1100000001111 7
1$
#38
0$
#39
b1111111111111111111001100101001111111110 !
b1111111111111111111001100101001111111110 6
b1111111111111111111110011100001111000001 #
b1111111111111111111110011100001111000001 ,
b10001110010101101100 "
b10001110010101101100 1
b10011 )
b1101101001100010 &
b1101101001100010 /
b1111011111111011 %
b1111011111111011 *
b1100001000000011 '
b1100001000000011 4
b1100100 8
b111111011111001 7
b1100100 .
b1000101111110101 -
b1100100 3
b1111111111111111111111111000111100100110 2
1$
#40
0$
#41
b10111111001111010000 "
b10111111001111010000 1
b101011010110000101101 #
b101011010110000101101 ,
b1111111111111111111111010010010101110100 !
b1111111111111111111111010010010101110100 6
b10100 )
b1100001100100010 &
b1100001100100010 /
b10001001001011 %
b10001001001011 *
b1100001111001001 '
b1100001111001001 4
b1100100 3
b111000011011010 2
b1100100 .
b1100000001111 -
b1100100 8
b1011100111110111 7
1$
#42
0$
#43
b111000100001000101000 !
b111000100001000101000 6
b1011111110101101111011 #
b1011111110101101111011 ,
b10101101101010111010 "
b10101101101010111010 1
b10101 )
b0 &
b0 /
b11110011011110 %
b11110011011110 *
b1101101001100010 '
b1101101001100010 4
b1100100 8
b1011010010100101 7
b1100100 .
b1111111111111111111111111001100100011111 -
b1100100 3
b1011011010011010 2
1$
#44
0$
#45
b1011110111001001000 "
b1011110111001001000 1
b1110111010100110110101 #
b1110111010100110110101 ,
b1110000011001110111110 !
b1110000011001110111110 6
b10110 )
b11110011011110 &
b11110011011110 /
b11101110000001 %
b11101110000001 *
b1111110111111101 '
b1111110111111101 4
b1100100 3
b0 2
b1100100 .
b1111111111111111111111110100100101100110 -
b1100100 8
b111000011011010 7
1$
#46
0$
#47
b10000111000010011110110 !
b10000111000010011110110 6
b1011110011010110011010 #
b1011110011010110011010 ,
b1111111111111111111111011001000011110110 "
b1111111111111111111111011001000011110110 1
b10111 )
b10010110011110 &
b10010110011110 /
b1111011010101 %
b1111011010101 *
b10001001001011 '
b10001001001011 4
b1100100 8
b11000001001 7
b1100100 .
b1111111111111111111111110100110101111101 -
b1100100 3
b1111111111111111111111110100100101100110 2
1$
#48
0$
#49
b1111111111111111111100110101010110010110 "
b1111111111111111111100110101010110010110 1
b10011001010100000110 #
b10011001010100000110 ,
b1101000110010011111011 !
b1101000110010011111011 6
b11000 )
b1101101001100010 &
b1101101001100010 /
b1111010000000010 %
b1111010000000010 *
b11101010111100 '
b11101010111100 4
b1100100 3
b1111111111111111111111111000111100100110 2
b1100100 .
b1111111111111111111111111010001110000001 -
b1100100 8
b1111111111111111111111111001100100011111 7
1$
#50
0$
#51
b10100010100000000100 !
b10100010100000000100 6
b1111111111111111110101010101101110101100 #
b1111111111111111110101010101101110101100 ,
b1111111111111111111010110110001110100010 "
b1111111111111111111010110110001110100010 1
b11001 )
b1100001100100010 &
b1100001100100010 /
b1100111010110000 %
b1100111010110000 *
b11111011011110 '
b11111011011110 4
b1100100 8
b1111111111111111111111110100111111001100 7
b1100100 .
b10001111111010 -
b1100100 3
b111000011011010 2
1$
#52
0$
#53
b1111111111111111111010110011111000000100 "
b1111111111111111111010110011111000000100 1
b1111111111111111101001101101011101110000 #
b1111111111111111101001101101011101110000 ,
b1111111111111111110100000010111000111001 !
b1111111111111111110100000010111000111001 6
b11010 )
b0 &
b0 /
b1100000000000000 %
b1100000000000000 *
b10110101000001 '
b10110101000001 4
b1100100 3
b1011011010011010 2
b1100100 .
b1001001111110000 -
b1100100 8
b1111111111111111111111110100001101100110 7
1$
#54
0$
#55
b1111111111111111100110111100100000110101 !
b1111111111111111100110111100100000110101 6
b1111111111111111100101001101000100001101 #
b1111111111111111100101001101000100001101 ,
b1111111111111111111101010011110010000110 "
b1111111111111111111101010011110010000110 1
b11011 )
b11110011011110 &
b11110011011110 /
b1100111010110000 %
b1100111010110000 *
b101111111110 '
b101111111110 4
b1100100 8
b1111111111111111111111110111100000111101 7
b1100100 .
b1100000000000000 -
b1100100 3
b0 2
1$
#56
0$
#57
b1100100001001100110 "
b1100100001001100110 1
b1111111111111111101011101011101000110000 #
b1111111111111111101011101011101000110000 ,
b1111111111111111100001010110011111010100 !
b1111111111111111100001010110011111010100 6
b11100 )
b10010110011110 &
b10010110011110 /
b1111010000000010 %
b1111010000000010 *
b1110011010010101 '
b1110011010010101 4
b1100100 3
b1111111111111111111111110100100101100110 2
b1100100 .
b1001001111110000 -
b1100100 8
b1111111111111111111111111101110000000110 7
1$
#58
0$
#59
b1111111111111111100111100111110001010001 !
b1111111111111111100111100111110001010001 6
b1111111111111111111100111010110101001001 #
b1111111111111111111100111010110101001001 ,
b101110011000100000110 "
b101110011000100000110 1
b11101 )
b1101101001100010 &
b1101101001100010 /
b1111011010101 %
b1111011010101 *
b1100100111110111 '
b1100100111110111 4
b1100100 8
b100110001000001 7
b1100100 .
b10001111111010 -
b1100100 3
b1111111111111111111111111000111100100110 2
1$
#60
0$
#61
b1000001100110100001100 "
b1000001100110100001100 1
b10011101101101100000111 #
b10011101101101100000111 ,
b1111111111111111111001111110011101100010 !
b1111111111111111111001111110011101100010 6
b11110 )
b1100001100100010 &
b1100001100100010 /
b11101110000001 %
b11101110000001 *
b1100000000001000 '
b1100000000001000 4
b1100100 3
b111000011011010 2
b1100100 .
b1111111111111111111111111010001110000001 -
b1100100 8
b1010001000011011 7
1$
#62
0$
#63
b10011010111011111111011 !
b10011010111011111111011 6
b100111000100111110010110 #
b100111000100111110010110 ,
b111101001101011100000 "
b111101001101011100000 1
b11111 )
b0 &
b0 /
b11110011011110 %
b11110011011110 *
b1100110000111001 '
b1100110000111001 4
b1100100 8
b1011111111101000 7
b1100100 .
b1111111111111111111111110100110101111101 -
b1100100 3
b1011011010011010 2
1$
#64
0$
#65
b11111101010110001010 "
b11111101010110001010 1
b101101011111000101110001 #
b101101011111000101110001 ,
b101010011100111010001100 !
b101010011100111010001100 6
b100000 )
b11110011011110 &
b11110011011110 /
b10001001001011 %
b10001001001011 *
b1110101001010010 '
b1110101001010010 4
b1100100 3
b0 2
b1100100 .
b1111111111111111111111110100100101100110 -
b1100100 8
b1001101101010101 7
1$
#66
0$
#67
b110100101011100111110001 !
b110100101011100111110001 6
b100001000101101011010010 #
b100001000101101011010010 ,
b1111111111111111111101111000101101101110 "
b1111111111111111111101111000101101101110 1
b100001 )
b10010110011110 &
b10010110011110 /
b1111011111111011 %
b1111011111111011 *
b111111101011 '
b111111101011 4
b1100100 8
b100000100001010 7
b1100100 .
b1111111111111111111111111001100100011111 -
b1100100 3
b1111111111111111111111110100100101100110 2
1$
#68
0$
#69
b1111111111111111110111010110001101000100 "
b1111111111111111110111010110001101000100 1
b11001110111110001001 #
b11001110111110001001 ,
b101010101100001001010010 !
b101010101100001001010010 6
b100010 )
b1101101001100010 &
b1101101001100010 /
b1101000101011001 %
b1101000101011001 *
b11000000000010 '
b11000000000010 4
b1100100 3
b1111111111111111111111111000111100100110 2
b1100100 .
b1100000001111 -
b1100100 8
b1111111111111111111111111101000000111111 7
1$
#70
0$
#71
b1100001011000100001110 !
b1100001011000100001110 6
b1111111111111111011101010111000111101000 #
b1111111111111111011101010111000111101000 ,
b1111111111111111110011000001001000101000 "
b1111111111111111110011000001001000101000 1
b100011 )
b1100001100100010 &
b1100001100100010 /
b1100000000100000 %
b1100000000100000 *
b11111101111111 '
b11111101111111 4
b1100100 8
b1111111111111111111111110110111111111010 7
b1100100 .
b1000101111110101 -
b1100100 3
b111000011011010 2
1$
#72
0$
#73
b1111111111111111110011011011110000111010 "
b1111111111111111110011011011110000111010 1
b1111111111111110111110100010101110010000 #
b1111111111111110111110100010101110010000 ,
b1111111111111111100001101001011011100011 !
b1111111111111111100001101001011011100011 6
b100100 )
b0 &
b0 /
b1100110000111001 %
b1100110000111001 *
b11100100000110 '
b11100100000110 4
b1100100 3
b1011011010011010 2
b1100100 .
b1011111110100000 -
b1100100 8
b1111111111111111111111110100000110000011 7
1$
#74
0$
#75
b1111111111111110111010101100101100010010 !
b1111111111111110111010101100101100010010 6
b1111111111111110110101111010110011011011 #
b1111111111111110110101111010110011011011 ,
b1111111111111111111001100000011001010110 "
b1111111111111111111001100000011001010110 1
b100101 )
b11110011011110 &
b11110011011110 /
b1111000000010101 %
b1111000000010101 *
b1111011010101 '
b1111011010101 4
b1100100 8
b1111111111111111111111110101010011101110 7
b1100100 .
b1001101101010101 -
b1100100 3
b0 2
1$
#76
0$
#77
b11100111101000011010 "
b11100111101000011010 1
b1111111111111111001011111111010110000100 #
b1111111111111111001011111111010110000100 ,
b1111111111111110101000110011001111011110 !
b1111111111111110101000110011001111011110 6
b100110 )
b10010110011110 &
b10010110011110 /
b1101101000000 %
b1101101000000 *
b1111100111111010 '
b1111100111111010 4
b1100100 3
b1111111111111111111111110100100101100110 2
b1100100 .
b10111111000001 -
b1100100 8
b1111111111111111111111111010001110000001 7
1$
#78
0$
#79
b1111111111111110111000010000011011010100 !
b1111111111111110111000010000011011010100 6
b1111111111111111111101100011101011010010 #
b1111111111111111111101100011101011010010 ,
b1110001000111100001110 "
b1110001000111100001110 1
b100111 )
b1101101001100010 &
b1101101001100010 /
b11100111101001 %
b11100111101001 *
b1101011100110100 '
b1101011100110100 4
b1100100 8
b1001000010010 7
b1100100 .
b1111111111111111111111111010111001000000 -
b1100100 3
b1111111111111111111111111000111100100110 2
1$
#80
0$
#81
b10100110000001001110100 "
b10100110000001001110100 1
b111010101110010101000111 #
b111010101110010101000111 ,
b1111111111111111101001110000110110111101 !
b1111111111111111101001110000110110111101 6
b101000 )
b1100001100100010 &
b1100001100100010 /
b11110111111101 %
b11110111111101 *
b1100001010001011 '
b1100001010001011 4
b1100100 3
b111000011011010 2
b1100100 .
b1111111111111111111111110101001001000101 -
b1100100 8
b111101001100100 7
1$
#82
0$
#83
b101111100110110111000000 !
b101111100110110111000000 6
b1101011010001111001110000 #
b1101011010001111001110000 ,
b10100000101011010001100 "
b10100000101011010001100 1
b101001 )
b0 &
b0 /
b10010110011110 %
b10010110011110 *
b1100001100100010 '
b1100001100100010 4
b1100100 8
b1011100001011111 7
b1100100 .
b1111111111111111111111110100011000001001 -
b1100100 3
b1011011010011010 2
1$
#84
0$
#85
b1010111010110101000010 "
b1010111010110101000010 1
b1110111100000010011110011 #
b1110111100000010011110011 ,
b1110000010111100101111100 !
b1110000010111100101111100 6
b101010 )
b11110011011110 &
b11110011011110 /
b1111101111111011 %
b1111101111111011 *
b1101100011000110 '
b1101100011000110 4
b1100100 3
b0 2
b1100100 .
b1111111111111111111111111000111100100110 -
b1100100 8
b1011011010011010 7
1$
#86
0$
#87
b10001111001001101101110001 !
b10001111001001101101110001 6
b1010010011010101111111111 #
b1010010011010101111111111 ,
b1111111111111111111010111011010001011010 "
b1111111111111111111010111011010001011010 1
b101011 )
b10010110011110 &
b10010110011110 /
b1101010000110000 %
b1101010000110000 *
b1111101111111011 '
b1111101111111011 4
b1100100 8
b111010110101110 7
b1100100 .
b110000001111 -
b1100100 3
b1111111111111111111111110100100101100110 2
1$
#88
0$
#89
b1111111111111111101000101011000001101000 "
b1111111111111111101000101011000001101000 1
b1010010011101100000 #
b1010010011101100000 ,
b1110110111100101000011011 !
b1110110111100101000011011 6
b101100 )
b1101101001100010 &
b1101101001100010 /
b1100000010000001 %
b1100000010000001 *
b10000010010100 '
b10000010010100 4
b1100100 3
b1111111111111111111111111000111100100110 2
b1100100 .
b1000001101110000 -
b1100100 8
b110000001111 7
1$
#90
0$
#91
b100101010001010110001110 !
b100101010001010110001110 6
b1111111111111110011101000010101101010101 #
b1111111111111110011101000010101101010101 ,
b1111111111111111011011000001000100101100 "
b1111111111111111011011000001000100101100 1
b101101 )
b1100001100100010 &
b1100001100100010 /
b1100100111110111 %
b1100100111110111 *
b11100111101001 '
b11100111101001 4
b1100100 8
b1111111111111111111111111001111001000100 7
b1100100 .
b1011111001111101 -
b1100100 3
b111000011011010 2
1$
#92
0$
#93
b1111111111111111011001001011100100010110 "
b1111111111111111011001001011100100010110 1
b1111111111111101001011111000011010011101 #
b1111111111111101001011111000011010011101 ,
b1111111111111110101111011110111111001011 !
b1111111111111110101111011110111111001011 6
b101110 )
b0 &
b0 /
b1110110000111001 %
b1110110000111001 *
b11111100110110 '
b11111100110110 4
b1100100 3
b1011011010011010 2
b1100100 .
b1010001000011011 -
b1100100 8
b1111111111111111111111110101001001000101 7
1$
#94
0$
#95
b1111111111111100111111100101100010101011 !
b1111111111111100111111100101100010101011 6
b1111111111111100110100011111011010100001 #
b1111111111111100110100011111011010100001 ,
b1111111111111111100111110101110110010100 "
b1111111111111111100111110101110110010100 1
b101111 )
b11110011011110 &
b11110011011110 /
b1011110001111 %
b1011110001111 *
b10111010100111 '
b10111010100111 4
b1100100 8
b1111111111111111111111110100001001011110 7
b1100100 .
b11101101010101 -
b1100100 3
b0 2
1$
#96
0$
#97
b110111100101010101010 "
b110111100101010101010 1
b1111111111111101101111001001101100111001 #
b1111111111111101101111001001101100111001 ,
b1111111111111100001000001110001000101001 !
b1111111111111100001000001110001000101001 6
b110000 )
b10010110011110 &
b10010110011110 /
b11100000010101 %
b11100000010101 *
b110111110110 '
b110111110110 4
b1100100 3
b1111111111111111111111110100100101100110 2
b1100100 .
b1111111111111111111111111011100101010011 -
b1100100 8
b1111111111111111111111110111010000001011 7
1$
#98
0$
#99
b1111111111111100110010111010011000011010 !
b1111111111111100110010111010011000011010 6
b1111111111111111111010010100010100111100 #
b1111111111111111111010010100010100111100 ,
b110001011000000010110110 "
b110001011000000010110110 1
b110001 )
b1101101001100010 &
b1101101001100010 /
b11111011011110 %
b11111011011110 *
b1110100001110001 '
b1110100001110001 4
b1100100 8
b1111111111111111111111111101011000011110 7
b1100100 .
b1111111111111111111111110101011111000001 -
b1100100 3
b1111111111111111111111111000111100100110 2
1$
#100
0$
#101
b1011110100010100010111100 "
b1011110100010100010111100 1
b10110111101010001111110111 #
b10110111101010001111110111 ,
b1111111111111111001110011110011011110001 !
b1111111111111111001110011110011011110001 6
b110010 )
b1100001100100010 &
b1100001100100010 /
b10100011001100 %
b10100011001100 *
b1100101100010001 '
b1100101100010001 4
b1100100 3
b111000011011010 2
b1100100 .
b1111111111111111111111110100001101100110 -
b1100100 8
b100011010101101 7
1$
#102
0$
#103
b11000100001000010110110011 !
b11000100001000010110110011 6
b101110011011101000011100111 #
b101110011011101000011100111 ,
b10000100100000101100001110 "
b10000100100000101100001110 1
b110011 )
b0 &
b0 /
b0 %
b0 *
b1100000000000000 '
b1100000000000000 4
b1100100 8
b1001111011001101 7
b1100100 .
b1111111111111111111111111000010110011100 -
b1100100 3
b1011011010011010 2
1$
#104
0$
#105
b10011010011100010111111000 "
b10011010011100010111111000 1
b111110100101111111011001111 #
b111110100101111111011001111 ,
b111011000101101001001110101 !
b111011000101101001001110101 6
b110100 )
b11110011011110 &
b11110011011110 /
b1101011100110100 %
b1101011100110100 *
b1100101100010001 '
b1100101100010001 4
b1100100 3
b0 2
b1100100 .
b0 -
b1100100 8
b1100000000000000 7
1$
#106
0$
#107
b1010111011001010011111111000 !
b1010111011001010011111111000 6
b1000010000110001100101100000 #
b1000010000110001100101100000 ,
b10011010110000010010101100 "
b10011010110000010010101100 1
b110101 )
b10010110011110 &
b10010110011110 /
b1100000100100010 %
b1100000100100010 *
b1110100001110001 '
b1110100001110001 4
b1100100 8
b1001111011001101 7
b1100100 .
b111101001100100 -
b1100100 3
b1111111111111111111111110100100101100110 2
1$
#108
0$
