main-04.m.v
module newton_raphson #(
    parameter I_BITS = 8,
    parameter F_BITS = 16
)(
    // input wire clk,
    // input wire reset,
    input wire [I_BITS+F_BITS-1:0] numerator,
    input wire [I_BITS+F_BITS-1:0] denominator,
    output reg [I_BITS+F_BITS-1:0] result
);

    localparam TOTAL_BITS = I_BITS + F_BITS;
    localparam ITERATIONS = 8;  // Fixed iterations
    localparam ONE  = 1 << F_BITS;       // 256
    localparam HALF = 1 << (F_BITS-1);   // 128

   function [TOTAL_BITS-1:0] mul;
    input [TOTAL_BITS-1:0] a, b;
    reg [2*TOTAL_BITS-1:0] product;  // product result
    begin
        product = a * b;
        mul = product >> F_BITS;
    end
   endfunction
   
function [TOTAL_BITS-1:0] normalize;
    input [TOTAL_BITS-1:0] D_in;
    reg [TOTAL_BITS-1:0] D_out;
    integer i;
    begin
        D_out = D_in;
        for (i = 0; i < TOTAL_BITS; i = i + 1) begin
            if (D_out < HALF)
                D_out = D_out << 1;
            else if (D_out > ONE)
                D_out = D_out >> 1;
        end
        normalize = D_out;
    end
endfunction
function integer compute_scale;
    input [TOTAL_BITS-1:0] D_in;
    reg [TOTAL_BITS-1:0] D_func;
    integer i;
    integer scale;
    begin
        scale = 0;
        D_func = D_in;

        for (i = 0; i < TOTAL_BITS; i = i + 1) begin
            if (D_func < HALF) begin
                D_func = D_func << 1;
                scale = scale - 1;
            end
            else if (D_func > ONE) begin
                D_func = D_func >> 1;
                scale = scale + 1;
            end
        end

        compute_scale = scale;
    end
endfunction

function [TOTAL_BITS-1:0] newton_raphson;
    input [TOTAL_BITS-1:0] D;
    reg [TOTAL_BITS-1:0] x;
    reg [TOTAL_BITS-1:0] D_norm;
    integer scale;
    integer i;
    begin
        // Constants in 8.16 fixed-point format
        
       localparam [TOTAL_BITS-1:0] CONST_48_17 = 24'b00000010_11010011_00010000; 
       localparam [TOTAL_BITS-1:0] CONST_32_17 = 24'b00000001_11100010_00001011; 
       localparam [TOTAL_BITS-1:0] TWO = 24'b00000010_00000000_00000000;   
        
        D_norm = normalize(D);
        scale = compute_scale(D);
        // $display("D_norm:%b scale:%d",D_norm,scale);
        // initial guess = 48/17 - (32/17)*D_normalized
        x = CONST_48_17 - mul(CONST_32_17, D_norm);
        
        // Newton-Raphson iterations: x = x * (2 - x*D)
        for (i = 0; i < ITERATIONS; i = i + 1) begin
            x = mul(x, TWO - mul(x, D_norm));
        end
        if (scale >= 0)
    newton_raphson = x >> scale;
else
    newton_raphson = x << (-scale);
    end
endfunction
 
    always @(*) begin
            result <= mul(numerator, newton_raphson(denominator));
        end

endmodule

main-04.tb.v
`timescale 1ns/1ns
module tb;
    localparam F = 8;           // Fractional bits
    localparam CLK_PERIOD = 1ns; // 10ns clock period
    localparam I_BITS = 8;
    localparam F_BITS = 16;
    localparam TOTAL_BITS = I_BITS + F_BITS;
    reg clk;
    reg reset;
    reg [TOTAL_BITS-1:0] num, den;
    wire [TOTAL_BITS-1:0] result;
    reg [3:0] i;
    integer nums[0:9];
    integer dens[0:9];
    reg [TOTAL_BITS-1:0] results [0:10];
    
    // Instantiate DUT (clocked version)
    newton_raphson #(
        .I_BITS(I_BITS),
        .F_BITS(F_BITS)
    ) dut (
        .numerator(num),
        .denominator(den),
        .result(result)
    );
    task write_results;
        integer fd, j;
        begin
            fd = $fopen("newton_raphson_results.txt", "w");
            if (fd == 0) begin
                $display("ERROR: Could not open output file!");
                $finish;
            end
            for (j = 1; j <=10; j = j + 1) begin
                $fwrite(fd,"%b\n", results[j]);
            end
            $fclose(fd);
        end
    endtask
    // Clock generation
    initial clk = 0;
    always #(CLK_PERIOD/2) clk = ~clk;
    
    // Waveform dumping
    initial begin
        $dumpfile("newton_raphson.vcd");
        $dumpvars(0, tb);
    end
    function [15:0] make_8_8;
        input integer val;
        reg [7:0] int_part;
        int_part = val;
        make_8_8 = {int_part,8'b0};
    endfunction
    always @(posedge clk)begin
        if(reset)begin
            nums[0]<=3;
            dens[0]<=21;
        end
        else if(i<=10) begin
            num<=make_8_8(nums[i]);
            den<=make_8_8(dens[i]);
            results[i]<=result;
            i<=i+1;
        end
    end
    initial begin
        nums[0] = 3;   nums[1] = 7;   nums[2] = 9;   nums[3] = 11;  nums[4] = 17;
        nums[5] = 31;  nums[6] = 41;  nums[7] = 51;  nums[8] = 67;  nums[9] = 81;
        
        dens[0] = 21;  dens[1] = 31;  dens[2] = 41;  dens[3] = 51;  dens[4] = 81;
        dens[5] = 67;  dens[6] = 91;  dens[7] = 101; dens[8] = 131; dens[9] = 151;
    end
    initial begin
        // Initialize
        reset = 1;
        i=0;

        #(CLK_PERIOD*2);
        
        reset = 0;
        #(CLK_PERIOD *30);
        write_results();
        $finish;
    end

endmodule

newton_raphson.vcd
$date
	Tue Mar 31 17:33:09 2026
$end
$version
	Icarus Verilog
$end
$timescale
	1ns
$end
$scope module tb $end
$var wire 24 ! result [23:0] $end
$var real 1 " CLK_PERIOD $end
$var parameter 32 # F $end
$var parameter 32 $ F_BITS $end
$var parameter 32 % I_BITS $end
$var parameter 33 & TOTAL_BITS $end
$var reg 1 ' clk $end
$var reg 24 ( den [23:0] $end
$var reg 4 ) i [3:0] $end
$var reg 24 * num [23:0] $end
$var reg 1 + reset $end
$scope function make_8_8 $end
$var reg 8 , int_part [7:0] $end
$var integer 32 - val [31:0] $end
$upscope $end
$scope module dut $end
$var wire 24 . denominator [23:0] $end
$var wire 24 / numerator [23:0] $end
$var parameter 32 0 F_BITS $end
$var parameter 47 1 HALF $end
$var parameter 32 2 ITERATIONS $end
$var parameter 32 3 I_BITS $end
$var parameter 48 4 ONE $end
$var parameter 33 5 TOTAL_BITS $end
$var reg 24 6 result [23:0] $end
$scope function compute_scale $end
$var reg 24 7 D_func [23:0] $end
$var reg 24 8 D_in [23:0] $end
$var integer 32 9 i [31:0] $end
$var integer 32 : scale [31:0] $end
$upscope $end
$scope function mul $end
$var reg 24 ; a [23:0] $end
$var reg 24 < b [23:0] $end
$var reg 48 = product [47:0] $end
$upscope $end
$scope function newton_raphson $end
$var reg 24 > D [23:0] $end
$var reg 24 ? D_norm [23:0] $end
$var reg 24 @ x [23:0] $end
$var integer 32 A i [31:0] $end
$var integer 32 B scale [31:0] $end
$scope begin $unm_blk_8 $end
$var parameter 24 C CONST_32_17 $end
$var parameter 24 D CONST_48_17 $end
$var parameter 24 E TWO $end
$upscope $end
$upscope $end
$scope function normalize $end
$var reg 24 F D_in [23:0] $end
$var reg 24 G D_out [23:0] $end
$var integer 32 H i [31:0] $end
$upscope $end
$upscope $end
$scope task write_results $end
$var integer 32 I fd [31:0] $end
$var integer 32 J j [31:0] $end
$upscope $end
$upscope $end
$enddefinitions $end
$comment Show the parameter values. $end
$dumpall
b100000000000000000 E
b101101001100010000 D
b11110001000001011 C
b11000 5
b10000000000000000 4
b1000 3
b1000 2
b1000000000000000 1
b10000 0
b11000 &
b1000 %
b10000 $
b1000 #
r1 "
$end
#0
$dumpvars
bx J
bx I
bx H
bx G
bx F
bx B
bx A
bx @
bx ?
bx >
bx =
bx <
bx ;
bx :
bx 9
bx 8
bx 7
bx 6
bx /
bx .
bx -
bx ,
1+
bx *
b0 )
bx (
0'
bx !
$end
#1
1'
#2
0'
0+
#3
b10010010010010 !
b10010010010010 6
b1000 A
b11000011000011001 @
b100100100100100101100000000000 =
b1100000000 ;
b11000011000011001000 <
b11111111111111111111111111111101 B
b11000 9
b1010100000000000 7
b11111111111111111111111111111101 :
b1010100000000 8
b1010100000000000 ?
b11000 H
b1010100000000000 G
b1010100000000 F
b1010100000000 >
b1 )
b1010100000000 (
b1010100000000 .
b1100000000 *
b1100000000 /
b10101 ,
b10101 -
1'
#4
0'
#5
b11100111001110 !
b11100111001110 6
b1000 A
b10000100001000011 @
b111001110011101010100000000000 =
b11100000000 ;
b10000100001000011000 <
b11000 9
b1111100000000000 7
b11111111111111111111111111111101 :
b1111100000000 8
b1111100000000000 ?
b11000 H
b1111100000000000 G
b1111100000000 F
b1111100000000 >
b10 )
b1111100000000 (
b1111100000000 .
b11100000000 *
b11100000000 /
b11111 ,
b11111 -
1'
#6
0'
#7
b11100000110010 !
b11100000110010 6
b1000 A
b11000111110011101 @
b111000001100100001010000000000 =
b100100000000 ;
b1100011111001110100 <
b11111111111111111111111111111110 B
b11000 9
b1010010000000000 7
b11111111111111111111111111111110 :
b10100100000000 8
b1010010000000000 ?
b11000 H
b1010010000000000 G
b10100100000000 F
b10100100000000 >
b11 )
b10100100000000 (
b10100100000000 .
b100100000000 *
b100100000000 /
b101001 ,
b101001 -
1'
#8
0'
#9
b11011100110111 !
b11011100110111 6
b1000 A
b10100000101000010 @
b110111001101110101100000000000 =
b101100000000 ;
b1010000010100001000 <
b11000 9
b1100110000000000 7
b11111111111111111111111111111110 :
b11001100000000 8
b1100110000000000 ?
b11000 H
b1100110000000000 G
b11001100000000 F
b11001100000000 >
b100 )
b11001100000000 (
b11001100000000 .
b101100000000 *
b101100000000 /
b110011 ,
b110011 -
1'
#10
0'
#11
b11010110111010 !
b11010110111010 6
b1000 A
b11001010010001100 @
b110101101110101001100000000000 =
b1000100000000 ;
b110010100100011000 <
b11111111111111111111111111111111 B
b11000 9
b1010001000000000 7
b11111111111111111111111111111111 :
b101000100000000 8
b1010001000000000 ?
b11000 H
b1010001000000000 G
b101000100000000 F
b101000100000000 >
b101 )
b101000100000000 (
b101000100000000 .
b1000100000000 *
b1000100000000 /
b1010001 ,
b1010001 -
1'
#12
0'
#13
b111011001110010 !
b111011001110010 6
b1000 A
b11110100100010100 @
b1110110011100101101100000000000 =
b1111100000000 ;
b111101001000101000 <
b11000 9
b1000011000000000 7
b11111111111111111111111111111111 :
b100001100000000 8
b1000011000000000 ?
b11000 H
b1000011000000000 G
b100001100000000 F
b100001100000000 >
b110 )
b100001100000000 (
b100001100000000 .
b1111100000000 *
b1111100000000 /
b1000011 ,
b1000011 -
1'
#14
0'
#15
b111001101010111 !
b111001101010111 6
b1000 A
b10110100000010111 @
b1110011010101110101111000000000 =
b10100100000000 ;
b101101000000101110 <
b11000 9
b1011011000000000 7
b11111111111111111111111111111111 :
b101101100000000 8
b1011011000000000 ?
b11000 H
b1011011000000000 G
b101101100000000 F
b101101100000000 >
b111 )
b101101100000000 (
b101101100000000 .
b10100100000000 *
b10100100000000 /
b1011011 ,
b1011011 -
1'
#16
0'
#17
b1000000101000100 !
b1000000101000100 6
b1000 A
b10100010001110000 @
b10000001010001001010000000000000 =
b11001100000000 ;
b101000100011100000 <
b11000 9
b1100101000000000 7
b11111111111111111111111111111111 :
b110010100000000 8
b1100101000000000 ?
b11000 H
b1100101000000000 G
b110010100000000 F
b110010100000000 >
b1000 )
b110010100000000 (
b110010100000000 .
b11001100000000 *
b11001100000000 /
b1100101 ,
b1100101 -
1'
#18
0'
#19
b1000001011101110 !
b1000001011101110 6
b1000 A
b11111010001000111 @
b10000010111011101001010100000000 =
b100001100000000 ;
b11111010001000111 <
b0 B
b11000 9
b1000001100000000 7
b0 :
b1000001100000000 8
b1000001100000000 ?
b11000 H
b1000001100000000 G
b1000001100000000 F
b1000001100000000 >
b1001 )
b1000001100000000 (
b1000001100000000 .
b100001100000000 *
b100001100000000 /
b10000011 ,
b10000011 -
1'
#20
0'
#21
b1000100101010011 !
b1000100101010011 6
b1000 A
b11011001000000100 @
b10001001010100110100010000000000 =
b101000100000000 ;
b11011001000000100 <
b11000 9
b1001011100000000 7
b1001011100000000 8
b1001011100000000 ?
b11000 H
b1001011100000000 G
b1001011100000000 F
b1001011100000000 >
b1010 )
b1001011100000000 (
b1001011100000000 .
b101000100000000 *
b101000100000000 /
b10010111 ,
b10010111 -
1'
#22
0'
#23
bx !
bx 6
b1000 A
bx @
bx =
b0xxxxxxxx00000000 ;
bx <
b11000 9
b0xxxxxxxx00000000 7
b0xxxxxxxx00000000 8
b0xxxxxxxx00000000 ?
b11000 H
b0xxxxxxxx00000000 G
b0xxxxxxxx00000000 F
b0xxxxxxxx00000000 >
b1011 )
b0xxxxxxxx00000000 (
b0xxxxxxxx00000000 .
b0xxxxxxxx00000000 *
b0xxxxxxxx00000000 /
bx ,
bx -
1'
#24
0'
#25
1'
#26
0'
#27
1'
#28
0'
#29
1'
#30
0'
#31
1'
#32
0'
b1011 J
b10000000000000000000000000000011 I
