direct-form.v
module fir_direct (
    input wire clk,
    input wire rst_n,
    input wire [15:0] coeffs [0:99], 
    input wire [15:0] din,
    output reg [31:0] dout
);
    parameter TAPS = 100;
    
    // Delay line
    reg [15:0] delay_line [0:TAPS-1];
    
    // Accumulator
    reg [31:0] next_accum;
    integer i;
    
    // Shift register (always runs)
    always @(posedge clk or negedge rst_n) begin
        if (rst_n) begin
            for (i = 0; i < TAPS; i = i + 1)
                delay_line[i] <= 16'b0;
            dout <= 32'b0;
        end
        else begin
            // Shift every clock cycle
            for (i = TAPS-1; i > 0; i = i - 1)
                delay_line[i] <= delay_line[i-1];
            delay_line[0] <= din;
            dout <= next_accum;
        end
    end
    
    // Compute output every cycle
    always @* begin
        next_accum = 32'b0;
        for (i = 0; i < TAPS; i = i + 1)
            next_accum = next_accum + (delay_line[i] * coeffs[i]);
    end
    
endmodule

direct-form_tb.v
module tb_fir_direct();
    reg clk, rst_n;
    wire [31:0] dout;
    reg [15:0] din;
    reg [15:0] coeffs [0:99];
    reg [15:0] samples [0:1999];
    reg [31:0] out [0:499];
    integer idx;
    
    fir_direct u_dut (
        .clk(clk),
        .rst_n(rst_n),
        .din(din),
        .dout(dout),
        .coeffs(coeffs)
    );
    
    initial clk = 0;
    always #1 clk = ~clk;

    always @(posedge clk)begin
        if(rst_n)begin
            idx<=0;
            din<=16'b0;
        end
        else begin
            if(idx<501)begin
                din<=samples[idx];
                out[idx]<=dout;
                idx = idx+1;
            end
        end
    end

    task read_coeffs;
       integer  coeff_file;
       integer  i;
        coeff_file = $fopen("fc_quantized_2_14.txt", "r");
        for (i = 0; i < 100; i = i + 1)
            $fscanf(coeff_file, "%b\n", coeffs[i]);
        $fclose(coeff_file);
        $display("Read 100 coefficients");

    endtask;

    task read_q_2_14_950;
        integer in_file;
        integer  idx;
        in_file = $fopen("q_2_14_950.txt", "r");
        idx = 0;
        while (!$feof(in_file) && idx < 600) begin
            $fscanf(in_file, "%b\n", samples[idx]);
            idx = idx + 1;
        end
        $fclose(in_file);
    endtask;

    task writeFiles;
       integer j,out_file;
        out_file = $fopen("out_950_verilog.txt","w");
        for(j=0;j<500;j++)begin
            $fwrite(out_file,"%b\n",out[j]);
        end
    endtask;

    initial begin
        $dumpfile("wave-05.vcd"); 
        $dumpvars(0, tb_fir_direct);
    end
    initial begin
        rst_n = 1;
        idx =0;

        read_coeffs();
        read_q_2_14_950();

        #2;
        rst_n = 0;

        #10002;
      
        writeFiles();
        $finish;
    end
   
endmodule

wave-05.vcd
$date
	Wed Mar  4 23:34:22 2026
$end
$version
	Icarus Verilog
$end
$timescale
	1s
$end
$scope module tb_fir_direct $end
$var wire 32 ! dout [31:0] $end
$var reg 1 " clk $end
$var reg 16 # din [15:0] $end
$var reg 1 $ rst_n $end
$var integer 32 % idx [31:0] $end
$scope module u_dut $end
$var wire 1 " clk $end
$var wire 16 & din [15:0] $end
$var wire 1 $ rst_n $end
$var parameter 32 ' TAPS $end
$var reg 32 ( dout [31:0] $end
$var reg 32 ) next_accum [31:0] $end
$var integer 32 * i [31:0] $end
$upscope $end
$scope task read_coeffs $end
$var integer 32 + coeff_file [31:0] $end
$var integer 32 , i [31:0] $end
$upscope $end
$scope task read_q_2_14_950 $end
$var integer 32 - idx [31:0] $end
$var integer 32 . in_file [31:0] $end
$upscope $end
$scope task writeFiles $end
$var integer 32 / j [31:0] $end
$var integer 32 0 out_file [31:0] $end
$upscope $end
$upscope $end
$enddefinitions $end
$comment Show the parameter values. $end
$dumpall
b1100100 '
$end
#0
$dumpvars
bx 0
bx /
b10000000000000000000000000000011 .
b1001011000 -
b1100100 ,
b10000000000000000000000000000011 +
b1100100 *
bx )
bx (
bx &
b0 %
1$
bx #
0"
bx !
$end
#1
b0 )
b0 !
b0 (
b0 #
b0 &
b1100100 *
1"
#2
b0 *
0"
0$
#3
b0 *
b1 %
1"
#4
0"
#5
b10001111111001 #
b10001111111001 &
b0 *
b10 %
1"
#6
0"
#7
b100011111110001001010000010101 )
b11101110000001 #
b11101110000001 &
b1100100 *
b11 %
1"
#8
0"
#9
b1011111011110000101000110101110 )
b100011111110001001010000010101 !
b100011111110001001010000010101 (
b11111001110101 #
b11111001110101 &
b1100100 *
b100 %
1"
#10
0"
#11
b10011101111010110110000001011001 )
b1011111011110000101000110101110 !
b1011111011110000101000110101110 (
b10101111010000 #
b10101111010000 &
b1100100 *
b101 %
1"
#12
0"
#13
b11001001101110011001000000001100 )
b10011101111010110110000001011001 !
b10011101111010110110000001011001 (
b101000000011 #
b101000000011 &
b1100100 *
b110 %
1"
#14
0"
#15
b11010011101111000011010100110111 )
b11001001101110011001000000001100 !
b11001001101110011001000000001100 (
b1110010011000000 #
b1110010011000000 &
b1100100 *
b111 %
1"
#16
0"
#17
b10010100100000100110101100010100 )
b11010011101111000011010100110111 !
b11010011101111000011010100110111 (
b1100100011101010 #
b1100100011101010 &
b1100100 *
b1000 %
1"
#18
0"
#19
b100001111010010110100110111111 )
b10010100100000100110101100010100 !
b10010100100000100110101100010100 (
b1100000000100000 #
b1100000000100000 &
b1100100 *
b1001 %
1"
#20
0"
#21
b10100011100100100000011011101000 )
b100001111010010110100110111111 !
b100001111010010110100110111111 (
b1100110101101110 #
b1100110101101110 &
b1100100 *
b1010 %
1"
#22
0"
#23
b1000101001011011101010100000111 )
b10100011100100100000011011101000 !
b10100011100100100000011011101000 (
b1110110000111001 #
b1110110000111001 &
b1100100 *
b1011 %
1"
#24
0"
#25
b100111011000101011001001011110 )
b1000101001011011101010100000111 !
b1000101001011011101010100000111 (
b1000111011011 #
b1000111011011 &
b1100100 *
b1100 %
1"
#26
0"
#27
b1111000011110010010011000110010 )
b100111011000101011001001011110 !
b100111011000101011001001011110 (
b11000101010000 #
b11000101010000 &
b1100100 *
b1101 %
1"
#28
0"
#29
b11100011001101100101110000001 )
b1111000011110010010011000110010 !
b1111000011110010010011000110010 (
b11111110110111 #
b11111110110111 &
b1100100 *
b1110 %
1"
#30
0"
#31
b11011010011110110110111111000001 )
b11100011001101100101110000001 !
b11100011001101100101110000001 (
b11100000010101 #
b11100000010101 &
b1100100 *
b1111 %
1"
#32
0"
#33
b1110000111110101100111010011101 )
b11011010011110110110111111000001 !
b11011010011110110110111111000001 (
b1110100001110 #
b1110100001110 &
b1100100 *
b10000 %
1"
#34
0"
#35
b10101011110101101011101001011010 )
b1110000111110101100111010011101 !
b1110000111110101100111010011101 (
b1111011111111011 #
b1111011111111011 &
b1100100 *
b10001 %
1"
#36
0"
#37
b1010010101110000101001111111110 )
b10101011110101101011101001011010 !
b10101011110101101011101001011010 (
b1101010110101101 #
b1101010110101101 &
b1100100 *
b10010 %
1"
#38
0"
#39
b10000100011011100010010101110100 )
b1010010101110000101001111111110 !
b1010010101110000101001111111110 (
b1100001000000011 #
b1100001000000011 &
b1100100 *
b10011 %
1"
#40
0"
#41
b10001000010011110100001000101000 )
b10000100011011100010010101110100 !
b10000100011011100010010101110100 (
b1100001111001001 #
b1100001111001001 &
b1100100 *
b10100 %
1"
#42
0"
#43
b10110101100011010011001110111110 )
b10001000010011110100001000101000 !
b10001000010011110100001000101000 (
b1101101001100010 #
b1101101001100010 &
b1100100 *
b10101 %
1"
#44
0"
#45
b1010101000011101000010011110110 )
b10110101100011010011001110111110 !
b10110101100011010011001110111110 (
b1111110111111101 #
b1111110111111101 &
b1100100 *
b10110 %
1"
#46
0"
#47
b10101100001011010110010011111011 )
b1010101000011101000010011110110 !
b1010101000011101000010011110110 (
b10001001001011 #
b10001001001011 &
b1100100 *
b10111 %
1"
#48
0"
#49
b10011100110100010010100000000100 )
b10101100001011010110010011111011 !
b10101100001011010110010011111011 (
b11101010111100 #
b11101010111100 &
b1100100 *
b11000 %
1"
#50
0"
#51
b11010011110000110010111000111001 )
b10011100110100010010100000000100 !
b10011100110100010010100000000100 (
b11111011011110 #
b11111011011110 &
b1100100 *
b11001 %
1"
#52
0"
#53
b11100101011110101100100000110101 )
b11010011110000110010111000111001 !
b11010011110000110010111000111001 (
b10110101000001 #
b10110101000001 &
b1100100 *
b11010 %
1"
#54
0"
#55
b1110011010010000110011111010100 )
b11100101011110101100100000110101 !
b11100101011110101100100000110101 (
b101111111110 #
b101111111110 &
b1100100 *
b11011 %
1"
#56
0"
#57
b101000001000100111110001010001 )
b1110011010010000110011111010100 !
b1110011010010000110011111010100 (
b1110011010010101 #
b1110011010010101 &
b1100100 *
b11100 %
1"
#58
0"
#59
b11101111110011110011101100010 )
b101000001000100111110001010001 !
b101000001000100111110001010001 (
b1100100111110111 #
b1100100111110111 &
b1100100 *
b11101 %
1"
#60
0"
#61
b10110000110101110111011111111011 )
b11101111110011110011101100010 !
b11101111110011110011101100010 (
b1100000000001000 #
b1100000000001000 &
b1100100 *
b11110 %
1"
#62
0"
#63
b1011111000000001100111010001100 )
b10110000110101110111011111111011 !
b10110000110101110111011111111011 (
b1100110000111001 #
b1100110000111001 &
b1100100 *
b11111 %
1"
#64
0"
#65
b10011101010101011011100111110001 )
b1011111000000001100111010001100 !
b1011111000000001100111010001100 (
b1110101001010010 #
b1110101001010010 &
b1100100 *
b100000 %
1"
#66
0"
#67
b11010010110101011100001001010010 )
b10011101010101011011100111110001 !
b10011101010101011011100111110001 (
b111111101011 #
b111111101011 &
b1100100 *
b100001 %
1"
#68
0"
#69
b11101101000100101011000100001110 )
b11010010110101011100001001010010 !
b11010010110101011100001001010010 (
b11000000000010 #
b11000000000010 &
b1100100 *
b100010 %
1"
#70
0"
#71
b10001010011101111001011011100011 )
b11101101000100101011000100001110 !
b11101101000100101011000100001110 (
b11111101111111 #
b11111101111111 &
b1100100 *
b100011 %
1"
#72
0"
#73
b11100000011011100101100010010 )
b10001010011101111001011011100011 !
b10001010011101111001011011100011 (
b11100100000110 #
b11100100000110 &
b1100100 *
b100100 %
1"
#74
0"
#75
b10110111000110011001111011110 )
b11100000011011100101100010010 !
b11100000011011100101100010010 (
b1111011010101 #
b1111011010101 &
b1100100 *
b100101 %
1"
#76
0"
#77
b1011010000011011010100 )
b10110111000110011001111011110 !
b10110111000110011001111011110 (
b1111100111111010 #
b1111100111111010 &
b1100100 *
b100110 %
1"
#78
0"
#79
b11011111101010110000110110111101 )
b1011010000011011010100 !
b1011010000011011010100 (
b1101011100110100 #
b1101011100110100 &
b1100100 *
b100111 %
1"
#80
0"
#81
b11001000101110110110111000000 )
b11011111101010110000110110111101 !
b11011111101010110000110110111101 (
b1100001010001011 #
b1100001010001011 &
b1100100 *
b101000 %
1"
#82
0"
#83
b1001001101010010111100101111100 )
b11001000101110110110111000000 !
b11001000101110110110111000000 (
b1100001100100010 #
b1100001100100010 &
b1100100 *
b101001 %
1"
#84
0"
#85
b10001101110111001101101110001 )
b1001001101010010111100101111100 !
b1001001101010010111100101111100 (
b1101100011000110 #
b1101100011000110 &
b1100100 *
b101010 %
1"
#86
0"
#87
b1010001011100101000011011 )
b10001101110111001101101110001 !
b10001101110111001101101110001 (
b1111101111111011 #
b1111101111111011 &
b1100100 *
b101011 %
1"
#88
0"
#89
b11110000111000001010110001110 )
b1010001011100101000011011 !
b1010001011100101000011011 (
b10000010010100 #
b10000010010100 &
b1100100 *
b101100 %
1"
#90
0"
#91
b101110100001110111111001011 )
b11110000111000001010110001110 !
b11110000111000001010110001110 (
b11100111101001 #
b11100111101001 &
b1100100 *
b101101 %
1"
#92
0"
#93
b1111101101100101100010101011 )
b101110100001110111111001011 !
b101110100001110111111001011 (
b11111100110110 #
b11111100110110 &
b1100100 *
b101110 %
1"
#94
0"
#95
b10000111001100001110001000101001 )
b1111101101100101100010101011 !
b1111101101100101100010101011 (
b10111010100111 #
b10111010100111 &
b1100100 *
b101111 %
1"
#96
0"
#97
b11000110010001011010011000011010 )
b10000111001100001110001000101001 !
b10000111001100001110001000101001 (
b110111110110 #
b110111110110 &
b1100100 *
b110000 %
1"
#98
0"
#99
b10110111000001101110011011110001 )
b11000110010001011010011000011010 !
b11000110010001011010011000011010 (
b1110100001110001 #
b1110100001110001 &
b1100100 *
b110001 %
1"
#100
0"
#101
b10110111010110011000010110110011 )
b10110111000001101110011011110001 !
b10110111000001101110011011110001 (
b1100101100010001 #
b1100101100010001 &
b1100100 *
b110010 %
1"
#102
0"
#103
b1111000100110101101001001110101 )
b10110111010110011000010110110011 !
b10110111010110011000010110110011 (
b1100000000000000 #
b1100000000000000 &
b1100100 *
b110011 %
1"
#104
0"
#105
b11000010011001011010011111111000 )
b1111000100110101101001001110101 !
b1111000100110101101001001110101 (
b1100101100010001 #
b1100101100010001 &
b1100100 *
b110100 %
1"
#106
0"
#107
b101101100001101100000001101010 )
b11000010011001011010011111111000 !
b11000010011001011010011111111000 (
b1110100001110001 #
b1110100001110001 &
b1100100 *
b110101 %
1"
#108
0"
#109
b11101111000110100000110011101011 )
b101101100001101100000001101010 !
b101101100001101100000001101010 (
b110111110110 #
b110111110110 &
b1100100 *
b110110 %
1"
#110
0"
#111
b11000101111110101001011111000001 )
b11101111000110100000110011101011 !
b11101111000110100000110011101011 (
b10111010100111 #
b10111010100111 &
b1100100 *
b110111 %
1"
#112
0"
#113
b10001000110110010110100001001 )
b11000101111110101001011111000001 !
b11000101111110101001011111000001 (
b11111100110110 #
b11111100110110 &
b1100100 *
b111000 %
1"
#114
0"
#115
b110111111010100010110010011 )
b10001000110110010110100001001 !
b10001000110110010110100001001 (
b11100111101001 #
b11100111101001 &
b1100100 *
b111001 %
1"
#116
0"
#117
b11111001101101001110001100011 )
b110111111010100010110010011 !
b110111111010100010110010011 (
b10000010010100 #
b10000010010100 &
b1100100 *
b111010 %
1"
#118
0"
#119
b11111001100011101000100111011101 )
b11111001101101001110001100011 !
b11111001101101001110001100011 (
b1111101111111011 #
b1111101111111011 &
b1100100 *
b111011 %
1"
#120
0"
#121
b10100011010100111111111001011111 )
b11111001100011101000100111011101 !
b11111001100011101000100111011101 (
b1101100011000110 #
b1101100011000110 &
b1100100 *
b111100 %
1"
#122
0"
#123
b10010010110100110011000011100011 )
b10100011010100111111111001011111 !
b10100011010100111111111001011111 (
b1100001100100010 #
b1100001100100010 &
b1100100 *
b111101 %
1"
#124
0"
#125
b1111110100111110000111000010011 )
b10010010110100110011000011100011 !
b10010010110100110011000011100011 (
b1100001010001011 #
b1100001010001011 &
b1100100 *
b111110 %
1"
#126
0"
#127
b11111010100101111011111001101011 )
b1111110100111110000111000010011 !
b1111110100111110000111000010011 (
b1101011100110100 #
b1101011100110100 &
b1100100 *
b111111 %
1"
#128
0"
#129
b10001100111001100010110010101000 )
b11111010100101111011111001101011 !
b11111010100101111011111001101011 (
b1111100111111010 #
b1111100111111010 &
b1100100 *
b1000000 %
1"
#130
0"
#131
b1011011100110101010011000001110 )
b10001100111001100010110010101000 !
b10001100111001100010110010101000 (
b1111011010101 #
b1111011010101 &
b1100100 *
b1000001 %
1"
#132
0"
#133
b11111100100100000111010011011 )
b1011011100110101010011000001110 !
b1011011100110101010011000001110 (
b11100100000110 #
b11100100000110 &
b1100100 *
b1000010 %
1"
#134
0"
#135
b111100111011110111001100111110 )
b11111100100100000111010011011 !
b11111100100100000111010011011 (
b11111101111111 #
b11111101111111 &
b1100100 *
b1000011 %
1"
#136
0"
#137
b11100111010101101111101110110 )
b111100111011110111001100111110 !
b111100111011110111001100111110 (
b11000000000010 #
b11000000000010 &
b1100100 *
b1000100 %
1"
#138
0"
#139
b11001111000000000011101100101 )
b11100111010101101111101110110 !
b11100111010101101111101110110 (
b111111101011 #
b111111101011 &
b1100100 *
b1000101 %
1"
#140
0"
#141
b11011100100011001000111000001000 )
b11001111000000000011101100101 !
b11001111000000000011101100101 (
b1110101001010010 #
b1110101001010010 &
b1100100 *
b1000110 %
1"
#142
0"
#143
b1111010001010110011001101010000 )
b11011100100011001000111000001000 !
b11011100100011001000111000001000 (
b1100110000111001 #
b1100110000111001 &
b1100100 *
b1000111 %
1"
#144
0"
#145
b1101101001010111111000111101101 )
b1111010001010110011001101010000 !
b1111010001010110011001101010000 (
b1100000000001000 #
b1100000000001000 &
b1100100 *
b1001000 %
1"
#146
0"
#147
b1000110111001100101111101000100 )
b1101101001010111111000111101101 !
b1101101001010111111000111101101 (
b1100100111110111 #
b1100100111110111 &
b1100100 *
b1001001 %
1"
#148
0"
#149
b11000101010111110111000001110110 )
b1000110111001100101111101000100 !
b1000110111001100101111101000100 (
b1110011010010101 #
b1110011010010101 &
b1100100 *
b1001010 %
1"
#150
0"
#151
b1101101100110001000001100011000 )
b11000101010111110111000001110110 !
b11000101010111110111000001110110 (
b101111111110 #
b101111111110 &
b1100100 *
b1001011 %
1"
#152
0"
#153
b1011101101001001111001111101101 )
b1101101100110001000001100011000 !
b1101101100110001000001100011000 (
b10110101000001 #
b10110101000001 &
b1100100 *
b1001100 %
1"
#154
0"
#155
b1000010001110100100100011000001 )
b1011101101001001111001111101101 !
b1011101101001001111001111101101 (
b11111011011110 #
b11111011011110 &
b1100100 *
b1001101 %
1"
#156
0"
#157
b10010111100000000001101101011101 )
b1000010001110100100100011000001 !
b1000010001110100100100011000001 (
b11101010111100 #
b11101010111100 &
b1100100 *
b1001110 %
1"
#158
0"
#159
b10001110101011100110110001101010 )
b10010111100000000001101101011101 !
b10010111100000000001101101011101 (
b10001001001011 #
b10001001001011 &
b1100100 *
b1001111 %
1"
#160
0"
#161
b1111001100101111110111011010010 )
b10001110101011100110110001101010 !
b10001110101011100110110001101010 (
b1111110111111101 #
b1111110111111101 &
b1100100 *
b1010000 %
1"
#162
0"
#163
b110110111111111101000101010 )
b1111001100101111110111011010010 !
b1111001100101111110111011010010 (
b1101101001100010 #
b1101101001100010 &
b1100100 *
b1010001 %
1"
#164
0"
#165
b1011110001010101000101101101010 )
b110110111111111101000101010 !
b110110111111111101000101010 (
b1100001111001001 #
b1100001111001001 &
b1100100 *
b1010010 %
1"
#166
0"
#167
b11101110011011110010110010001000 )
b1011110001010101000101101101010 !
b1011110001010101000101101101010 (
b1100001000000011 #
b1100001000000011 &
b1100100 *
b1010011 %
1"
#168
0"
#169
b10001111100011011101000100010010 )
b11101110011011110010110010001000 !
b11101110011011110010110010001000 (
b1101010110101101 #
b1101010110101101 &
b1100100 *
b1010100 %
1"
#170
0"
#171
b10011101010110001001010100000 )
b10001111100011011101000100010010 !
b10001111100011011101000100010010 (
b1111011111111011 #
b1111011111111011 &
b1100100 *
b1010101 %
1"
#172
0"
#173
b11111110011101111000011001010110 )
b10011101010110001001010100000 !
b10011101010110001001010100000 (
b1110100001110 #
b1110100001110 &
b1100100 *
b1010110 %
1"
#174
0"
#175
b1010111101000010001101111100000 )
b11111110011101111000011001010110 !
b11111110011101111000011001010110 (
b11100000010101 #
b11100000010101 &
b1100100 *
b1010111 %
1"
#176
0"
#177
b11001100000101100010010100010011 )
b1010111101000010001101111100000 !
b1010111101000010001101111100000 (
b11111110110111 #
b11111110110111 &
b1100100 *
b1011000 %
1"
#178
0"
#179
b10000010110001101101110001001001 )
b11001100000101100010010100010011 !
b11001100000101100010010100010011 (
b11000101010000 #
b11000101010000 &
b1100100 *
b1011001 %
1"
#180
0"
#181
b10001011101001010100101001011111 )
b10000010110001101101110001001001 !
b10000010110001101101110001001001 (
b1000111011011 #
b1000111011011 &
b1100100 *
b1011010 %
1"
#182
0"
#183
b110010101010110110010101000001 )
b10001011101001010100101001011111 !
b10001011101001010100101001011111 (
b1110110000111001 #
b1110110000111001 &
b1100100 *
b1011011 %
1"
#184
0"
#185
b111110000111010101111011101000 )
b110010101010110110010101000001 !
b110010101010110110010101000001 (
b1100110101101110 #
b1100110101101110 &
b1100100 *
b1011100 %
1"
#186
0"
#187
b11011110100001110001001010100111 )
b111110000111010101111011101000 !
b111110000111010101111011101000 (
b1100000000100000 #
b1100000000100000 &
b1100100 *
b1011101 %
1"
#188
0"
#189
b11100101111001111001000000011001 )
b11011110100001110001001010100111 !
b11011110100001110001001010100111 (
b1100100011101010 #
b1100100011101010 &
b1100100 *
b1011110 %
1"
#190
0"
#191
b1011011000110101111010011010010 )
b11100101111001111001000000011001 !
b11100101111001111001000000011001 (
b1110010011000000 #
b1110010011000000 &
b1100100 *
b1011111 %
1"
#192
0"
#193
b11110111100110001111100111011 )
b1011011000110101111010011010010 !
b1011011000110101111010011010010 (
b101000000011 #
b101000000011 &
b1100100 *
b1100000 %
1"
#194
0"
#195
b10011110011111010001000111000100 )
b11110111100110001111100111011 !
b11110111100110001111100111011 (
b10101111010000 #
b10101111010000 &
b1100100 *
b1100001 %
1"
#196
0"
#197
b11010001010001011011010010111011 )
b10011110011111010001000111000100 !
b10011110011111010001000111000100 (
b11111001110101 #
b11111001110101 &
b1100100 *
b1100010 %
1"
#198
0"
#199
b11110100010110111001101010001101 )
b11010001010001011011010010111011 !
b11010001010001011011010010111011 (
b11101110000001 #
b11101110000001 &
b1100100 *
b1100011 %
1"
#200
0"
#201
b11110001101110100110100011000000 )
b11110100010110111001101010001101 !
b11110100010110111001101010001101 (
b10001111111001 #
b10001111111001 &
b1100100 *
b1100100 %
1"
#202
0"
#203
b11000000011111001000010010000011 )
b11110001101110100110100011000000 !
b11110001101110100110100011000000 (
b0 #
b0 &
b1100100 *
b1100101 %
1"
#204
0"
#205
b11000000011111001000010010000011 )
b11000000011111001000010010000011 !
b11000000011111001000010010000011 (
b1101110000000111 #
b1101110000000111 &
b1100100 *
b1100110 %
1"
#206
0"
#207
b11001101101111101101010010101011 )
b1100010001111111 #
b1100010001111111 &
b1100100 *
b1100111 %
1"
#208
0"
#209
b10010100110110010100100011011111 )
b11001101101111101101010010101011 !
b11001101101111101101010010101011 (
b1100000110001011 #
b1100000110001011 &
b1100100 *
b1101000 %
1"
#210
0"
#211
b110011010001110101010001100010 )
b10010100110110010100100011011111 !
b10010100110110010100100011011111 (
b1101010000110000 #
b1101010000110000 &
b1100100 *
b1101001 %
1"
#212
0"
#213
b11010100101010001000000110111000 )
b110011010001110101010001100010 !
b110011010001110101010001100010 (
b1111010111111101 #
b1111010111111101 &
b1100100 *
b1101010 %
1"
#214
0"
#215
b1001011000110001110101000000100 )
b11010100101010001000000110111000 !
b11010100101010001000000110111000 (
b1101101000000 #
b1101101000000 &
b1100100 *
b1101011 %
1"
#216
0"
#217
b11000110011111101000100110111110 )
b1001011000110001110101000000100 !
b1001011000110001110101000000100 (
b11011100010110 #
b11011100010110 &
b1100100 *
b1101100 %
1"
#218
0"
#219
b11000011111011110010011001011010 )
b11000110011111101000100110111110 !
b11000110011111101000100110111110 (
b11111111100000 #
b11111111100000 &
b1100100 *
b1101101 %
1"
#220
0"
#221
b111010111101010000101110111111 )
b11000011111011110010011001011010 !
b11000011111011110010011001011010 (
b11001010010010 #
b11001010010010 &
b1100100 *
b1101110 %
1"
#222
0"
#223
b11111000111111011000100111100001 )
b111010111101010000101110111111 !
b111010111101010000101110111111 (
b1001111000111 #
b1001111000111 &
b1100100 *
b1101111 %
1"
#224
0"
#225
b1011010111001011001011100011 )
b11111000111111011000100111100001 !
b11111000111111011000100111100001 (
b1110111000100101 #
b1110111000100101 &
b1100100 *
b1110000 %
1"
#226
0"
#227
b10011001110010010010000101101 )
b1011010111001011001011100011 !
b1011010111001011001011100011 (
b1100111010110000 #
b1100111010110000 &
b1100100 *
b1110001 %
1"
#228
0"
#229
b1100110010110000001000011001000 )
b10011001110010010010000101101 !
b10011001110010010010000101101 (
b1100000001001001 #
b1100000001001001 &
b1100100 *
b1110010 %
1"
#230
0"
#231
b11110001011101011011010101010010 )
b1100110010110000001000011001000 !
b1100110010110000001000011001000 (
b1100011111101011 #
b1100011111101011 &
b1100100 *
b1110011 %
1"
#232
0"
#233
b11100110011001110100110101000011 )
b11110001011101011011010101010010 !
b11110001011101011011010101010010 (
b1110001011110010 #
b1110001011110010 &
b1100100 *
b1110100 %
1"
#234
0"
#235
b1010010010101101100101111111100 )
b11100110011001110100110101000011 !
b11100110011001110100110101000011 (
b100000000101 #
b100000000101 &
b1100100 *
b1110101 %
1"
#236
0"
#237
b11000000101101011011111010100010 )
b1010010010101101100101111111100 !
b1010010010101101100101111111100 (
b10101001010011 #
b10101001010011 &
b1100100 *
b1110110 %
1"
#238
0"
#239
b1011000010001010101110011110 )
b11000000101101011011111010100010 !
b11000000101101011011111010100010 (
b11110111111101 #
b11110111111101 &
b1100100 *
b1110111 %
1"
#240
0"
#241
b1100110001111001110101001100000 )
b1011000010001010101110011110 !
b1011000010001010101110011110 (
b11110000110111 #
b11110000110111 &
b1100100 *
b1111000 %
1"
#242
0"
#243
b10101000111010010101011110101100 )
b1100110001111001110101001100000 !
b1100110001111001110101001100000 (
b10010110011110 #
b10010110011110 &
b1100100 *
b1111001 %
1"
#244
0"
#245
b10110010001100010111010100110100 )
b10101000111010010101011110101100 !
b10101000111010010101011110101100 (
b1000000011 #
b1000000011 &
b1100100 *
b1111010 %
1"
#246
0"
#247
b11001101101101001000100111010111 )
b10110010001100010111010100110100 !
b10110010001100010111010100110100 (
b1101110110110101 #
b1101110110110101 &
b1100100 *
b1111011 %
1"
#248
0"
#249
b11110001111001110100010001100110 )
b11001101101101001000100111010111 !
b11001101101101001000100111010111 (
b1100010101000100 #
b1100010101000100 &
b1100100 *
b1111100 %
1"
#250
0"
#251
b11000011011011111110110100100100 )
b11110001111001110100010001100110 !
b11110001111001110100010001100110 (
b1100000100100010 #
b1100000100100010 &
b1100100 *
b1111101 %
1"
#252
0"
#253
b1011100001001001000000010001100 )
b11000011011011111110110100100100 !
b11000011011011111110110100100100 (
b1101001010111111 #
b1101001010111111 &
b1100100 *
b1111110 %
1"
#254
0"
#255
b11101001101000001000110000011001 )
b1011100001001001000000010001100 !
b1011100001001001000000010001100 (
b1111010000000010 #
b1111010000000010 &
b1100100 *
b1111111 %
1"
#256
0"
#257
b1000100110111100000011011000111 )
b11101001101000001000110000011001 !
b11101001101000001000110000011001 (
b1100101101011 #
b1100101101011 &
b1100100 *
b10000000 %
1"
#258
0"
#259
b10100111001101011000100100010100 )
b1000100110111100000011011000111 !
b1000100110111100000011011000111 (
b11011000001001 #
b11011000001001 &
b1100100 *
b10000001 %
1"
#260
0"
#261
b10010110011010111110011101001001 )
b10100111001101011000100100010100 !
b10100111001101011000100100010100 (
b11111111111000 #
b11111111111000 &
b1100100 *
b10000010 %
1"
#262
0"
#263
b1111000001010010001101100001 )
b10010110011010111110011101001001 !
b10010110011010111110011101001001 (
b11001111000111 #
b11001111000111 &
b1100100 *
b10000011 %
1"
#264
0"
#265
b11011101111000110111100101011111 )
b1111000001010010001101100001 !
b1111000001010010001101100001 (
b1010110101110 #
b1010110101110 &
b1100100 *
b10000100 %
1"
#266
0"
#267
b1010100010111100101110110110 )
b11011101111000110111100101011111 !
b11011101111000110111100101011111 (
b1111000000010101 #
b1111000000010101 &
b1100100 *
b10000101 %
1"
#268
0"
#269
b101100111111100101011001010111 )
b1010100010111100101110110110 !
b1010100010111100101110110110 (
b1100111111111110 #
b1100111111111110 &
b1100100 *
b10000110 %
1"
#270
0"
#271
b10010001110001100100100010010011 )
b101100111111100101011001010111 !
b101100111111100101011001010111 (
b1100000010000001 #
b1100000010000001 &
b1100100 *
b10000111 %
1"
#272
0"
#273
b11111011011111010100000101100 )
b10010001110001100100100010010011 !
b10010001110001100100100010010011 (
b1100011011111010 #
b1100011011111010 &
b1100100 *
b10001000 %
1"
#274
0"
#275
b110111010011101101010111101 )
b11111011011111010100000101100 !
b11111011011111010100000101100 (
b1110000100101011 #
b1110000100101011 &
b1100100 *
b10001001 %
1"
#276
0"
#277
b1011010000000111001111100111010 )
b110111010011101101010111101 !
b110111010011101101010111101 (
b11000000110 #
b11000000110 &
b1100100 *
b10001010 %
1"
#278
0"
#279
b10101100110110000001111011101011 )
b1011010000000111001111100111010 !
b1011010000000111001111100111010 (
b10100011001100 #
b10100011001100 &
b1100100 *
b10001011 %
1"
#280
0"
#281
b11100010100001010101000010101011 )
b10101100110110000001111011101011 !
b10101100110110000001111011101011 (
b11110101110101 #
b11110101110101 &
b1100100 *
b10001100 %
1"
#282
0"
#283
b110111001111101001010010010111 )
b11100010100001010101000010101011 !
b11100010100001010101000010101011 (
b11110011011110 #
b11110011011110 &
b1100100 *
b10001101 %
1"
#284
0"
#285
b10000011111010111001010101110010 )
b110111001111101001010010010111 !
b110111001111101001010010010111 (
b10011100111010 #
b10011100111010 &
b1100100 *
b10001110 %
1"
#286
0"
#287
b10100100010001100011010001000100 )
b10000011111010111001010101110010 !
b10000011111010111001010101110010 (
b10000000101 #
b10000000101 &
b1100100 *
b10001111 %
1"
#288
0"
#289
b11011011110110010111010001001111 )
b10100100010001100011010001000100 !
b10100100010001100011010001000100 (
b1101111101101100 #
b1101111101101100 &
b1100100 *
b10010000 %
1"
#290
0"
#291
b10111001101111010110010011000 )
b11011011110110010111010001001111 !
b11011011110110010111010001001111 (
b1100011000010111 #
b1100011000010111 &
b1100100 *
b10010001 %
1"
#292
0"
#293
b11110010101001111110110011101000 )
b10111001101111010110010011000 !
b10111001101111010110010011000 (
b1100000011001010 #
b1100000011001010 &
b1100100 *
b10010010 %
1"
#294
0"
#295
b10000100001011100100101011100000 )
b11110010101001111110110011101000 !
b11110010101001111110110011101000 (
b1101000101011001 #
b1101000101011001 &
b1100100 *
b10010011 %
1"
#296
0"
#297
b11111011010110001111000110100111 )
b10000100001011100100101011100000 !
b10000100001011100100101011100000 (
b1111001000001010 #
b1111001000001010 &
b1100100 *
b10010100 %
1"
#298
0"
#299
b111000011000010010010111111010 )
b11111011010110001111000110100111 !
b11111011010110001111000110100111 (
b1011110001111 #
b1011110001111 &
b1100100 *
b10010101 %
1"
#300
0"
