direct-form.v
module fir_direct (
    input wire clk,
    input wire rst_n,
    input wire signed [15:0] coeffs [0:99], 
    input wire signed [15:0] samples [0:1052],
    input wire signed [15:0] din_950,
    input wire signed [15:0] din_1100,
    input wire signed [15:0] din_2000,
    output reg signed [39:0] dout_950,
    output reg signed [39:0] dout_1100,
    output reg signed [39:0] dout_2000
);
    parameter TAPS = 100;
    
    // Delay line
    reg signed [15:0] delay_line_950 [0:TAPS-1];
    reg signed [15:0] delay_line_1100 [0:TAPS-1];
    reg signed [15:0] delay_line_2000 [0:TAPS-1];
    
    // Accumulator
    reg signed [39:0] next_accum_950;
    reg signed [39:0] next_accum_1100;
    reg signed [39:0] next_accum_2000;

    // Shift register (always runs)
    always @(posedge clk or negedge rst_n) begin
        integer i;
        if (rst_n) begin
            for (i = 0; i < TAPS; i = i + 1) begin
                delay_line_950[i] <= 16'sb0;
                delay_line_1100[i] <= 16'sb0;
                delay_line_2000[i] <= 16'sb0;
            end
            dout_950 <= 40'sb0;
            dout_1100 <= 40'sb0;
            dout_2000 <= 40'sb0;
        end
        else begin
            integer i;
            // Shift every clock cycle
            for (i = TAPS-1; i > 0; i = i - 1)begin
                delay_line_950[i] <= delay_line_950[i-1];
                delay_line_1100[i] <= delay_line_1100[i-1];
                delay_line_2000[i] <= delay_line_2000[i-1];
            end
            delay_line_950[0] <= din_950;
            delay_line_1100[0] <= din_1100;
            delay_line_2000[0] <= din_2000;
            dout_950 <= next_accum_950;
            dout_1100 <= next_accum_1100;
            dout_2000 <= next_accum_2000;
        end
    end
    
    // Compute output every cycle
   always @(*) begin
        integer i;
        reg signed [39:0] accum_950, accum_1100, accum_2000;
        reg signed [31:0] product_950;
        reg signed [31:0] product_1100;
        reg signed [31:0] product_2000;
        
        accum_950 = 40'sb0;
        accum_1100 = 40'sb0;
        accum_2000 = 40'sb0;
        for (i = 0; i < TAPS; i = i + 1) begin
            product_950 = delay_line_950[i] * coeffs[i];
            product_1100 = delay_line_1100[i] * coeffs[i];
            product_2000 = delay_line_2000[i] * coeffs[i];
            accum_950 = accum_950 + { {8{product_950[31]}}, product_950 }; 
            accum_1100 = accum_1100 + { {8{product_1100[31]}}, product_1100 }; 
            accum_2000 = accum_2000 + { {8{product_2000[31]}}, product_2000 }; 
        end
        next_accum_950 = accum_950;
        next_accum_1100 = accum_1100;
        next_accum_2000 = accum_2000;
    end
    
endmodule

direct-form_tb.v
`timescale 1ns/1ns
module tb_fir_direct();
    reg clk, rst_n;
    wire signed [39:0] dout_950;
    wire signed [39:0] dout_1100;
    wire signed [39:0] dout_2000;
    reg signed [15:0] din_950;
    reg signed [15:0] din_1100;
    reg signed [15:0] din_2000;
    reg signed [15:0] coeffs [0:99];
    reg signed [15:0] samples [0:1052];
    reg signed [39:0] out_950 [0:1899];
    reg signed [39:0] out_1100 [0:1899];
    reg signed [39:0] out_2000 [0:1899];
    integer idx;
    
    fir_direct u_dut (
        .clk(clk),
        .rst_n(rst_n),
        .din_950(din_950),
        .din_1100(din_1100),
        .din_2000(din_2000),
        .dout_950(dout_950),
        .dout_1100(dout_1100),
        .dout_2000(dout_2000),
        .coeffs(coeffs),
        .samples(samples)
    );
    
    initial clk = 0;
    always #1 clk = ~clk;

    always @(posedge clk)begin
        if(rst_n)begin
            idx<=0;
            din_950<=16'b0;
            din_1100<=16'b0;
            din_2000<=16'b0;
        end
        else begin
                din_950<=samples[idx];
                din_1100<=samples[idx];
                din_2000<=samples[idx];
                out_950[idx]<=dout_950;
                out_1100[idx]<=dout_1100;
                out_2000[idx]<=dout_2000;
                idx <= idx+1;
        end
    end

    task read_coeffs;
       integer  coeff_file;
       integer  i;
        coeff_file = $fopen("fc_quantized_2_14.txt", "r");
        for (i = 0; i < 100; i = i + 1)
            $fscanf(coeff_file, "%b\n", coeffs[i]);
        $fclose(coeff_file);
        $display("Read 100 coefficients");

    endtask;

    task read_q_2_14_950;
        integer in_file;
        integer  idx;
        in_file = $fopen("q_2_14_950.txt", "r");
        idx = 0;
        for (idx=0;idx<1053;idx++) begin
            $fscanf(in_file, "%b\n", samples[idx]);
        end
        $fclose(in_file);
    endtask;
    
    task readFiles;
        read_coeffs();
        read_q_2_14_950();
        read_q_2_14_1100();
        read_q_2_14_2000();
    endtask;
    task read_q_2_14_1100;
        integer in_file;
        integer  idx;
        in_file = $fopen("q_2_14_1100.txt", "r");
        idx = 0;
        for (idx=0;idx<1053;idx++) begin
            $fscanf(in_file, "%b\n", samples[idx]);
        end
        $fclose(in_file);
    endtask;

    task read_q_2_14_2000;
        integer in_file;
        integer  idx;
        in_file = $fopen("q_2_14_2000.txt", "r");
        idx = 0;
        for (idx=0;idx<1053;idx++) begin
            $fscanf(in_file, "%b\n", samples[idx]);
        end
        $fclose(in_file);
    endtask;

    task writeFiles;
       integer j,out_950_file,out_1100_file,out_2000_file;
        out_950_file = $fopen("out_950_verilog.txt","w");
        out_1100_file = $fopen("out_1100_verilog.txt","w");
        out_2000_file = $fopen("out_2000_verilog.txt","w");
        for(j=0;j<503;j++)begin
            $fwrite(out_950_file,"%b\n",out_950[j]);
            $fwrite(out_1100_file,"%b\n",out_1100[j]);
            $fwrite(out_2000_file,"%b\n",out_2000[j]);
        end
        $fclose(out_950_file);
        $fclose(out_1100_file);
        $fclose(out_2000_file);
    endtask;

    initial begin
        $dumpfile("wave-05.vcd"); 
        $dumpvars(0, tb_fir_direct);
    end
    initial begin
        rst_n = 1;
        idx =0;

        readFiles();

        #2;
        rst_n = 0;

        #10008;
      
        writeFiles();
        $finish;
    end
   
endmodule

wave-05.vcd
$date
	Sat Apr 18 13:32:48 2026
$end
$version
	Icarus Verilog
$end
$timescale
	1ns
$end
$scope module tb_fir_direct $end
$var wire 40 ! dout_950 [39:0] $end
$var wire 40 " dout_2000 [39:0] $end
$var wire 40 # dout_1100 [39:0] $end
$var reg 1 $ clk $end
$var reg 16 % din_1100 [15:0] $end
$var reg 16 & din_2000 [15:0] $end
$var reg 16 ' din_950 [15:0] $end
$var reg 1 ( rst_n $end
$var integer 32 ) idx [31:0] $end
$scope module u_dut $end
$var wire 1 $ clk $end
$var wire 16 * din_1100 [15:0] $end
$var wire 16 + din_2000 [15:0] $end
$var wire 16 , din_950 [15:0] $end
$var wire 1 ( rst_n $end
$var parameter 32 - TAPS $end
$var reg 40 . dout_1100 [39:0] $end
$var reg 40 / dout_2000 [39:0] $end
$var reg 40 0 dout_950 [39:0] $end
$var reg 40 1 next_accum_1100 [39:0] $end
$var reg 40 2 next_accum_2000 [39:0] $end
$var reg 40 3 next_accum_950 [39:0] $end
$scope begin $unm_blk_1 $end
$var integer 32 4 i [31:0] $end
$scope begin $unm_blk_4 $end
$var integer 32 5 i [31:0] $end
$upscope $end
$upscope $end
$scope begin $unm_blk_6 $end
$var reg 40 6 accum_1100 [39:0] $end
$var reg 40 7 accum_2000 [39:0] $end
$var reg 40 8 accum_950 [39:0] $end
$var reg 32 9 product_1100 [31:0] $end
$var reg 32 : product_2000 [31:0] $end
$var reg 32 ; product_950 [31:0] $end
$var integer 32 < i [31:0] $end
$upscope $end
$upscope $end
$scope task readFiles $end
$upscope $end
$scope task read_coeffs $end
$var integer 32 = coeff_file [31:0] $end
$var integer 32 > i [31:0] $end
$upscope $end
$scope task read_q_2_14_1100 $end
$var integer 32 ? idx [31:0] $end
$var integer 32 @ in_file [31:0] $end
$upscope $end
$scope task read_q_2_14_2000 $end
$var integer 32 A idx [31:0] $end
$var integer 32 B in_file [31:0] $end
$upscope $end
$scope task read_q_2_14_950 $end
$var integer 32 C idx [31:0] $end
$var integer 32 D in_file [31:0] $end
$upscope $end
$scope task writeFiles $end
$var integer 32 E j [31:0] $end
$var integer 32 F out_1100_file [31:0] $end
$var integer 32 G out_2000_file [31:0] $end
$var integer 32 H out_950_file [31:0] $end
$upscope $end
$upscope $end
$enddefinitions $end
$comment Show the parameter values. $end
$dumpall
b1100100 -
$end
#0
$dumpvars
bx H
bx G
bx F
bx E
b10000000000000000000000000000011 D
b10000011101 C
b10000000000000000000000000000011 B
b10000011101 A
b10000000000000000000000000000011 @
b10000011101 ?
b1100100 >
b10000000000000000000000000000011 =
b1100100 <
bx ;
bx :
bx 9
bx 8
bx 7
bx 6
bx 5
bx 4
bx 3
bx 2
bx 1
bx 0
bx /
bx .
bx ,
bx +
bx *
b0 )
1(
bx '
bx &
bx %
0$
bx #
bx "
bx !
$end
#1
b0 2
b0 1
b0 3
b0 :
b0 9
b0 ;
b1100100 <
b0 7
b0 6
b0 8
b0 "
b0 /
b0 #
b0 .
b0 !
b0 0
b0 &
b0 +
b0 %
b0 *
b0 '
b0 ,
b1100100 4
1$
#2
b0 5
0$
0(
#3
b1 )
b0 5
1$
#4
0$
#5
b10 )
b11110011011110 &
b11110011011110 +
b11110011011110 %
b11110011011110 *
b11110011011110 '
b11110011011110 ,
b0 5
1$
#6
0$
#7
b1111111111111111111111110100100101100110 2
b1111111111111111111111110100100101100110 1
b1111111111111111111111110100100101100110 3
b1111111111111111111111110100100101100110 7
b1111111111111111111111110100100101100110 6
b1111111111111111111111110100100101100110 8
b0 :
b0 9
b0 ;
b1100100 <
b11 )
b10010110011110 &
b10010110011110 +
b10010110011110 %
b10010110011110 *
b10010110011110 '
b10010110011110 ,
b0 5
1$
#8
0$
#9
b1111111111111111111111011110010100010100 2
b1111111111111111111111011110010100010100 1
b1111111111111111111111011110010100010100 3
b0 :
b0 9
b0 ;
b1100100 <
b1111111111111111111111011110010100010100 7
b1111111111111111111111011110010100010100 6
b1111111111111111111111011110010100010100 8
b1111111111111111111111110100100101100110 "
b1111111111111111111111110100100101100110 /
b1111111111111111111111110100100101100110 #
b1111111111111111111111110100100101100110 .
b1111111111111111111111110100100101100110 !
b1111111111111111111111110100100101100110 0
b100 )
b1101101001100010 &
b1101101001100010 +
b1101101001100010 %
b1101101001100010 *
b1101101001100010 '
b1101101001100010 ,
b0 5
1$
#10
0$
#11
b1111111111111111111111010100010110111010 2
b1111111111111111111111010100010110111010 1
b1111111111111111111111010100010110111010 3
b0 :
b0 9
b0 ;
b1100100 <
b1111111111111111111111010100010110111010 7
b1111111111111111111111010100010110111010 6
b1111111111111111111111010100010110111010 8
b1111111111111111111111011110010100010100 "
b1111111111111111111111011110010100010100 /
b1111111111111111111111011110010100010100 #
b1111111111111111111111011110010100010100 .
b1111111111111111111111011110010100010100 !
b1111111111111111111111011110010100010100 0
b101 )
b1100001100100010 &
b1100001100100010 +
b1100001100100010 %
b1100001100100010 *
b1100001100100010 '
b1100001100100010 ,
b0 5
1$
#12
0$
#13
b1111111111111111111111101000010001101110 2
b1111111111111111111111101000010001101110 1
b1111111111111111111111101000010001101110 3
b0 :
b0 9
b0 ;
b1100100 <
b1111111111111111111111101000010001101110 7
b1111111111111111111111101000010001101110 6
b1111111111111111111111101000010001101110 8
b1111111111111111111111010100010110111010 "
b1111111111111111111111010100010110111010 /
b1111111111111111111111010100010110111010 #
b1111111111111111111111010100010110111010 .
b1111111111111111111111010100010110111010 !
b1111111111111111111111010100010110111010 0
b110 )
b0 &
b0 +
b0 %
b0 *
b0 '
b0 ,
b0 5
1$
#14
0$
#15
b10001100100010110 2
b10001100100010110 1
b10001100100010110 3
b0 :
b0 9
b0 ;
b1100100 <
b10001100100010110 7
b10001100100010110 6
b10001100100010110 8
b1111111111111111111111101000010001101110 "
b1111111111111111111111101000010001101110 /
b1111111111111111111111101000010001101110 #
b1111111111111111111111101000010001101110 .
b1111111111111111111111101000010001101110 !
b1111111111111111111111101000010001101110 0
b111 )
b11110011011110 &
b11110011011110 +
b11110011011110 %
b11110011011110 *
b11110011011110 '
b11110011011110 ,
b0 5
1$
#16
0$
#17
b110001110011000010 2
b110001110011000010 1
b110001110011000010 3
b0 :
b0 9
b0 ;
b1100100 <
b110001110011000010 7
b110001110011000010 6
b110001110011000010 8
b10001100100010110 "
b10001100100010110 /
b10001100100010110 #
b10001100100010110 .
b10001100100010110 !
b10001100100010110 0
b1000 )
b10010110011110 &
b10010110011110 +
b10010110011110 %
b10010110011110 *
b10010110011110 '
b10010110011110 ,
b0 5
1$
#18
0$
#19
b110111000011100000 2
b110111000011100000 1
b110111000011100000 3
b0 :
b0 9
b0 ;
b1100100 <
b110111000011100000 7
b110111000011100000 6
b110111000011100000 8
b110001110011000010 "
b110001110011000010 /
b110001110011000010 #
b110001110011000010 .
b110001110011000010 !
b110001110011000010 0
b1001 )
b1101101001100010 &
b1101101001100010 +
b1101101001100010 %
b1101101001100010 *
b1101101001100010 '
b1101101001100010 ,
b0 5
1$
#20
0$
#21
b101001010010101000 2
b101001010010101000 1
b101001010010101000 3
b0 :
b0 9
b0 ;
b1100100 <
b101001010010101000 7
b101001010010101000 6
b101001010010101000 8
b110111000011100000 "
b110111000011100000 /
b110111000011100000 #
b110111000011100000 .
b110111000011100000 !
b110111000011100000 0
b1010 )
b1100001100100010 &
b1100001100100010 +
b1100001100100010 %
b1100001100100010 *
b1100001100100010 '
b1100001100100010 ,
b0 5
1$
#22
0$
#23
b10111101110010010 2
b10111101110010010 1
b10111101110010010 3
b0 :
b0 9
b0 ;
b1100100 <
b10111101110010010 7
b10111101110010010 6
b10111101110010010 8
b101001010010101000 "
b101001010010101000 /
b101001010010101000 #
b101001010010101000 .
b101001010010101000 !
b101001010010101000 0
b1011 )
b0 &
b0 +
b0 %
b0 *
b0 '
b0 ,
b0 5
1$
#24
0$
#25
b1111111111111111111111111100001100100010 2
b1111111111111111111111111100001100100010 1
b1111111111111111111111111100001100100010 3
b0 :
b0 9
b0 ;
b1100100 <
b1111111111111111111111111100001100100010 7
b1111111111111111111111111100001100100010 6
b1111111111111111111111111100001100100010 8
b10111101110010010 "
b10111101110010010 /
b10111101110010010 #
b10111101110010010 .
b10111101110010010 !
b10111101110010010 0
b1100 )
b11110011011110 &
b11110011011110 +
b11110011011110 %
b11110011011110 *
b11110011011110 '
b11110011011110 ,
b0 5
1$
#26
0$
#27
b1111111111111111111111001011010010111110 2
b1111111111111111111111001011010010111110 1
b1111111111111111111111001011010010111110 3
b0 :
b0 9
b0 ;
b1100100 <
b1111111111111111111111001011010010111110 7
b1111111111111111111111001011010010111110 6
b1111111111111111111111001011010010111110 8
b1111111111111111111111111100001100100010 "
b1111111111111111111111111100001100100010 /
b1111111111111111111111111100001100100010 #
b1111111111111111111111111100001100100010 .
b1111111111111111111111111100001100100010 !
b1111111111111111111111111100001100100010 0
b1101 )
b10010110011110 &
b10010110011110 +
b10010110011110 %
b10010110011110 *
b10010110011110 '
b10010110011110 ,
b0 5
1$
#28
0$
#29
b1111111111111111111110010011010110000000 2
b1111111111111111111110010011010110000000 1
b1111111111111111111110010011010110000000 3
b0 :
b0 9
b0 ;
b1100100 <
b1111111111111111111110010011010110000000 7
b1111111111111111111110010011010110000000 6
b1111111111111111111110010011010110000000 8
b1111111111111111111111001011010010111110 "
b1111111111111111111111001011010010111110 /
b1111111111111111111111001011010010111110 #
b1111111111111111111111001011010010111110 .
b1111111111111111111111001011010010111110 !
b1111111111111111111111001011010010111110 0
b1110 )
b1101101001100010 &
b1101101001100010 +
b1101101001100010 %
b1101101001100010 *
b1101101001100010 '
b1101101001100010 ,
b0 5
1$
#30
0$
#31
b1111111111111111111110000011001110101010 2
b1111111111111111111110000011001110101010 1
b1111111111111111111110000011001110101010 3
b0 :
b0 9
b0 ;
b1100100 <
b1111111111111111111110000011001110101010 7
b1111111111111111111110000011001110101010 6
b1111111111111111111110000011001110101010 8
b1111111111111111111110010011010110000000 "
b1111111111111111111110010011010110000000 /
b1111111111111111111110010011010110000000 #
b1111111111111111111110010011010110000000 .
b1111111111111111111110010011010110000000 !
b1111111111111111111110010011010110000000 0
b1111 )
b1100001100100010 &
b1100001100100010 +
b1100001100100010 %
b1100001100100010 *
b1100001100100010 '
b1100001100100010 ,
b0 5
1$
#32
0$
#33
b1111111111111111111110111100101000101000 2
b1111111111111111111110111100101000101000 1
b1111111111111111111110111100101000101000 3
b0 :
b0 9
b0 ;
b1100100 <
b1111111111111111111110111100101000101000 7
b1111111111111111111110111100101000101000 6
b1111111111111111111110111100101000101000 8
b1111111111111111111110000011001110101010 "
b1111111111111111111110000011001110101010 /
b1111111111111111111110000011001110101010 #
b1111111111111111111110000011001110101010 .
b1111111111111111111110000011001110101010 !
b1111111111111111111110000011001110101010 0
b10000 )
b0 &
b0 +
b0 %
b0 *
b0 '
b0 ,
b0 5
1$
#34
0$
#35
b101001010010101000 2
b101001010010101000 1
b101001010010101000 3
b0 :
b0 9
b0 ;
b1100100 <
b101001010010101000 7
b101001010010101000 6
b101001010010101000 8
b1111111111111111111110111100101000101000 "
b1111111111111111111110111100101000101000 /
b1111111111111111111110111100101000101000 #
b1111111111111111111110111100101000101000 .
b1111111111111111111110111100101000101000 !
b1111111111111111111110111100101000101000 0
b10001 )
b11110011011110 &
b11110011011110 +
b11110011011110 %
b11110011011110 *
b11110011011110 '
b11110011011110 ,
b0 5
1$
#36
0$
#37
b10001110010101101100 2
b10001110010101101100 1
b10001110010101101100 3
b0 :
b0 9
b0 ;
b1100100 <
b10001110010101101100 7
b10001110010101101100 6
b10001110010101101100 8
b101001010010101000 "
b101001010010101000 /
b101001010010101000 #
b101001010010101000 .
b101001010010101000 !
b101001010010101000 0
b10010 )
b10010110011110 &
b10010110011110 +
b10010110011110 %
b10010110011110 *
b10010110011110 '
b10010110011110 ,
b0 5
1$
#38
0$
#39
b10111111001111010000 2
b10111111001111010000 1
b10111111001111010000 3
b0 :
b0 9
b0 ;
b1100100 <
b10111111001111010000 7
b10111111001111010000 6
b10111111001111010000 8
b10001110010101101100 "
b10001110010101101100 /
b10001110010101101100 #
b10001110010101101100 .
b10001110010101101100 !
b10001110010101101100 0
b10011 )
b1101101001100010 &
b1101101001100010 +
b1101101001100010 %
b1101101001100010 *
b1101101001100010 '
b1101101001100010 ,
b0 5
1$
#40
0$
#41
b10101101101010111010 2
b10101101101010111010 1
b10101101101010111010 3
b0 :
b0 9
b0 ;
b1100100 <
b10101101101010111010 7
b10101101101010111010 6
b10101101101010111010 8
b10111111001111010000 "
b10111111001111010000 /
b10111111001111010000 #
b10111111001111010000 .
b10111111001111010000 !
b10111111001111010000 0
b10100 )
b1100001100100010 &
b1100001100100010 +
b1100001100100010 %
b1100001100100010 *
b1100001100100010 '
b1100001100100010 ,
b0 5
1$
#42
0$
#43
b1011110111001001000 2
b1011110111001001000 1
b1011110111001001000 3
b0 :
b0 9
b0 ;
b1100100 <
b1011110111001001000 7
b1011110111001001000 6
b1011110111001001000 8
b10101101101010111010 "
b10101101101010111010 /
b10101101101010111010 #
b10101101101010111010 .
b10101101101010111010 !
b10101101101010111010 0
b10101 )
b0 &
b0 +
b0 %
b0 *
b0 '
b0 ,
b0 5
1$
#44
0$
#45
b1111111111111111111111011001000011110110 2
b1111111111111111111111011001000011110110 1
b1111111111111111111111011001000011110110 3
b0 :
b0 9
b0 ;
b1100100 <
b1111111111111111111111011001000011110110 7
b1111111111111111111111011001000011110110 6
b1111111111111111111111011001000011110110 8
b1011110111001001000 "
b1011110111001001000 /
b1011110111001001000 #
b1011110111001001000 .
b1011110111001001000 !
b1011110111001001000 0
b10110 )
b11110011011110 &
b11110011011110 +
b11110011011110 %
b11110011011110 *
b11110011011110 '
b11110011011110 ,
b0 5
1$
#46
0$
#47
b1111111111111111111100110101010110010110 2
b1111111111111111111100110101010110010110 1
b1111111111111111111100110101010110010110 3
b0 :
b0 9
b0 ;
b1100100 <
b1111111111111111111100110101010110010110 7
b1111111111111111111100110101010110010110 6
b1111111111111111111100110101010110010110 8
b1111111111111111111111011001000011110110 "
b1111111111111111111111011001000011110110 /
b1111111111111111111111011001000011110110 #
b1111111111111111111111011001000011110110 .
b1111111111111111111111011001000011110110 !
b1111111111111111111111011001000011110110 0
b10111 )
b10010110011110 &
b10010110011110 +
b10010110011110 %
b10010110011110 *
b10010110011110 '
b10010110011110 ,
b0 5
1$
#48
0$
#49
b1111111111111111111010110110001110100010 2
b1111111111111111111010110110001110100010 1
b1111111111111111111010110110001110100010 3
b0 :
b0 9
b0 ;
b1100100 <
b1111111111111111111010110110001110100010 7
b1111111111111111111010110110001110100010 6
b1111111111111111111010110110001110100010 8
b1111111111111111111100110101010110010110 "
b1111111111111111111100110101010110010110 /
b1111111111111111111100110101010110010110 #
b1111111111111111111100110101010110010110 .
b1111111111111111111100110101010110010110 !
b1111111111111111111100110101010110010110 0
b11000 )
b1101101001100010 &
b1101101001100010 +
b1101101001100010 %
b1101101001100010 *
b1101101001100010 '
b1101101001100010 ,
b0 5
1$
#50
0$
#51
b1111111111111111111010110011111000000100 2
b1111111111111111111010110011111000000100 1
b1111111111111111111010110011111000000100 3
b0 :
b0 9
b0 ;
b1100100 <
b1111111111111111111010110011111000000100 7
b1111111111111111111010110011111000000100 6
b1111111111111111111010110011111000000100 8
b1111111111111111111010110110001110100010 "
b1111111111111111111010110110001110100010 /
b1111111111111111111010110110001110100010 #
b1111111111111111111010110110001110100010 .
b1111111111111111111010110110001110100010 !
b1111111111111111111010110110001110100010 0
b11001 )
b1100001100100010 &
b1100001100100010 +
b1100001100100010 %
b1100001100100010 *
b1100001100100010 '
b1100001100100010 ,
b0 5
1$
#52
0$
#53
b1111111111111111111101010011110010000110 2
b1111111111111111111101010011110010000110 1
b1111111111111111111101010011110010000110 3
b0 :
b0 9
b0 ;
b1100100 <
b1111111111111111111101010011110010000110 7
b1111111111111111111101010011110010000110 6
b1111111111111111111101010011110010000110 8
b1111111111111111111010110011111000000100 "
b1111111111111111111010110011111000000100 /
b1111111111111111111010110011111000000100 #
b1111111111111111111010110011111000000100 .
b1111111111111111111010110011111000000100 !
b1111111111111111111010110011111000000100 0
b11010 )
b0 &
b0 +
b0 %
b0 *
b0 '
b0 ,
b0 5
1$
#54
0$
#55
b1100100001001100110 2
b1100100001001100110 1
b1100100001001100110 3
b0 :
b0 9
b0 ;
b1100100 <
b1100100001001100110 7
b1100100001001100110 6
b1100100001001100110 8
b1111111111111111111101010011110010000110 "
b1111111111111111111101010011110010000110 /
b1111111111111111111101010011110010000110 #
b1111111111111111111101010011110010000110 .
b1111111111111111111101010011110010000110 !
b1111111111111111111101010011110010000110 0
b11011 )
b11110011011110 &
b11110011011110 +
b11110011011110 %
b11110011011110 *
b11110011011110 '
b11110011011110 ,
b0 5
1$
#56
0$
#57
b101110011000100000110 2
b101110011000100000110 1
b101110011000100000110 3
b0 :
b0 9
b0 ;
b1100100 <
b101110011000100000110 7
b101110011000100000110 6
b101110011000100000110 8
b1100100001001100110 "
b1100100001001100110 /
b1100100001001100110 #
b1100100001001100110 .
b1100100001001100110 !
b1100100001001100110 0
b11100 )
b10010110011110 &
b10010110011110 +
b10010110011110 %
b10010110011110 *
b10010110011110 '
b10010110011110 ,
b0 5
1$
#58
0$
#59
b1000001100110100001100 2
b1000001100110100001100 1
b1000001100110100001100 3
b0 :
b0 9
b0 ;
b1100100 <
b1000001100110100001100 7
b1000001100110100001100 6
b1000001100110100001100 8
b101110011000100000110 "
b101110011000100000110 /
b101110011000100000110 #
b101110011000100000110 .
b101110011000100000110 !
b101110011000100000110 0
b11101 )
b1101101001100010 &
b1101101001100010 +
b1101101001100010 %
b1101101001100010 *
b1101101001100010 '
b1101101001100010 ,
b0 5
1$
#60
0$
#61
b111101001101011100000 2
b111101001101011100000 1
b111101001101011100000 3
b0 :
b0 9
b0 ;
b1100100 <
b111101001101011100000 7
b111101001101011100000 6
b111101001101011100000 8
b1000001100110100001100 "
b1000001100110100001100 /
b1000001100110100001100 #
b1000001100110100001100 .
b1000001100110100001100 !
b1000001100110100001100 0
b11110 )
b1100001100100010 &
b1100001100100010 +
b1100001100100010 %
b1100001100100010 *
b1100001100100010 '
b1100001100100010 ,
b0 5
1$
#62
0$
#63
b11111101010110001010 2
b11111101010110001010 1
b11111101010110001010 3
b0 :
b0 9
b0 ;
b1100100 <
b11111101010110001010 7
b11111101010110001010 6
b11111101010110001010 8
b111101001101011100000 "
b111101001101011100000 /
b111101001101011100000 #
b111101001101011100000 .
b111101001101011100000 !
b111101001101011100000 0
b11111 )
b0 &
b0 +
b0 %
b0 *
b0 '
b0 ,
b0 5
1$
#64
0$
#65
b1111111111111111111101111000101101101110 2
b1111111111111111111101111000101101101110 1
b1111111111111111111101111000101101101110 3
b0 :
b0 9
b0 ;
b1100100 <
b1111111111111111111101111000101101101110 7
b1111111111111111111101111000101101101110 6
b1111111111111111111101111000101101101110 8
b11111101010110001010 "
b11111101010110001010 /
b11111101010110001010 #
b11111101010110001010 .
b11111101010110001010 !
b11111101010110001010 0
b100000 )
b11110011011110 &
b11110011011110 +
b11110011011110 %
b11110011011110 *
b11110011011110 '
b11110011011110 ,
b0 5
1$
#66
0$
#67
b1111111111111111110111010110001101000100 2
b1111111111111111110111010110001101000100 1
b1111111111111111110111010110001101000100 3
b0 :
b0 9
b0 ;
b1100100 <
b1111111111111111110111010110001101000100 7
b1111111111111111110111010110001101000100 6
b1111111111111111110111010110001101000100 8
b1111111111111111111101111000101101101110 "
b1111111111111111111101111000101101101110 /
b1111111111111111111101111000101101101110 #
b1111111111111111111101111000101101101110 .
b1111111111111111111101111000101101101110 !
b1111111111111111111101111000101101101110 0
b100001 )
b10010110011110 &
b10010110011110 +
b10010110011110 %
b10010110011110 *
b10010110011110 '
b10010110011110 ,
b0 5
1$
#68
0$
#69
b1111111111111111110011000001001000101000 2
b1111111111111111110011000001001000101000 1
b1111111111111111110011000001001000101000 3
b0 :
b0 9
b0 ;
b1100100 <
b1111111111111111110011000001001000101000 7
b1111111111111111110011000001001000101000 6
b1111111111111111110011000001001000101000 8
b1111111111111111110111010110001101000100 "
b1111111111111111110111010110001101000100 /
b1111111111111111110111010110001101000100 #
b1111111111111111110111010110001101000100 .
b1111111111111111110111010110001101000100 !
b1111111111111111110111010110001101000100 0
b100010 )
b1101101001100010 &
b1101101001100010 +
b1101101001100010 %
b1101101001100010 *
b1101101001100010 '
b1101101001100010 ,
b0 5
1$
#70
0$
#71
b1111111111111111110011011011110000111010 2
b1111111111111111110011011011110000111010 1
b1111111111111111110011011011110000111010 3
b0 :
b0 9
b0 ;
b1100100 <
b1111111111111111110011011011110000111010 7
b1111111111111111110011011011110000111010 6
b1111111111111111110011011011110000111010 8
b1111111111111111110011000001001000101000 "
b1111111111111111110011000001001000101000 /
b1111111111111111110011000001001000101000 #
b1111111111111111110011000001001000101000 .
b1111111111111111110011000001001000101000 !
b1111111111111111110011000001001000101000 0
b100011 )
b1100001100100010 &
b1100001100100010 +
b1100001100100010 %
b1100001100100010 *
b1100001100100010 '
b1100001100100010 ,
b0 5
1$
#72
0$
#73
b1111111111111111111001100000011001010110 2
b1111111111111111111001100000011001010110 1
b1111111111111111111001100000011001010110 3
b0 :
b0 9
b0 ;
b1100100 <
b1111111111111111111001100000011001010110 7
b1111111111111111111001100000011001010110 6
b1111111111111111111001100000011001010110 8
b1111111111111111110011011011110000111010 "
b1111111111111111110011011011110000111010 /
b1111111111111111110011011011110000111010 #
b1111111111111111110011011011110000111010 .
b1111111111111111110011011011110000111010 !
b1111111111111111110011011011110000111010 0
b100100 )
b0 &
b0 +
b0 %
b0 *
b0 '
b0 ,
b0 5
1$
#74
0$
#75
b11100111101000011010 2
b11100111101000011010 1
b11100111101000011010 3
b0 :
b0 9
b0 ;
b1100100 <
b11100111101000011010 7
b11100111101000011010 6
b11100111101000011010 8
b1111111111111111111001100000011001010110 "
b1111111111111111111001100000011001010110 /
b1111111111111111111001100000011001010110 #
b1111111111111111111001100000011001010110 .
b1111111111111111111001100000011001010110 !
b1111111111111111111001100000011001010110 0
b100101 )
b11110011011110 &
b11110011011110 +
b11110011011110 %
b11110011011110 *
b11110011011110 '
b11110011011110 ,
b0 5
1$
#76
0$
#77
b1110001000111100001110 2
b1110001000111100001110 1
b1110001000111100001110 3
b0 :
b0 9
b0 ;
b1100100 <
b1110001000111100001110 7
b1110001000111100001110 6
b1110001000111100001110 8
b11100111101000011010 "
b11100111101000011010 /
b11100111101000011010 #
b11100111101000011010 .
b11100111101000011010 !
b11100111101000011010 0
b100110 )
b10010110011110 &
b10010110011110 +
b10010110011110 %
b10010110011110 *
b10010110011110 '
b10010110011110 ,
b0 5
1$
#78
0$
#79
b10100110000001001110100 2
b10100110000001001110100 1
b10100110000001001110100 3
b0 :
b0 9
b0 ;
b1100100 <
b10100110000001001110100 7
b10100110000001001110100 6
b10100110000001001110100 8
b1110001000111100001110 "
b1110001000111100001110 /
b1110001000111100001110 #
b1110001000111100001110 .
b1110001000111100001110 !
b1110001000111100001110 0
b100111 )
b1101101001100010 &
b1101101001100010 +
b1101101001100010 %
b1101101001100010 *
b1101101001100010 '
b1101101001100010 ,
b0 5
1$
#80
0$
#81
b10100000101011010001100 2
b10100000101011010001100 1
b10100000101011010001100 3
b0 :
b0 9
b0 ;
b1100100 <
b10100000101011010001100 7
b10100000101011010001100 6
b10100000101011010001100 8
b10100110000001001110100 "
b10100110000001001110100 /
b10100110000001001110100 #
b10100110000001001110100 .
b10100110000001001110100 !
b10100110000001001110100 0
b101000 )
b1100001100100010 &
b1100001100100010 +
b1100001100100010 %
b1100001100100010 *
b1100001100100010 '
b1100001100100010 ,
b0 5
1$
#82
0$
#83
b1010111010110101000010 2
b1010111010110101000010 1
b1010111010110101000010 3
b0 :
b0 9
b0 ;
b1100100 <
b1010111010110101000010 7
b1010111010110101000010 6
b1010111010110101000010 8
b10100000101011010001100 "
b10100000101011010001100 /
b10100000101011010001100 #
b10100000101011010001100 .
b10100000101011010001100 !
b10100000101011010001100 0
b101001 )
b0 &
b0 +
b0 %
b0 *
b0 '
b0 ,
b0 5
1$
#84
0$
