optimized-form.v
module fir_optimized (
    input wire clk,
    input wire rst_n,
    input wire signed [15:0] coeffs [0:99],
    input wire signed [15:0] din_950,
    input wire signed [15:0] din_1100,
    input wire signed [15:0] din_2000,
    output reg signed [39:0] dout_950,
    output reg signed [39:0] dout_1100,
    output reg signed [39:0] dout_2000
);
    parameter TAPS = 100;
    
    // Transposed form uses registers after each multiply-accumulate
    reg signed [39:0] tap_reg_950 [0:TAPS-1];
    reg signed [39:0] tap_reg_1100 [0:TAPS-1];
    reg signed [39:0] tap_reg_2000 [0:TAPS-1];
    
    integer i;
    
    // Transposed form implementation (more pipelined)
    always @(posedge clk or negedge rst_n) begin
        if (!rst_n) begin
            for (i = 0; i < TAPS; i = i + 1) begin
                tap_reg_950[i] <= 40'sb0;
                tap_reg_1100[i] <= 40'sb0;
                tap_reg_2000[i] <= 40'sb0;
            end
            dout_950 <= 40'sb0;
            dout_1100 <= 40'sb0;
            dout_2000 <= 40'sb0;
        end
        else begin
            // First tap (no feedback)
            tap_reg_950[0] <= din_950 * coeffs[0];
            tap_reg_1100[0] <= din_1100 * coeffs[0];
            tap_reg_2000[0] <= din_2000 * coeffs[0];
            
            // Remaining taps with accumulation
            for (i = 1; i < TAPS; i = i + 1) begin
                tap_reg_950[i] <= tap_reg_950[i-1] + (din_950 * coeffs[i]);
                tap_reg_1100[i] <= tap_reg_1100[i-1] + (din_1100 * coeffs[i]);
                tap_reg_2000[i] <= tap_reg_2000[i-1] + (din_2000 * coeffs[i]);
            end
            
            // Output is the last tap
            dout_950 <= tap_reg_950[TAPS-1];
            dout_1100 <= tap_reg_1100[TAPS-1];
            dout_2000 <= tap_reg_2000[TAPS-1];
        end
    end
    
endmodule

optimized-form_tb.v
`timescale 1ns/1ns
module tb_fir_optimized();
    reg clk, rst_n;
    wire signed [39:0] dout_950, dout_1100, dout_2000;
    reg signed [15:0] din_950, din_1100, din_2000;
    reg signed [15:0] coeffs [0:99];
    reg signed [15:0] samples_950 [0:1052];
    reg signed [15:0] samples_1100 [0:1052];
    reg signed [15:0] samples_2000 [0:1052];
    reg signed [39:0] out_950 [0:1899];
    reg signed [39:0] out_1100 [0:1899];
    reg signed [39:0] out_2000 [0:1899];
    integer idx;
    
    fir_optimized u_dut (
        .clk(clk),
        .rst_n(rst_n),
        .din_950(din_950),
        .din_1100(din_1100),
        .din_2000(din_2000),
        .dout_950(dout_950),
        .dout_1100(dout_1100),
        .dout_2000(dout_2000),
        .coeffs(coeffs)
    );
    
    initial clk = 0;
    always #1 clk = ~clk;
    
    always @(posedge clk) begin
        if (!rst_n) begin
            idx <= 0;
            din_950 <= 16'sb0;
            din_1100 <= 16'sb0;
            din_2000 <= 16'sb0;
        end
        else begin
            if (idx < 1053) begin
                din_950 <= samples_950[idx];
                din_1100 <= samples_1100[idx];
                din_2000 <= samples_2000[idx];
                out_950[idx] <= dout_950;
                out_1100[idx] <= dout_1100;
                out_2000[idx] <= dout_2000;
                idx <= idx + 1;
            end
        end
    end
    
    task read_coeffs;
        integer coeff_file, i;
        begin
            coeff_file = $fopen("fc_quantized_2_14.txt", "r");
            for (i = 0; i < 100; i = i + 1)
                $fscanf(coeff_file, "%b\n", coeffs[i]);
            $fclose(coeff_file);
            $display("Read 100 coefficients");
        end
    endtask
    
    task read_samples;
        integer file_950, file_1100, file_2000, i;
        begin
            file_950 = $fopen("q_2_14_950.txt", "r");
            file_1100 = $fopen("q_2_14_1100.txt", "r");
            file_2000 = $fopen("q_2_14_2000.txt", "r");
            
            for (i = 0; i < 1053; i = i + 1) begin
                $fscanf(file_950, "%b\n", samples_950[i]);
                $fscanf(file_1100, "%b\n", samples_1100[i]);
                $fscanf(file_2000, "%b\n", samples_2000[i]);
            end
            
            $fclose(file_950);
            $fclose(file_1100);
            $fclose(file_2000);
            $display("Read samples for all frequencies");
        end
    endtask
    
    task write_outputs;
        integer j, f_950, f_1100, f_2000;
        begin
            f_950 = $fopen("out_950_optimized.txt", "w");
            f_1100 = $fopen("out_1100_optimized.txt", "w");
            f_2000 = $fopen("out_2000_optimized.txt", "w");
            
            for (j = 100; j < 603; j = j + 1) begin  // Skip initial transients
                $fwrite(f_950, "%b\n", out_950[j]);
                $fwrite(f_1100, "%b\n", out_1100[j]);
                $fwrite(f_2000, "%b\n", out_2000[j]);
            end
            
            $fclose(f_950);
            $fclose(f_1100);
            $fclose(f_2000);
            $display("Written optimized outputs");
        end
    endtask
    
    initial begin
        $dumpfile("wave_optimized.vcd");
        $dumpvars(0, tb_fir_optimized);
    end
    
    initial begin
        rst_n = 0;
        idx = 0;
        
        read_coeffs();
        read_samples();
        
        #2;
        rst_n = 1;
        
        #10008;
        
        write_outputs();
        $finish;
    end
    
endmodule

wave_optimized.vcd
$date
	Thu Apr  9 16:26:10 2026
$end
$version
	Icarus Verilog
$end
$timescale
	1ns
$end
$scope module tb_fir_optimized $end
$var wire 40 ! dout_950 [39:0] $end
$var wire 40 " dout_2000 [39:0] $end
$var wire 40 # dout_1100 [39:0] $end
$var reg 1 $ clk $end
$var reg 16 % din_1100 [15:0] $end
$var reg 16 & din_2000 [15:0] $end
$var reg 16 ' din_950 [15:0] $end
$var reg 1 ( rst_n $end
$var integer 32 ) idx [31:0] $end
$scope module u_dut $end
$var wire 1 $ clk $end
$var wire 16 * din_1100 [15:0] $end
$var wire 16 + din_2000 [15:0] $end
$var wire 16 , din_950 [15:0] $end
$var wire 1 ( rst_n $end
$var parameter 32 - TAPS $end
$var reg 40 . dout_1100 [39:0] $end
$var reg 40 / dout_2000 [39:0] $end
$var reg 40 0 dout_950 [39:0] $end
$var integer 32 1 i [31:0] $end
$upscope $end
$scope task read_coeffs $end
$var integer 32 2 coeff_file [31:0] $end
$var integer 32 3 i [31:0] $end
$upscope $end
$scope task read_samples $end
$var integer 32 4 file_1100 [31:0] $end
$var integer 32 5 file_2000 [31:0] $end
$var integer 32 6 file_950 [31:0] $end
$var integer 32 7 i [31:0] $end
$upscope $end
$scope task write_outputs $end
$var integer 32 8 f_1100 [31:0] $end
$var integer 32 9 f_2000 [31:0] $end
$var integer 32 : f_950 [31:0] $end
$var integer 32 ; j [31:0] $end
$upscope $end
$upscope $end
$enddefinitions $end
$comment Show the parameter values. $end
$dumpall
b1100100 -
$end
#0
$dumpvars
bx ;
bx :
bx 9
bx 8
b10000011101 7
b10000000000000000000000000000011 6
b10000000000000000000000000000101 5
b10000000000000000000000000000100 4
b1100100 3
b10000000000000000000000000000011 2
b1100100 1
b0 0
b0 /
b0 .
bx ,
bx +
bx *
b0 )
0(
bx '
bx &
bx %
0$
b0 #
b0 "
b0 !
$end
#1
b0 &
b0 +
b0 %
b0 *
b0 '
b0 ,
b1100100 1
1$
#2
0$
1(
#3
b1 )
b1100100 1
1$
#4
0$
#5
b10 )
b11110011011110 &
b11110011011110 +
b10100011001100 %
b10100011001100 *
b10001111111001 '
b10001111111001 ,
b1100100 1
1$
#6
0$
#7
b11 )
b10010110011110 &
b10010110011110 +
b11111011011110 %
b11111011011110 *
b11101110000001 '
b11101110000001 ,
b1100100 1
1$
#8
0$
#9
b1111111111111111111111110100100101100110 "
b1111111111111111111111110100100101100110 /
b1111111111111111111111111000010110011100 #
b1111111111111111111111111000010110011100 .
b1111111111111111111111111001010000010101 !
b1111111111111111111111111001010000010101 0
b100 )
b1101101001100010 &
b1101101001100010 +
b11100000010101 %
b11100000010101 *
b11111001110101 '
b11111001110101 ,
b1100100 1
1$
#10
0$
#11
b1111111111111111111111011110010100010100 "
b1111111111111111111111011110010100010100 /
b1111111111111111111111100010010111010010 #
b1111111111111111111111100010010111010010 .
b1111111111111111111111100101000110101110 !
b1111111111111111111111100101000110101110 0
b101 )
b1100001100100010 &
b1100001100100010 +
b1011110001111 %
b1011110001111 *
b10101111010000 '
b10101111010000 ,
b1100100 1
1$
#12
0$
#13
b1111111111111111111111010100010110111010 "
b1111111111111111111111010100010110111010 /
b1111111111111111111111000011000010000011 #
b1111111111111111111111000011000010000011 .
b1111111111111111111111000110000001011001 !
b1111111111111111111111000110000001011001 0
b110 )
b0 &
b0 +
b1110110000111001 %
b1110110000111001 *
b101000000011 '
b101000000011 ,
b1100100 1
1$
#14
0$
#15
b1111111111111111111111101000010001101110 "
b1111111111111111111111101000010001101110 /
b1111111111111111111110101011010010010010 #
b1111111111111111111110101011010010010010 .
b1111111111111111111110101001000000001100 !
b1111111111111111111110101001000000001100 0
b111 )
b11110011011110 &
b11110011011110 +
b1100100111110111 %
b1100100111110111 *
b1110010011000000 '
b1110010011000000 ,
b1100100 1
1$
#16
0$
#17
b10001100100010110 "
b10001100100010110 /
b1111111111111111111110110010110001011011 #
b1111111111111111111110110010110001011011 .
b1111111111111111111110100011010100110111 !
b1111111111111111111110100011010100110111 0
b1000 )
b10010110011110 &
b10010110011110 +
b1100000010000001 %
b1100000010000001 *
b1100100011101010 '
b1100100011101010 ,
b1100100 1
1$
#18
0$
#19
b110001110011000010 "
b110001110011000010 /
b1111111111111111111111100111111001110011 #
b1111111111111111111111100111111001110011 .
b1111111111111111111111000110101100010100 !
b1111111111111111111111000110101100010100 0
b1001 )
b1101101001100010 &
b1101101001100010 +
b1101010000110000 %
b1101010000110000 *
b1100000000100000 '
b1100000000100000 ,
b1100100 1
1$
#20
0$
#21
b110111000011100000 "
b110111000011100000 /
b1000100001001000000 #
b1000100001001000000 .
b10110100110111111 !
b10110100110111111 0
b1010 )
b1100001100100010 &
b1100001100100010 +
b1111101111111011 %
b1111101111111011 *
b1100110101101110 '
b1100110101101110 ,
b1100100 1
1$
#22
0$
#23
b101001010010101000 "
b101001010010101000 /
b10100111010110010111 #
b10100111010110010111 .
b10000000011011101000 !
b10000000011011101000 0
b1011 )
b0 &
b0 +
b10010110011110 %
b10010110011110 *
b1110110000111001 '
b1110110000111001 ,
b1100100 1
1$
#24
0$
#25
b10111101110010010 "
b10111101110010010 /
b11100001011100100000 #
b11100001011100100000 .
b11011101010100000111 !
b11011101010100000111 0
b1100 )
b11110011011110 &
b11110011011110 +
b11110111111101 %
b11110111111101 *
b1000111011011 '
b1000111011011 ,
b1100100 1
1$
#26
0$
#27
b1111111111111111111111111100001100100010 "
b1111111111111111111111111100001100100010 /
b11000011010111011100 #
b11000011010111011100 .
b11111011001001011110 !
b11111011001001011110 0
b1101 )
b10010110011110 &
b10010110011110 +
b11100111101001 %
b11100111101001 *
b11000101010000 '
b11000101010000 ,
b1100100 1
1$
#28
0$
#29
b1111111111111111111111001011010010111110 "
b1111111111111111111111001011010010111110 /
b111001110001010111 #
b111001110001010111 .
b10110010011000110010 !
b10110010011000110010 0
b1110 )
b1101101001100010 &
b1101101001100010 +
b1101101000000 %
b1101101000000 *
b11111110110111 '
b11111110110111 ,
b1100100 1
1$
#30
0$
#31
b1111111111111111111110010011010110000000 "
b1111111111111111111110010011010110000000 /
b1111111111111111111101100000000111011110 #
b1111111111111111111101100000000111011110 .
b1111111111111111111111111100101110000001 !
b1111111111111111111111111100101110000001 0
b1111 )
b1100001100100010 &
b1100001100100010 +
b1111000000010101 %
b1111000000010101 *
b11100000010101 '
b11100000010101 ,
b1100100 1
1$
#32
0$
#33
b1111111111111111111110000011001110101010 "
b1111111111111111111110000011001110101010 /
b1111111111111111111010000101111001110010 #
b1111111111111111111010000101111001110010 .
b1111111111111111111100000110111111000001 !
b1111111111111111111100000110111111000001 0
b10000 )
b0 &
b0 +
b1100110000111001 %
b1100110000111001 *
b1110100001110 '
b1110100001110 ,
b1100100 1
1$
#34
0$
#35
b1111111111111111111110111100101000101000 "
b1111111111111111111110111100101000101000 /
b1111111111111111111000010110111011110001 #
b1111111111111111111000010110111011110001 .
b1111111111111111111000101100111010011101 !
b1111111111111111111000101100111010011101 0
b10001 )
b11110011011110 &
b11110011011110 +
b1100000000100000 %
b1100000000100000 *
b1111011111111011 '
b1111011111111011 ,
b1100100 1
1$
#36
0$
#37
b101001010010101000 "
b101001010010101000 /
b1111111111111111111001101100011000110001 #
b1111111111111111111001101100011000110001 .
b1111111111111111110111011011101001011010 !
b1111111111111111110111011011101001011010 0
b10010 )
b10010110011110 &
b10010110011110 +
b1101000101011001 %
b1101000101011001 *
b1101010110101101 '
b1101010110101101 ,
b1100100 1
1$
#38
0$
#39
b10001110010101101100 "
b10001110010101101100 /
b1111111111111111111110011100001111000001 #
b1111111111111111111110011100001111000001 .
b1111111111111111111001100101001111111110 !
b1111111111111111111001100101001111111110 0
b10011 )
b1101101001100010 &
b1101101001100010 +
b1111011111111011 %
b1111011111111011 *
b1100001000000011 '
b1100001000000011 ,
b1100100 1
1$
#40
0$
#41
b10111111001111010000 "
b10111111001111010000 /
b101011010110000101101 #
b101011010110000101101 .
b1111111111111111111111010010010101110100 !
b1111111111111111111111010010010101110100 0
b10100 )
b1100001100100010 &
b1100001100100010 +
b10001001001011 %
b10001001001011 *
b1100001111001001 '
b1100001111001001 ,
b1100100 1
1$
#42
0$
#43
b10101101101010111010 "
b10101101101010111010 /
b1011111110101101111011 #
b1011111110101101111011 .
b111000100001000101000 !
b111000100001000101000 0
b10101 )
b0 &
b0 +
b11110011011110 %
b11110011011110 *
b1101101001100010 '
b1101101001100010 ,
b1100100 1
1$
#44
0$
#45
b1011110111001001000 "
b1011110111001001000 /
b1110111010100110110101 #
b1110111010100110110101 .
b1110000011001110111110 !
b1110000011001110111110 0
b10110 )
b11110011011110 &
b11110011011110 +
b11101110000001 %
b11101110000001 *
b1111110111111101 '
b1111110111111101 ,
b1100100 1
1$
#46
0$
#47
b1111111111111111111111011001000011110110 "
b1111111111111111111111011001000011110110 /
b1011110011010110011010 #
b1011110011010110011010 .
b10000111000010011110110 !
b10000111000010011110110 0
b10111 )
b10010110011110 &
b10010110011110 +
b1111011010101 %
b1111011010101 *
b10001001001011 '
b10001001001011 ,
b1100100 1
1$
#48
0$
#49
b1111111111111111111100110101010110010110 "
b1111111111111111111100110101010110010110 /
b10011001010100000110 #
b10011001010100000110 .
b1101000110010011111011 !
b1101000110010011111011 0
b11000 )
b1101101001100010 &
b1101101001100010 +
b1111010000000010 %
b1111010000000010 *
b11101010111100 '
b11101010111100 ,
b1100100 1
1$
#50
0$
#51
b1111111111111111111010110110001110100010 "
b1111111111111111111010110110001110100010 /
b1111111111111111110101010101101110101100 #
b1111111111111111110101010101101110101100 .
b10100010100000000100 !
b10100010100000000100 0
b11001 )
b1100001100100010 &
b1100001100100010 +
b1100111010110000 %
b1100111010110000 *
b11111011011110 '
b11111011011110 ,
b1100100 1
1$
#52
0$
#53
b1111111111111111111010110011111000000100 "
b1111111111111111111010110011111000000100 /
b1111111111111111101001101101011101110000 #
b1111111111111111101001101101011101110000 .
b1111111111111111110100000010111000111001 !
b1111111111111111110100000010111000111001 0
b11010 )
b0 &
b0 +
b1100000000000000 %
b1100000000000000 *
b10110101000001 '
b10110101000001 ,
b1100100 1
1$
#54
0$
#55
b1111111111111111111101010011110010000110 "
b1111111111111111111101010011110010000110 /
b1111111111111111100101001101000100001101 #
b1111111111111111100101001101000100001101 .
b1111111111111111100110111100100000110101 !
b1111111111111111100110111100100000110101 0
b11011 )
b11110011011110 &
b11110011011110 +
b1100111010110000 %
b1100111010110000 *
b101111111110 '
b101111111110 ,
b1100100 1
1$
#56
0$
#57
b1100100001001100110 "
b1100100001001100110 /
b1111111111111111101011101011101000110000 #
b1111111111111111101011101011101000110000 .
b1111111111111111100001010110011111010100 !
b1111111111111111100001010110011111010100 0
b11100 )
b10010110011110 &
b10010110011110 +
b1111010000000010 %
b1111010000000010 *
b1110011010010101 '
b1110011010010101 ,
b1100100 1
1$
#58
0$
#59
b101110011000100000110 "
b101110011000100000110 /
b1111111111111111111100111010110101001001 #
b1111111111111111111100111010110101001001 .
b1111111111111111100111100111110001010001 !
b1111111111111111100111100111110001010001 0
b11101 )
b1101101001100010 &
b1101101001100010 +
b1111011010101 %
b1111011010101 *
b1100100111110111 '
b1100100111110111 ,
b1100100 1
1$
#60
0$
#61
b1000001100110100001100 "
b1000001100110100001100 /
b10011101101101100000111 #
b10011101101101100000111 .
b1111111111111111111001111110011101100010 !
b1111111111111111111001111110011101100010 0
b11110 )
b1100001100100010 &
b1100001100100010 +
b11101110000001 %
b11101110000001 *
b1100000000001000 '
b1100000000001000 ,
b1100100 1
1$
#62
0$
#63
b111101001101011100000 "
b111101001101011100000 /
b100111000100111110010110 #
b100111000100111110010110 .
b10011010111011111111011 !
b10011010111011111111011 0
b11111 )
b0 &
b0 +
b11110011011110 %
b11110011011110 *
b1100110000111001 '
b1100110000111001 ,
b1100100 1
1$
#64
0$
#65
b11111101010110001010 "
b11111101010110001010 /
b101101011111000101110001 #
b101101011111000101110001 .
b101010011100111010001100 !
b101010011100111010001100 0
b100000 )
b11110011011110 &
b11110011011110 +
b10001001001011 %
b10001001001011 *
b1110101001010010 '
b1110101001010010 ,
b1100100 1
1$
#66
0$
#67
b1111111111111111111101111000101101101110 "
b1111111111111111111101111000101101101110 /
b100001000101101011010010 #
b100001000101101011010010 .
b110100101011100111110001 !
b110100101011100111110001 0
b100001 )
b10010110011110 &
b10010110011110 +
b1111011111111011 %
b1111011111111011 *
b111111101011 '
b111111101011 ,
b1100100 1
1$
#68
0$
#69
b1111111111111111110111010110001101000100 "
b1111111111111111110111010110001101000100 /
b11001110111110001001 #
b11001110111110001001 .
b101010101100001001010010 !
b101010101100001001010010 0
b100010 )
b1101101001100010 &
b1101101001100010 +
b1101000101011001 %
b1101000101011001 *
b11000000000010 '
b11000000000010 ,
b1100100 1
1$
#70
0$
#71
b1111111111111111110011000001001000101000 "
b1111111111111111110011000001001000101000 /
b1111111111111111011101010111000111101000 #
b1111111111111111011101010111000111101000 .
b1100001011000100001110 !
b1100001011000100001110 0
b100011 )
b1100001100100010 &
b1100001100100010 +
b1100000000100000 %
b1100000000100000 *
b11111101111111 '
b11111101111111 ,
b1100100 1
1$
#72
0$
#73
b1111111111111111110011011011110000111010 "
b1111111111111111110011011011110000111010 /
b1111111111111110111110100010101110010000 #
b1111111111111110111110100010101110010000 .
b1111111111111111100001101001011011100011 !
b1111111111111111100001101001011011100011 0
b100100 )
b0 &
b0 +
b1100110000111001 %
b1100110000111001 *
b11100100000110 '
b11100100000110 ,
b1100100 1
1$
#74
0$
#75
b1111111111111111111001100000011001010110 "
b1111111111111111111001100000011001010110 /
b1111111111111110110101111010110011011011 #
b1111111111111110110101111010110011011011 .
b1111111111111110111010101100101100010010 !
b1111111111111110111010101100101100010010 0
b100101 )
b11110011011110 &
b11110011011110 +
b1111000000010101 %
b1111000000010101 *
b1111011010101 '
b1111011010101 ,
b1100100 1
1$
#76
0$
#77
b11100111101000011010 "
b11100111101000011010 /
b1111111111111111001011111111010110000100 #
b1111111111111111001011111111010110000100 .
b1111111111111110101000110011001111011110 !
b1111111111111110101000110011001111011110 0
b100110 )
b10010110011110 &
b10010110011110 +
b1101101000000 %
b1101101000000 *
b1111100111111010 '
b1111100111111010 ,
b1100100 1
1$
#78
0$
#79
b1110001000111100001110 "
b1110001000111100001110 /
b1111111111111111111101100011101011010010 #
b1111111111111111111101100011101011010010 .
b1111111111111110111000010000011011010100 !
b1111111111111110111000010000011011010100 0
b100111 )
b1101101001100010 &
b1101101001100010 +
b11100111101001 %
b11100111101001 *
b1101011100110100 '
b1101011100110100 ,
b1100100 1
1$
#80
0$
#81
b10100110000001001110100 "
b10100110000001001110100 /
b111010101110010101000111 #
b111010101110010101000111 .
b1111111111111111101001110000110110111101 !
b1111111111111111101001110000110110111101 0
b101000 )
b1100001100100010 &
b1100001100100010 +
b11110111111101 %
b11110111111101 *
b1100001010001011 '
b1100001010001011 ,
b1100100 1
1$
#82
0$
#83
b10100000101011010001100 "
b10100000101011010001100 /
b1101011010001111001110000 #
b1101011010001111001110000 .
b101111100110110111000000 !
b101111100110110111000000 0
b101001 )
b0 &
b0 +
b10010110011110 %
b10010110011110 *
b1100001100100010 '
b1100001100100010 ,
b1100100 1
1$
#84
0$
#85
b1010111010110101000010 "
b1010111010110101000010 /
b1110111100000010011110011 #
b1110111100000010011110011 .
b1110000010111100101111100 !
b1110000010111100101111100 0
b101010 )
b11110011011110 &
b11110011011110 +
b1111101111111011 %
b1111101111111011 *
b1101100011000110 '
b1101100011000110 ,
b1100100 1
1$
#86
0$
#87
b1111111111111111111010111011010001011010 "
b1111111111111111111010111011010001011010 /
b1010010011010101111111111 #
b1010010011010101111111111 .
b10001111001001101101110001 !
b10001111001001101101110001 0
b101011 )
b10010110011110 &
b10010110011110 +
b1101010000110000 %
b1101010000110000 *
b1111101111111011 '
b1111101111111011 ,
b1100100 1
1$
#88
0$
#89
b1111111111111111101000101011000001101000 "
b1111111111111111101000101011000001101000 /
b1010010011101100000 #
b1010010011101100000 .
b1110110111100101000011011 !
b1110110111100101000011011 0
b101100 )
b1101101001100010 &
b1101101001100010 +
b1100000010000001 %
b1100000010000001 *
b10000010010100 '
b10000010010100 ,
b1100100 1
1$
#90
0$
#91
b1111111111111111011011000001000100101100 "
b1111111111111111011011000001000100101100 /
b1111111111111110011101000010101101010101 #
b1111111111111110011101000010101101010101 .
b100101010001010110001110 !
b100101010001010110001110 0
b101101 )
b1100001100100010 &
b1100001100100010 +
b1100100111110111 %
b1100100111110111 *
b11100111101001 '
b11100111101001 ,
b1100100 1
1$
#92
0$
#93
b1111111111111111011001001011100100010110 "
b1111111111111111011001001011100100010110 /
b1111111111111101001011111000011010011101 #
b1111111111111101001011111000011010011101 .
b1111111111111110101111011110111111001011 !
b1111111111111110101111011110111111001011 0
b101110 )
b0 &
b0 +
b1110110000111001 %
b1110110000111001 *
b11111100110110 '
b11111100110110 ,
b1100100 1
1$
#94
0$
#95
b1111111111111111100111110101110110010100 "
b1111111111111111100111110101110110010100 /
b1111111111111100110100011111011010100001 #
b1111111111111100110100011111011010100001 .
b1111111111111100111111100101100010101011 !
b1111111111111100111111100101100010101011 0
b101111 )
b11110011011110 &
b11110011011110 +
b1011110001111 %
b1011110001111 *
b10111010100111 '
b10111010100111 ,
b1100100 1
1$
#96
0$
#97
b110111100101010101010 "
b110111100101010101010 /
b1111111111111101101111001001101100111001 #
b1111111111111101101111001001101100111001 .
b1111111111111100001000001110001000101001 !
b1111111111111100001000001110001000101001 0
b110000 )
b10010110011110 &
b10010110011110 +
b11100000010101 %
b11100000010101 *
b110111110110 '
b110111110110 ,
b1100100 1
1$
#98
0$
#99
b110001011000000010110110 "
b110001011000000010110110 /
b1111111111111111111010010100010100111100 #
b1111111111111111111010010100010100111100 .
b1111111111111100110010111010011000011010 !
b1111111111111100110010111010011000011010 0
b110001 )
b1101101001100010 &
b1101101001100010 +
b11111011011110 %
b11111011011110 *
b1110100001110001 '
b1110100001110001 ,
b1100100 1
1$
#100
0$
#101
b1011110100010100010111100 "
b1011110100010100010111100 /
b10110111101010001111110111 #
b10110111101010001111110111 .
b1111111111111111001110011110011011110001 !
b1111111111111111001110011110011011110001 0
b110010 )
b1100001100100010 &
b1100001100100010 +
b10100011001100 %
b10100011001100 *
b1100101100010001 '
b1100101100010001 ,
b1100100 1
1$
#102
0$
#103
b10000100100000101100001110 "
b10000100100000101100001110 /
b101110011011101000011100111 #
b101110011011101000011100111 .
b11000100001000010110110011 !
b11000100001000010110110011 0
b110011 )
b0 &
b0 +
b0 %
b0 *
b1100000000000000 '
b1100000000000000 ,
b1100100 1
1$
#104
0$
#105
b10011010011100010111111000 "
b10011010011100010111111000 /
b111110100101111111011001111 #
b111110100101111111011001111 .
b111011000101101001001110101 !
b111011000101101001001110101 0
b110100 )
b11110011011110 &
b11110011011110 +
b1101011100110100 %
b1101011100110100 *
b1100101100010001 '
b1100101100010001 ,
b1100100 1
1$
#106
0$
#107
b10011010110000010010101100 "
b10011010110000010010101100 /
b1000010000110001100101100000 #
b1000010000110001100101100000 .
b1010111011001010011111111000 !
b1010111011001010011111111000 0
b110101 )
b10010110011110 &
b10010110011110 +
b1100000100100010 %
b1100000100100010 *
b1110100001110001 '
b1110100001110001 ,
b1100100 1
1$
#108
0$
#109
b10000101000000111010111010 "
b10000101000000111010111010 /
b110111010101010110010010001 #
b110111010101010110010010001 .
b1100011101001100000001101010 !
b1100011101001100000001101010 0
b110110 )
b1101101001100010 &
b1101101001100010 +
b1100011111101011 %
b1100011111101011 *
b110111110110 '
b110111110110 ,
b1100100 1
1$
#110
0$
#111
b1011110100010100010111100 "
b1011110100010100010111100 /
b100001001011000001000110110 #
b100001001011000001000110110 .
b1011001110010000110011101011 !
b1011001110010000110011101011 0
b110111 )
b1100001100100010 &
b1100001100100010 +
b1110100001110001 %
b1110100001110001 *
b10111010100111 '
b10111010100111 ,
b1100100 1
1$
#112
0$
#113
b110000110111110100001010 "
b110000110111110100001010 /
b110001000001111100000111 #
b110001000001111100000111 .
b111001111111001011111000001 !
b111001111111001011111000001 0
b111000 )
b0 &
b0 +
b1001111000111 %
b1001111000111 *
b11111100110110 '
b11111100110110 ,
b1100100 1
1$
#114
0$
#115
b110101000101111110110 "
b110101000101111110110 /
b1111111111111101110001101111110010111011 #
b1111111111111101110001101111110010111011 .
b1011011000010110100001001 !
b1011011000010110100001001 0
b111001 )
b11110011011110 &
b11110011011110 +
b11011000001001 %
b11011000001001 *
b11100111101001 '
b11100111101001 ,
b1100100 1
1$
#116
0$
#117
b1111111111111111101000001001110001001000 "
b1111111111111111101000001001110001001000 /
b1111111111111100000001110001101000000011 #
b1111111111111100000001110001101000000011 .
b1111111111111011010011000100010110010011 !
b1111111111111011010011000100010110010011 0
b111010 )
b10010110011110 &
b10010110011110 +
b11111101111111 %
b11111101111111 *
b10000010010100 '
b10000010010100 ,
b1100100 1
1$
#118
0$
#119
b1111111111111111011001101011110011000010 "
b1111111111111111011001101011110011000010 /
b1111111111111011111011001000010011000100 #
b1111111111111011111011001000010011000100 .
b1111111111110110101001001001110001100011 !
b1111111111110110101001001001110001100011 0
b111011 )
b1101101001100010 &
b1101101001100010 +
b10101111010000 %
b10101111010000 *
b1111101111111011 '
b1111101111111011 ,
b1100100 1
1$
#120
0$
#121
b1111111111111111011011000001000100101100 "
b1111111111111111011011000001000100101100 /
b1111111111111101010011010100000100111011 #
b1111111111111101010011010100000100111011 .
b1111111111110100111000011000100111011101 !
b1111111111110100111000011000100111011101 0
b111100 )
b1100001100100010 &
b1100001100100010 +
b10000000101 %
b10000000101 *
b1101100011000110 '
b1101100011000110 ,
b1100100 1
1$
#122
0$
#123
b1111111111111111101000001010110010111100 "
b1111111111111111101000001010110010111100 /
b1111111111111111100000011010110010011010 #
b1111111111111111100000011010110010011010 .
b1111111111110110100110011111111001011111 !
b1111111111110110100110011111111001011111 0
b111101 )
b0 &
b0 +
b1101101001100010 %
b1101101001100010 *
b1100001100100010 '
b1100001100100010 ,
b1100100 1
1$
#124
0$
#125
b1111111111111111111010100111010110100110 "
b1111111111111111111010100111010110100110 /
b1101001011111010010100101 #
b1101001011111010010100101 .
b1111111111111011010100010011000011100011 !
b1111111111111011010100010011000011100011 0
b111110 )
b11110011011110 &
b11110011011110 +
b1100001000000011 %
b1100001000000011 *
b1100001010001011 '
b1100001010001011 ,
b1100100 1
1$
#126
0$
#127
b1011001110101111110110 "
b1011001110101111110110 /
b10111011111011000101110110 #
b10111011111011000101110110 .
b1100100010000111000010011 !
b1100100010000111000010011 0
b111111 )
b10010110011110 &
b10010110011110 +
b1100011000010111 %
b1100011000010111 *
b1101011100110100 '
b1101011100110100 ,
b1100100 1
1$
#128
0$
#129
b10100100101101000111000 "
b10100100101101000111000 /
b10111101101000111010100100 #
b10111101101000111010100100 .
b111010110011011111001101011 !
b111010110011011111001101011 0
b1000000 )
b1101101001100010 &
b1101101001100010 +
b1110010011000000 %
b1110010011000000 *
b1111100111111010 '
b1111100111111010 ,
b1100100 1
1$
#130
0$
#131
b10100110000001001110100 "
b10100110000001001110100 /
b1110101001110000101010100 #
b1110101001110000101010100 .
b1010110001010010110010101000 !
b1010110001010010110010101000 0
b1000001 )
b1100001100100010 &
b1100001100100010 +
b111111101011 %
b111111101011 *
b1111011010101 '
b1111011010101 ,
b1100100 1
1$
#132
0$
#133
b1101101000101101100010 "
b1101101000101101100010 /
b101010101101100100011 #
b101010101101100100011 .
b1010101010011010011000001110 !
b1010101010011010011000001110 0
b1000010 )
b0 &
b0 +
b11001111000111 %
b11001111000111 *
b11100100000110 '
b11100100000110 ,
b1100100 1
1$
#134
0$
#135
b11010011101101100110 "
b11010011101101100110 /
b1111111111111110011101011110111010011110 #
b1111111111111110011101011110111010011110 .
b111000000110000111010011011 !
b111000000110000111010011011 0
b1000011 )
b11110011011110 &
b11110011011110 +
b11111111100000 %
b11111111100000 *
b11111101111111 '
b11111101111111 ,
b1100100 1
1$
#136
0$
#137
b1111111111111111111001110100010100001010 "
b1111111111111111111001110100010100001010 /
b1111111111111101100110011101111100000000 #
b1111111111111101100110011101111100000000 .
b111111000111001100111110 !
b111111000111001100111110 0
b1000100 )
b10010110011110 &
b10010110011110 +
b10111010100111 %
b10111010100111 *
b11000000000010 '
b11000000000010 ,
b1100100 1
1$
#138
0$
#139
b1111111111111111110011111011111111100110 "
b1111111111111111110011111011111111100110 /
b1111111111111101110010100111001100110100 #
b1111111111111101110010100111001100110100 .
b1111111111111010100100101101111101110110 !
b1111111111111010100100101101111101110110 0
b1000101 )
b1101101001100010 &
b1101101001100010 +
b100000000101 %
b100000000101 *
b111111101011 '
b111111101011 ,
b1100100 1
1$
#140
0$
