main-03.v
module add(
    input  wire  clk,        
    input  wire  rst,       
    input  wire [16:0] a,         
    input  wire [16:0] b,         
    output reg  [17:0] result     
);

reg [16:0] a_reg, b_reg;          

always @(posedge clk or posedge rst) begin
    if (rst) begin
        result   <= 17'b0;
    end else begin
         a_reg<=a;
         b_reg<=b;
         result <= {a_reg[16], a_reg} + {b_reg[16], b_reg};
    end
end

endmodule

module subtract(
    input  wire  clk,
    input  wire  rst,
    input  wire [16:0] a,
    input  wire [16:0] b,
    output reg  [17:0] result
);

reg [16:0] a_reg, b_reg, b_neg;

always @(posedge clk or posedge rst) begin
    if (rst) begin
        result   <= 17'b0;
    end else begin
            a_reg <= a;
            b_reg <= b;
            // Compute two's complement of b
            b_neg <= ~b_reg + 1'b1;
            // Add a and negated b
            result <= {a_reg[16], a_reg} + {b_neg[16], b_neg};
    end
end

endmodule


module mul(
    input  wire        clk,
    input  wire        rst,
    input  wire [16:0] a,
    input  wire [16:0] b,
    output reg  [33:0] result
);

reg [33:0] product;

always @(posedge clk or posedge rst) begin
    if (rst) begin
        result <= 34'b0;
    end else begin
        // Sign-extend and multiply
        product <= {{17{a[16]}}, a} * {{17{b[16]}}, b};
        result  <= product;
    end
end

endmodule

main-03.tb.v
`timescale 1ns/1ns

module tb;

reg        clk;
reg        rst;
reg  [16:0] q_3_14 [0:47999];   
reg  [16:0] q_5_12 [0:47999];   
reg  [16:0] a_reg, b_reg;


wire [17:0] add_res, sub_res;
wire [33:0] mul_res;


integer i;
reg  [15:0] sample_idx;
reg         start;
wire        done;

add add_mod (
    .clk(clk),
    .rst(rst),
    .a(a_reg),
    .b(b_reg),
    .result(add_res)
);

subtract sub_mod (
    .clk(clk),
    .rst(rst),
    .a(a_reg),
    .b(b_reg),
    .result(sub_res)
);

mul mul_mod (
    .clk(clk),
    .rst(rst),
    .a(a_reg),
    .b(b_reg),
    .result(mul_res)
);


always #1 clk = ~clk;



always @(posedge clk or posedge rst) begin
    if (rst) begin
        a_reg <= 17'b0;
        b_reg <= 17'b0;
        i=0;
    end else begin
            a_reg <= q_3_14[i];
            b_reg <= q_5_12[i];
            i=i+1;
    end
end

task read_q_3_14;
    integer i, file;
    begin
        file = $fopen("q_3_14.txt", "r");
        for(i = 0; i < 48000; i=i+1) begin
            $fscanf(file, "%b\n", q_3_14[i]);
        end
        $fclose(file);
    end
endtask

task read_q_5_12;
    integer i, file;
    begin
        file = $fopen("q_5_12.txt", "r");
        for(i = 0; i < 48000; i=i+1) begin
            $fscanf(file, "%b\n", q_5_12[i]);
        end
        $fclose(file);
    end
endtask

initial begin
    $dumpfile("wave-03.vcd"); 
    $dumpvars(0, tb);
end

initial begin
    clk = 0;
    rst = 1;
    read_q_3_14();
    read_q_5_12(); 
    
    #2 rst = 0;
  #500;
    $finish;
end

endmodule

wave-03.vcd
$date
	Thu Feb 19 11:59:28 2026
$end
$version
	Icarus Verilog
$end
$timescale
	1ns
$end
$scope module tb $end
$var wire 18 ! sub_res [17:0] $end
$var wire 34 " mul_res [33:0] $end
$var wire 18 # add_res [17:0] $end
$var reg 17 $ a_reg [16:0] $end
$var reg 17 % b_reg [16:0] $end
$var reg 1 & clk $end
$var reg 1 ' rst $end
$var integer 32 ( i [31:0] $end
$scope module add_mod $end
$var wire 17 ) a [16:0] $end
$var wire 17 * b [16:0] $end
$var wire 1 & clk $end
$var wire 1 ' rst $end
$var reg 17 + a_reg [16:0] $end
$var reg 17 , b_reg [16:0] $end
$var reg 18 - result [17:0] $end
$upscope $end
$scope module mul_mod $end
$var wire 17 . a [16:0] $end
$var wire 17 / b [16:0] $end
$var wire 1 & clk $end
$var wire 1 ' rst $end
$var reg 34 0 product [33:0] $end
$var reg 34 1 result [33:0] $end
$upscope $end
$scope module sub_mod $end
$var wire 17 2 a [16:0] $end
$var wire 17 3 b [16:0] $end
$var wire 1 & clk $end
$var wire 1 ' rst $end
$var reg 17 4 a_reg [16:0] $end
$var reg 17 5 b_neg [16:0] $end
$var reg 17 6 b_reg [16:0] $end
$var reg 18 7 result [17:0] $end
$upscope $end
$scope task read_q_3_14 $end
$var integer 32 8 file [31:0] $end
$var integer 32 9 i [31:0] $end
$upscope $end
$scope task read_q_5_12 $end
$var integer 32 : file [31:0] $end
$var integer 32 ; i [31:0] $end
$upscope $end
$upscope $end
$enddefinitions $end
$comment Show the parameter values. $end
$dumpall
$end
#0
$dumpvars
b1011101110000000 ;
b10000000000000000000000000000011 :
b1011101110000000 9
b10000000000000000000000000000011 8
b0 7
bx 6
bx 5
bx 4
b0 3
b0 2
b0 1
bx 0
b0 /
b0 .
b0 -
bx ,
bx +
b0 *
b0 )
b0 (
1'
0&
b0 %
b0 $
b0 #
b0 "
b0 !
$end
#1
1&
#2
0&
0'
#3
bx #
bx -
b0 ,
b0 +
bx !
bx 7
b0 6
b0 4
bx "
bx 1
b0 0
b1 (
1&
#4
0&
#5
b10000101101 %
b10000101101 *
b10000101101 /
b10000101101 3
b1000010110101 $
b1000010110101 )
b1000010110101 .
b1000010110101 2
b0 "
b0 1
b0 5
b0 #
b0 -
b10 (
1&
#6
0&
#7
b10000101101 ,
b1000010110101 +
b0 !
b0 7
b10000101101 6
b1000010110101 4
b10001011100001111010001 0
b100001001000 %
b100001001000 *
b100001001000 /
b100001001000 3
b10000100100001 $
b10000100100001 )
b10000100100001 .
b10000100100001 2
b11 (
1&
#8
0&
#9
b110000111111 %
b110000111111 *
b110000111111 /
b110000111111 3
b11000011111100 $
b11000011111100 )
b11000011111100 .
b11000011111100 2
b10001011100001111010001 "
b10001011100001111010001 1
b1000100100101100101001000 0
b1000010110101 !
b1000010110101 7
b11111101111010011 5
b100001001000 6
b10000100100001 4
b1010011100010 #
b1010011100010 -
b100001001000 ,
b10000100100001 +
b100 (
1&
#10
0&
#11
b10100101101001 #
b10100101101001 -
b110000111111 ,
b11000011111100 +
b1110011110100 !
b1110011110100 7
b11111011110111000 5
b110000111111 6
b11000011111100 4
b1000100100101100101001000 "
b1000100100101100101001000 1
b10010101111101111000000100 0
b1000000000000 %
b1000000000000 *
b1000000000000 /
b1000000000000 3
b100000000000000 $
b100000000000000 )
b100000000000000 .
b100000000000000 2
b101 (
1&
#12
0&
#13
b1001101111011 %
b1001101111011 *
b1001101111011 /
b1001101111011 3
b100110111101100 $
b100110111101100 )
b100110111101100 .
b100110111101100 2
b10010101111101111000000100 "
b10010101111101111000000100 1
b100000000000000000000000000 0
b10100010110100 !
b10100010110100 7
b11111001111000001 5
b1000000000000 6
b100000000000000 4
b11110100111011 #
b11110100111011 -
b1000000000000 ,
b100000000000000 +
b110 (
1&
#14
0&
#15
b101000000000000 #
b101000000000000 -
b1001101111011 ,
b100110111101100 +
b11001111000001 !
b11001111000001 7
b11111000000000000 5
b1001101111011 6
b100110111101100 4
b100000000000000000000000000 "
b100000000000000000000000000 1
b101111011011111010001100100 0
b1011010100001 %
b1011010100001 *
b1011010100001 /
b1011010100001 3
b101101010000010 $
b101101010000010 )
b101101010000010 .
b101101010000010 2
b111 (
1&
#16
0&
#17
b1100101100011 %
b1100101100011 *
b1100101100011 /
b1100101100011 3
b110010110001101 $
b110010110001101 )
b110010110001101 .
b110010110001101 2
b101111011011111010001100100 "
b101111011011111010001100100 1
b1000000000000001011111000010 0
b11110111101100 !
b11110111101100 7
b11110110010000101 5
b1011010100001 6
b101101010000010 4
b110000101100111 #
b110000101100111 -
b1011010100001 ,
b101101010000010 +
b1000 (
1&
#18
0&
#19
b111000100100011 #
b111000100100011 -
b1100101100011 ,
b110010110001101 +
b100011100000111 !
b100011100000111 7
b11110100101011111 5
b1100101100011 6
b110010110001101 4
b1000000000000001011111000010 "
b1000000000000001011111000010 1
b1010000100100000101010000111 0
b1101110110110 %
b1101110110110 *
b1101110110110 /
b1101110110110 3
b110111011011010 $
b110111011011010 )
b110111011011010 .
b110111011011010 2
b1001 (
1&
#20
0&
#21
b1110110010000 %
b1110110010000 *
b1110110010000 /
b1110110010000 3
b111011001000010 $
b111011001000010 )
b111011001000010 .
b111011001000010 2
b1010000100100000101010000111 "
b1010000100100000101010000111 1
b1011111111111100110011111100 0
b100111011101100 !
b100111011101100 7
b11110011010011101 5
b1101110110110 6
b110111011011010 4
b111111011110000 #
b111111011110000 -
b1101110110110 ,
b110111011011010 +
b1010 (
1&
#22
0&
#23
b1000101010010000 #
b1000101010010000 -
b1110110010000 ,
b111011001000010 +
b101010101110111 !
b101010101110111 7
b11110010001001010 5
b1110110010000 6
b111011001000010 4
b1011111111111100110011111100 "
b1011111111111100110011111100 1
b1101101001111111111100100000 0
b1111011101001 %
b1111011101001 *
b1111011101001 /
b1111011101001 3
b111101110100011 $
b111101110100011 )
b111101110100011 .
b111101110100011 2
b1011 (
1&
#24
0&
#25
b1111110111010 %
b1111110111010 *
b1111110111010 /
b1111110111010 3
b111111011101000 $
b111111011101000 )
b111111011101000 .
b111111011101000 2
b1101101001111111111100100000 "
b1101101001111111111100100000 1
b1110111011011010000101011011 0
b101101010001100 !
b101101010001100 7
b11110001001110000 5
b1111011101001 6
b111101110100011 4
b1001001111010010 #
b1001001111010010 -
b1111011101001 ,
b111101110100011 +
b1100 (
1&
#26
0&
#27
b1001101010001100 #
b1001101010001100 -
b1111110111010 ,
b111111011101000 +
b101111000010011 !
b101111000010011 7
b11110000100010111 5
b1111110111010 6
b111111011101000 4
b1110111011011010000101011011 "
b1110111011011010000101011011 1
b1111101110100100110010010000 0
b10000000000000 %
b10000000000000 *
b10000000000000 /
b10000000000000 3
b1000000000000000 $
b1000000000000000 )
b1000000000000000 .
b1000000000000000 2
b1101 (
1&
#28
0&
#29
b1111110111010 %
b1111110111010 *
b1111110111010 /
b1111110111010 3
b111111011101000 $
b111111011101000 )
b111111011101000 .
b111111011101000 2
b1111101110100100110010010000 "
b1111101110100100110010010000 1
b10000000000000000000000000000 0
b101111111111111 !
b101111111111111 7
b11110000001000110 5
b10000000000000 6
b1000000000000000 4
b1001111010100010 #
b1001111010100010 -
b10000000000000 ,
b1000000000000000 +
b1110 (
1&
#30
0&
#31
b1010000000000000 #
b1010000000000000 -
b1111110111010 ,
b111111011101000 +
b110000001000110 !
b110000001000110 7
b11110000000000000 5
b1111110111010 6
b111111011101000 4
b10000000000000000000000000000 "
b10000000000000000000000000000 1
b1111101110100100110010010000 0
b1111011101001 %
b1111011101001 *
b1111011101001 /
b1111011101001 3
b111101110100011 $
b111101110100011 )
b111101110100011 .
b111101110100011 2
b1111 (
1&
#32
0&
#33
b1110110010000 %
b1110110010000 *
b1110110010000 /
b1110110010000 3
b111011001000010 $
b111011001000010 )
b111011001000010 .
b111011001000010 2
b1111101110100100110010010000 "
b1111101110100100110010010000 1
b1110111011011010000101011011 0
b101111011101000 !
b101111011101000 7
b11110000001000110 5
b1111011101001 6
b111101110100011 4
b1001111010100010 #
b1001111010100010 -
b1111011101001 ,
b111101110100011 +
b10000 (
1&
#34
0&
#35
b1001101010001100 #
b1001101010001100 -
b1110110010000 ,
b111011001000010 +
b101101111101001 !
b101101111101001 7
b11110000100010111 5
b1110110010000 6
b111011001000010 4
b1110111011011010000101011011 "
b1110111011011010000101011011 1
b1101101001111111111100100000 0
b1101110110110 %
b1101110110110 *
b1101110110110 /
b1101110110110 3
b110111011011010 $
b110111011011010 )
b110111011011010 .
b110111011011010 2
b10001 (
1&
#36
0&
#37
b1100101100011 %
b1100101100011 *
b1100101100011 /
b1100101100011 3
b110010110001101 $
b110010110001101 )
b110010110001101 .
b110010110001101 2
b1101101001111111111100100000 "
b1101101001111111111100100000 1
b1011111111111100110011111100 0
b101011101011001 !
b101011101011001 7
b11110001001110000 5
b1101110110110 6
b110111011011010 4
b1001001111010010 #
b1001001111010010 -
b1101110110110 ,
b110111011011010 +
b10010 (
1&
#38
0&
#39
b1000101010010000 #
b1000101010010000 -
b1100101100011 ,
b110010110001101 +
b101000101001010 !
b101000101001010 7
b11110010001001010 5
b1100101100011 6
b110010110001101 4
b1011111111111100110011111100 "
b1011111111111100110011111100 1
b1010000100100000101010000111 0
b1011010100001 %
b1011010100001 *
b1011010100001 /
b1011010100001 3
b101101010000010 $
b101101010000010 )
b101101010000010 .
b101101010000010 2
b10011 (
1&
#40
0&
#41
b1001101111011 %
b1001101111011 *
b1001101111011 /
b1001101111011 3
b100110111101100 $
b100110111101100 )
b100110111101100 .
b100110111101100 2
b1010000100100000101010000111 "
b1010000100100000101010000111 1
b1000000000000001011111000010 0
b100100111010111 !
b100100111010111 7
b11110011010011101 5
b1011010100001 6
b101101010000010 4
b111111011110000 #
b111111011110000 -
b1011010100001 ,
b101101010000010 +
b10100 (
1&
#42
0&
#43
b111000100100011 #
b111000100100011 -
b1001101111011 ,
b100110111101100 +
b100000100011111 !
b100000100011111 7
b11110100101011111 5
b1001101111011 6
b100110111101100 4
b1000000000000001011111000010 "
b1000000000000001011111000010 1
b101111011011111010001100100 0
b1000000000000 %
b1000000000000 *
b1000000000000 /
b1000000000000 3
b100000000000000 $
b100000000000000 )
b100000000000000 .
b100000000000000 2
b10101 (
1&
#44
0&
#45
b110000111111 %
b110000111111 *
b110000111111 /
b110000111111 3
b11000011111100 $
b11000011111100 )
b11000011111100 .
b11000011111100 2
b101111011011111010001100100 "
b101111011011111010001100100 1
b100000000000000000000000000 0
b11011101001011 !
b11011101001011 7
b11110110010000101 5
b1000000000000 6
b100000000000000 4
b110000101100111 #
b110000101100111 -
b1000000000000 ,
b100000000000000 +
b10110 (
1&
#46
0&
#47
b101000000000000 #
b101000000000000 -
b110000111111 ,
b11000011111100 +
b10110010000101 !
b10110010000101 7
b11111000000000000 5
b110000111111 6
b11000011111100 4
b100000000000000000000000000 "
b100000000000000000000000000 1
b10010101111101111000000100 0
b100001001000 %
b100001001000 *
b100001001000 /
b100001001000 3
b10000100100001 $
b10000100100001 )
b10000100100001 .
b10000100100001 2
b10111 (
1&
#48
0&
#49
b10000101101 %
b10000101101 *
b10000101101 /
b10000101101 3
b1000010110101 $
b1000010110101 )
b1000010110101 .
b1000010110101 2
b10010101111101111000000100 "
b10010101111101111000000100 1
b1000100100101100101001000 0
b10000011111100 !
b10000011111100 7
b11111001111000001 5
b100001001000 6
b10000100100001 4
b11110100111011 #
b11110100111011 -
b100001001000 ,
b10000100100001 +
b11000 (
1&
#50
0&
#51
b10100101101001 #
b10100101101001 -
b10000101101 ,
b1000010110101 +
b1010011100010 !
b1010011100010 7
b11111011110111000 5
b10000101101 6
b1000010110101 4
b1000100100101100101001000 "
b1000100100101100101001000 1
b10001011100001111010001 0
b0 %
b0 *
b0 /
b0 3
b0 $
b0 )
b0 .
b0 2
b11001 (
1&
#52
0&
#53
b11111101111010011 %
b11111101111010011 *
b11111101111010011 /
b11111101111010011 3
b11110111101001011 $
b11110111101001011 )
b11110111101001011 .
b11110111101001011 2
b10001011100001111010001 "
b10001011100001111010001 1
b0 0
b100001101101 !
b100001101101 7
b11111101111010011 5
b0 6
b0 4
b1010011100010 #
b1010011100010 -
b0 ,
b0 +
b11010 (
1&
#54
0&
#55
b0 #
b0 -
b11111101111010011 ,
b11110111101001011 +
b111111101111010011 !
b111111101111010011 7
b0 5
b11111101111010011 6
b11110111101001011 4
b0 "
b0 1
b10001011100001111010001 0
b11111011110111000 %
b11111011110111000 *
b11111011110111000 /
b11111011110111000 3
b11101111011011111 $
b11101111011011111 )
b11101111011011111 .
b11101111011011111 2
b11011 (
1&
#56
0&
#57
b11111001111000001 %
b11111001111000001 *
b11111001111000001 /
b11111001111000001 3
b11100111100000100 $
b11100111100000100 )
b11100111100000100 .
b11100111100000100 2
b10001011100001111010001 "
b10001011100001111010001 1
b1000100100101100101001000 0
b111110111101001011 !
b111110111101001011 7
b10000101101 5
b11111011110111000 6
b11101111011011111 4
b111110101100011110 #
b111110101100011110 -
b11111011110111000 ,
b11101111011011111 +
b11100 (
1&
#58
0&
#59
b111101011010010111 #
b111101011010010111 -
b11111001111000001 ,
b11100111100000100 +
b111110001100001100 !
b111110001100001100 7
b100001001000 5
b11111001111000001 6
b11100111100000100 4
b1000100100101100101001000 "
b1000100100101100101001000 1
b10010101111101111000000100 0
b11111000000000000 %
b11111000000000000 *
b11111000000000000 /
b11111000000000000 3
b11100000000000000 $
b11100000000000000 )
b11100000000000000 .
b11100000000000000 2
b11101 (
1&
#60
0&
#61
b11110110010000101 %
b11110110010000101 *
b11110110010000101 /
b11110110010000101 3
b11011001000010100 $
b11011001000010100 )
b11011001000010100 .
b11011001000010100 2
b10010101111101111000000100 "
b10010101111101111000000100 1
b100000000000000000000000000 0
b111101011101001100 !
b111101011101001100 7
b110000111111 5
b11111000000000000 6
b11100000000000000 4
b111100001011000101 #
b111100001011000101 -
b11111000000000000 ,
b11100000000000000 +
b11110 (
1&
#62
0&
#63
b111011000000000000 #
b111011000000000000 -
b11110110010000101 ,
b11011001000010100 +
b111100110000111111 !
b111100110000111111 7
b1000000000000 5
b11110110010000101 6
b11011001000010100 4
b100000000000000000000000000 "
b100000000000000000000000000 1
b101111011011111010001100100 0
b11110100101011111 %
b11110100101011111 *
b11110100101011111 /
b11110100101011111 3
b11010010101111110 $
b11010010101111110 )
b11010010101111110 .
b11010010101111110 2
b11111 (
1&
#64
0&
#65
b11110011010011101 %
b11110011010011101 *
b11110011010011101 /
b11110011010011101 3
b11001101001110011 $
b11001101001110011 )
b11001101001110011 .
b11001101001110011 2
b101111011011111010001100100 "
b101111011011111010001100100 1
b1000000000000001011111000010 0
b111100001000010100 !
b111100001000010100 7
b1001101111011 5
b11110100101011111 6
b11010010101111110 4
b111001111010011001 #
b111001111010011001 -
b11110100101011111 ,
b11010010101111110 +
b100000 (
1&
#66
0&
#67
b111000111011011101 #
b111000111011011101 -
b11110011010011101 ,
b11001101001110011 +
b111011100011111001 !
b111011100011111001 7
b1011010100001 5
b11110011010011101 6
b11001101001110011 4
b1000000000000001011111000010 "
b1000000000000001011111000010 1
b1010000100100000101010000111 0
b11110010001001010 %
b11110010001001010 *
b11110010001001010 /
b11110010001001010 3
b11001000100100110 $
b11001000100100110 )
b11001000100100110 .
b11001000100100110 2
b100001 (
1&
#68
0&
#69
b11110001001110000 %
b11110001001110000 *
b11110001001110000 /
b11110001001110000 3
b11000100110111110 $
b11000100110111110 )
b11000100110111110 .
b11000100110111110 2
b1010000100100000101010000111 "
b1010000100100000101010000111 1
b1011111111111100110011111100 0
b111011000100010100 !
b111011000100010100 7
b1100101100011 5
b11110010001001010 6
b11001000100100110 4
b111000000100010000 #
b111000000100010000 -
b11110010001001010 ,
b11001000100100110 +
b100010 (
1&
#70
0&
#71
b110111010101110000 #
b110111010101110000 -
b11110001001110000 ,
b11000100110111110 +
b111010101010001001 !
b111010101010001001 7
b1101110110110 5
b11110001001110000 6
b11000100110111110 4
b1011111111111100110011111100 "
b1011111111111100110011111100 1
b1101101001111111111100100000 0
b11110000100010111 %
b11110000100010111 *
b11110000100010111 /
b11110000100010111 3
b11000010001011101 $
b11000010001011101 )
b11000010001011101 .
b11000010001011101 2
b100011 (
1&
#72
0&
#73
b11110000001000110 %
b11110000001000110 *
b11110000001000110 /
b11110000001000110 3
b11000000100011000 $
b11000000100011000 )
b11000000100011000 .
b11000000100011000 2
b1101101001111111111100100000 "
b1101101001111111111100100000 1
b1110111011011010000101011011 0
b111010010101110100 !
b111010010101110100 7
b1110110010000 5
b11110000100010111 6
b11000010001011101 4
b110110110000101110 #
b110110110000101110 -
b11110000100010111 ,
b11000010001011101 +
b100100 (
1&
#74
0&
#75
b110110010101110100 #
b110110010101110100 -
b11110000001000110 ,
b11000000100011000 +
b111010000111101101 !
b111010000111101101 7
b1111011101001 5
b11110000001000110 6
b11000000100011000 4
b1110111011011010000101011011 "
b1110111011011010000101011011 1
b1111101110100100110010010000 0
b11110000000000000 %
b11110000000000000 *
b11110000000000000 /
b11110000000000000 3
b11000000000000000 $
b11000000000000000 )
b11000000000000000 .
b11000000000000000 2
b100101 (
1&
#76
0&
#77
b11110000001000110 %
b11110000001000110 *
b11110000001000110 /
b11110000001000110 3
b11000000100011000 $
b11000000100011000 )
b11000000100011000 .
b11000000100011000 2
b1111101110100100110010010000 "
b1111101110100100110010010000 1
b10000000000000000000000000000 0
b111010000000000001 !
b111010000000000001 7
b1111110111010 5
b11110000000000000 6
b11000000000000000 4
b110110000101011110 #
b110110000101011110 -
b11110000000000000 ,
b11000000000000000 +
b100110 (
1&
#78
0&
#79
b110110000000000000 #
b110110000000000000 -
b11110000001000110 ,
b11000000100011000 +
b111001111110111010 !
b111001111110111010 7
b10000000000000 5
b11110000001000110 6
b11000000100011000 4
b10000000000000000000000000000 "
b10000000000000000000000000000 1
b1111101110100100110010010000 0
b11110000100010111 %
b11110000100010111 *
b11110000100010111 /
b11110000100010111 3
b11000010001011101 $
b11000010001011101 )
b11000010001011101 .
b11000010001011101 2
b100111 (
1&
#80
0&
#81
b11110001001110000 %
b11110001001110000 *
b11110001001110000 /
b11110001001110000 3
b11000100110111110 $
b11000100110111110 )
b11000100110111110 .
b11000100110111110 2
b1111101110100100110010010000 "
b1111101110100100110010010000 1
b1110111011011010000101011011 0
b111010000100011000 !
b111010000100011000 7
b1111110111010 5
b11110000100010111 6
b11000010001011101 4
b110110000101011110 #
b110110000101011110 -
b11110000100010111 ,
b11000010001011101 +
b101000 (
1&
#82
0&
#83
b110110010101110100 #
b110110010101110100 -
b11110001001110000 ,
b11000100110111110 +
b111010010000010111 !
b111010010000010111 7
b1111011101001 5
b11110001001110000 6
b11000100110111110 4
b1110111011011010000101011011 "
b1110111011011010000101011011 1
b1101101001111111111100100000 0
b11110010001001010 %
b11110010001001010 *
b11110010001001010 /
b11110010001001010 3
b11001000100100110 $
b11001000100100110 )
b11001000100100110 .
b11001000100100110 2
b101001 (
1&
#84
0&
#85
b11110011010011101 %
b11110011010011101 *
b11110011010011101 /
b11110011010011101 3
b11001101001110011 $
b11001101001110011 )
b11001101001110011 .
b11001101001110011 2
b1101101001111111111100100000 "
b1101101001111111111100100000 1
b1011111111111100110011111100 0
b111010100010100111 !
b111010100010100111 7
b1110110010000 5
b11110010001001010 6
b11001000100100110 4
b110110110000101110 #
b110110110000101110 -
b11110010001001010 ,
b11001000100100110 +
b101010 (
1&
#86
0&
#87
b110111010101110000 #
b110111010101110000 -
b11110011010011101 ,
b11001101001110011 +
b111010111010110110 !
b111010111010110110 7
b1101110110110 5
b11110011010011101 6
b11001101001110011 4
b1011111111111100110011111100 "
b1011111111111100110011111100 1
b1010000100100000101010000111 0
b11110100101011111 %
b11110100101011111 *
b11110100101011111 /
b11110100101011111 3
b11010010101111110 $
b11010010101111110 )
b11010010101111110 .
b11010010101111110 2
b101011 (
1&
#88
0&
#89
b11110110010000101 %
b11110110010000101 *
b11110110010000101 /
b11110110010000101 3
b11011001000010100 $
b11011001000010100 )
b11011001000010100 .
b11011001000010100 2
b1010000100100000101010000111 "
b1010000100100000101010000111 1
b1000000000000001011111000010 0
b111011011000101001 !
b111011011000101001 7
b1100101100011 5
b11110100101011111 6
b11010010101111110 4
b111000000100010000 #
b111000000100010000 -
b11110100101011111 ,
b11010010101111110 +
b101100 (
1&
#90
0&
#91
b111000111011011101 #
b111000111011011101 -
b11110110010000101 ,
b11011001000010100 +
b111011111011100001 !
b111011111011100001 7
b1011010100001 5
b11110110010000101 6
b11011001000010100 4
b1000000000000001011111000010 "
b1000000000000001011111000010 1
b101111011011111010001100100 0
b11111000000000000 %
b11111000000000000 *
b11111000000000000 /
b11111000000000000 3
b11100000000000000 $
b11100000000000000 )
b11100000000000000 .
b11100000000000000 2
b101101 (
1&
#92
0&
#93
b11111001111000001 %
b11111001111000001 *
b11111001111000001 /
b11111001111000001 3
b11100111100000100 $
b11100111100000100 )
b11100111100000100 .
b11100111100000100 2
b101111011011111010001100100 "
b101111011011111010001100100 1
b100000000000000000000000000 0
b111100100010110101 !
b111100100010110101 7
b1001101111011 5
b11111000000000000 6
b11100000000000000 4
b111001111010011001 #
b111001111010011001 -
b11111000000000000 ,
b11100000000000000 +
b101110 (
1&
#94
0&
#95
b111011000000000000 #
b111011000000000000 -
b11111001111000001 ,
b11100111100000100 +
b111101001101111011 !
b111101001101111011 7
b1000000000000 5
b11111001111000001 6
b11100111100000100 4
b100000000000000000000000000 "
b100000000000000000000000000 1
b10010101111101111000000100 0
b11111011110111000 %
b11111011110111000 *
b11111011110111000 /
b11111011110111000 3
b11101111011011111 $
b11101111011011111 )
b11101111011011111 .
b11101111011011111 2
b101111 (
1&
#96
0&
#97
b11111101111010011 %
b11111101111010011 *
b11111101111010011 /
b11111101111010011 3
b11110111101001011 $
b11110111101001011 )
b11110111101001011 .
b11110111101001011 2
b10010101111101111000000100 "
b10010101111101111000000100 1
b1000100100101100101001000 0
b111101111100000100 !
b111101111100000100 7
b110000111111 5
b11111011110111000 6
b11101111011011111 4
b111100001011000101 #
b111100001011000101 -
b11111011110111000 ,
b11101111011011111 +
b110000 (
1&
#98
0&
#99
b111101011010010111 #
b111101011010010111 -
b11111101111010011 ,
b11110111101001011 +
b111110101100011110 !
b111110101100011110 7
b100001001000 5
b11111101111010011 6
b11110111101001011 4
b1000100100101100101001000 "
b1000100100101100101001000 1
b10001011100001111010001 0
b0 %
b0 *
b0 /
b0 3
b0 $
b0 )
b0 .
b0 2
b110001 (
1&
#100
0&
#101
b10000101101 %
b10000101101 *
b10000101101 /
b10000101101 3
b1000010110101 $
b1000010110101 )
b1000010110101 .
b1000010110101 2
b10001011100001111010001 "
b10001011100001111010001 1
b0 0
b111111011110010011 !
b111111011110010011 7
b10000101101 5
b0 6
b0 4
b111110101100011110 #
b111110101100011110 -
b0 ,
b0 +
b110010 (
1&
#102
0&
#103
b0 #
b0 -
b10000101101 ,
b1000010110101 +
b10000101101 !
b10000101101 7
b0 5
b10000101101 6
b1000010110101 4
b0 "
b0 1
b10001011100001111010001 0
b100001001000 %
b100001001000 *
b100001001000 /
b100001001000 3
b10000100100001 $
b10000100100001 )
b10000100100001 .
b10000100100001 2
b110011 (
1&
#104
0&
#105
b110000111111 %
b110000111111 *
b110000111111 /
b110000111111 3
b11000011111100 $
b11000011111100 )
b11000011111100 .
b11000011111100 2
b10001011100001111010001 "
b10001011100001111010001 1
b1000100100101100101001000 0
b1000010110101 !
b1000010110101 7
b11111101111010011 5
b100001001000 6
b10000100100001 4
b1010011100010 #
b1010011100010 -
b100001001000 ,
b10000100100001 +
b110100 (
1&
#106
0&
#107
b10100101101001 #
b10100101101001 -
b110000111111 ,
b11000011111100 +
b1110011110100 !
b1110011110100 7
b11111011110111000 5
b110000111111 6
b11000011111100 4
b1000100100101100101001000 "
b1000100100101100101001000 1
b10010101111101111000000100 0
b1000000000000 %
b1000000000000 *
b1000000000000 /
b1000000000000 3
b100000000000000 $
b100000000000000 )
b100000000000000 .
b100000000000000 2
b110101 (
1&
#108
0&
#109
b1001101111011 %
b1001101111011 *
b1001101111011 /
b1001101111011 3
b100110111101100 $
b100110111101100 )
b100110111101100 .
b100110111101100 2
b10010101111101111000000100 "
b10010101111101111000000100 1
b100000000000000000000000000 0
b10100010110100 !
b10100010110100 7
b11111001111000001 5
b1000000000000 6
b100000000000000 4
b11110100111011 #
b11110100111011 -
b1000000000000 ,
b100000000000000 +
b110110 (
1&
#110
0&
#111
b101000000000000 #
b101000000000000 -
b1001101111011 ,
b100110111101100 +
b11001111000001 !
b11001111000001 7
b11111000000000000 5
b1001101111011 6
b100110111101100 4
b100000000000000000000000000 "
b100000000000000000000000000 1
b101111011011111010001100100 0
b1011010100001 %
b1011010100001 *
b1011010100001 /
b1011010100001 3
b101101010000010 $
b101101010000010 )
b101101010000010 .
b101101010000010 2
b110111 (
1&
#112
0&
#113
b1100101100011 %
b1100101100011 *
b1100101100011 /
b1100101100011 3
b110010110001101 $
b110010110001101 )
b110010110001101 .
b110010110001101 2
b101111011011111010001100100 "
b101111011011111010001100100 1
b1000000000000001011111000010 0
b11110111101100 !
b11110111101100 7
b11110110010000101 5
b1011010100001 6
b101101010000010 4
b110000101100111 #
b110000101100111 -
b1011010100001 ,
b101101010000010 +
b111000 (
1&
#114
0&
#115
b111000100100011 #
b111000100100011 -
b1100101100011 ,
b110010110001101 +
b100011100000111 !
b100011100000111 7
b11110100101011111 5
b1100101100011 6
b110010110001101 4
b1000000000000001011111000010 "
b1000000000000001011111000010 1
b1010000100100000101010000111 0
b1101110110110 %
b1101110110110 *
b1101110110110 /
b1101110110110 3
b110111011011010 $
b110111011011010 )
b110111011011010 .
b110111011011010 2
b111001 (
1&
#116
0&
#117
b1110110010000 %
b1110110010000 *
b1110110010000 /
b1110110010000 3
b111011001000010 $
b111011001000010 )
b111011001000010 .
b111011001000010 2
b1010000100100000101010000111 "
b1010000100100000101010000111 1
b1011111111111100110011111100 0
b100111011101100 !
b100111011101100 7
b11110011010011101 5
b1101110110110 6
b110111011011010 4
b111111011110000 #
b111111011110000 -
b1101110110110 ,
b110111011011010 +
b111010 (
1&
#118
0&
#119
b1000101010010000 #
b1000101010010000 -
b1110110010000 ,
b111011001000010 +
b101010101110111 !
b101010101110111 7
b11110010001001010 5
b1110110010000 6
b111011001000010 4
b1011111111111100110011111100 "
b1011111111111100110011111100 1
b1101101001111111111100100000 0
b1111011101001 %
b1111011101001 *
b1111011101001 /
b1111011101001 3
b111101110100011 $
b111101110100011 )
b111101110100011 .
b111101110100011 2
b111011 (
1&
#120
0&
